untitled:Untitled-4
    0 aload_0
    1 getfield #19 <g/bh Lh;>
    4 pop
    5 getstatic #423 <h/cz Z>
    8 ifeq 43 (+35)
   11 invokestatic #424 <java/lang/System/currentTimeMillis()J>
   14 lstore_1
   15 lload_1
   16 aload_0
   17 getfield #134 <g/lN J>
   20 lsub
   21 ldc2_w #425 <60000>
   24 lcmp
   25 iflt 43 (+18)
   28 aload_0
   29 lload_1
   30 putfield #134 <g/lN J>
   33 aload_0
   34 getfield #19 <g/bh Lh;>
   37 getfield #427 <h/aG Lq;>
   40 invokevirtual #428 <q/new()V>
   43 aload_0
   44 getfield #19 <g/bh Lh;>
   47 getfield #429 <h/fK Z>
   50 ifeq 270 (+220)
   53 aload_0
   54 getfield #19 <g/bh Lh;>
   57 getfield #320 <h/fj Ljavax/microedition/lcdui/Graphics;>
   60 iconst_0
   61 invokevirtual #322 <javax/microedition/lcdui/Graphics/setColor(I)V>
   64 aload_0
   65 getfield #19 <g/bh Lh;>
   68 getfield #320 <h/fj Ljavax/microedition/lcdui/Graphics;>
   71 iconst_0
   72 iconst_0
   73 aload_0
   74 getfield #19 <g/bh Lh;>
   77 pop
   78 getstatic #319 <h/dU S>
   81 aload_0
   82 getfield #19 <g/bh Lh;>
   85 pop
   86 getstatic #20 <h/fp S>
   89 invokevirtual #411 <javax/microedition/lcdui/Graphics/fillRect(IIII)V>
   92 aload_0
   93 getfield #19 <g/bh Lh;>
   96 getfield #320 <h/fj Ljavax/microedition/lcdui/Graphics;>
   99 aload_0
  100 getfield #19 <g/bh Lh;>
  103 pop
  104 getstatic #321 <h/b2 [[I>
  107 aload_0
  108 getfield #19 <g/bh Lh;>
  111 pop
  112 iconst_5
  113 aaload
  114 iconst_0
  115 iaload
  116 invokevirtual #322 <javax/microedition/lcdui/Graphics/setColor(I)V>
  119 aload_0
  120 getfield #19 <g/bh Lh;>
  123 getfield #320 <h/fj Ljavax/microedition/lcdui/Graphics;>
  126 new #401 <java/lang/StringBuffer>
  129 dup
  130 invokespecial #402 <java/lang/StringBuffer/<init>()V>
  133 aload_0
  134 getfield #19 <g/bh Lh;>
  137 getfield #430 <h/dp B>
  140 ifne 149 (+9)
  143 ldc_w #431 <>>>
  146 goto 151 (+5)
  149 ldc #5
  151 invokevirtual #404 <java/lang/StringBuffer/append(Ljava/lang/String;)Ljava/lang/StringBuffer;>
  154 ldc_w #432 <暂停游戏>
  157 invokevirtual #404 <java/lang/StringBuffer/append(Ljava/lang/String;)Ljava/lang/StringBuffer;>
  160 aload_0
  161 getfield #19 <g/bh Lh;>
  164 getfield #430 <h/dp B>
  167 ifne 176 (+9)
  170 ldc_w #433 <<<>
  173 goto 178 (+5)
  176 ldc #5
  178 invokevirtual #404 <java/lang/StringBuffer/append(Ljava/lang/String;)Ljava/lang/StringBuffer;>
  181 invokevirtual #405 <java/lang/StringBuffer/toString()Ljava/lang/String;>
  184 bipush 50
  186 bipush 20
  188 bipush 17
  190 invokevirtual #390 <javax/microedition/lcdui/Graphics/drawString(Ljava/lang/String;III)V>
  193 aload_0
  194 getfield #19 <g/bh Lh;>
  197 getfield #320 <h/fj Ljavax/microedition/lcdui/Graphics;>
  200 new #401 <java/lang/StringBuffer>
  203 dup
  204 invokespecial #402 <java/lang/StringBuffer/<init>()V>
  207 aload_0
  208 getfield #19 <g/bh Lh;>
  211 getfield #430 <h/dp B>
  214 iconst_1
  215 if_icmpne 224 (+9)
  218 ldc_w #431 <>>>
  221 goto 226 (+5)
  224 ldc #5
  226 invokevirtual #404 <java/lang/StringBuffer/append(Ljava/lang/String;)Ljava/lang/StringBuffer;>
  229 ldc_w #434 <继续游戏>
  232 invokevirtual #404 <java/lang/StringBuffer/append(Ljava/lang/String;)Ljava/lang/StringBuffer;>
  235 aload_0
  236 getfield #19 <g/bh Lh;>
  239 getfield #430 <h/dp B>
  242 iconst_1
  243 if_icmpne 252 (+9)
  246 ldc_w #433 <<<>
  249 goto 254 (+5)
  252 ldc #5
  254 invokevirtual #404 <java/lang/StringBuffer/append(Ljava/lang/String;)Ljava/lang/StringBuffer;>
  257 invokevirtual #405 <java/lang/StringBuffer/toString()Ljava/lang/String;>
  260 bipush 50
  262 bipush 45
  264 bipush 17
  266 invokevirtual #390 <javax/microedition/lcdui/Graphics/drawString(Ljava/lang/String;III)V>
  269 return
  270 aload_0
  271 getfield #19 <g/bh Lh;>
  274 pop
  275 getstatic #435 <h/fZ [[I>
  278 ifnull 325 (+47)
  281 iconst_0
  282 istore_1
  283 iload_1
  284 aload_0
  285 getfield #19 <g/bh Lh;>
  288 pop
  289 getstatic #435 <h/fZ [[I>
  292 arraylength
  293 if_icmpge 325 (+32)
  296 aload_0
  297 getfield #19 <g/bh Lh;>
  300 pop
  301 getstatic #436 <h/a5 Lx;>
  304 aload_0
  305 getfield #19 <g/bh Lh;>
  308 pop
  309 getstatic #435 <h/fZ [[I>
  312 iload_1
  313 aaload
  314 invokevirtual #362 <x/a([I)V>
  317 iload_1
  318 iconst_1
  319 iadd
  320 i2b
  321 istore_1
  322 goto 283 (-39)
  325 aload_0
  326 getfield #19 <g/bh Lh;>
  329 iconst_0
  330 putfield #429 <h/fK Z>
  333 aload_0
  334 dup
  335 getfield #437 <g/kp I>
  338 iconst_1
  339 iadd
  340 putfield #437 <g/kp I>
  343 aload_0
  344 getfield #19 <g/bh Lh;>
  347 getfield #250 <h/cZ Lag;>
  350 getfield #438 <ag/he Z>
  353 ifeq 389 (+36)
  356 aload_0
  357 getfield #19 <g/bh Lh;>
  360 getfield #250 <h/cZ Lag;>
  363 getfield #439 <ag/ii S>
  366 sipush 2000
  369 if_icmpge 389 (+20)
  372 aload_0
  373 getfield #19 <g/bh Lh;>
  376 getfield #250 <h/cZ Lag;>
  379 dup
  380 getfield #439 <ag/ii S>
  383 iconst_1
  384 iadd
  385 i2s
  386 putfield #439 <ag/ii S>
  389 aload_0
  390 getfield #19 <g/bh Lh;>
  393 getfield #250 <h/cZ Lag;>
  396 getfield #440 <a3/a8 Z>
  399 ifne 553 (+154)
  402 aload_0
  403 getfield #297 <ap/do S>
  406 iconst_1
  407 if_icmpeq 499 (+92)
  410 aload_0
  411 getfield #297 <ap/do S>
  414 iconst_2
  415 if_icmpeq 499 (+84)
  418 aload_0
  419 getfield #297 <ap/do S>
  422 bipush 26
  424 if_icmpeq 499 (+75)
  427 aload_0
  428 getfield #297 <ap/do S>
  431 bipush 27
  433 if_icmpeq 499 (+66)
  436 aload_0
  437 getfield #297 <ap/do S>
  440 bipush 74
  442 if_icmpeq 499 (+57)
  445 aload_0
  446 getfield #297 <ap/do S>
  449 bipush 15
  451 if_icmpeq 499 (+48)
  454 aload_0
  455 getfield #297 <ap/do S>
  458 bipush 93
  460 if_icmpeq 499 (+39)
  463 aload_0
  464 getfield #297 <ap/do S>
  467 bipush 29
  469 if_icmpeq 499 (+30)
  472 aload_0
  473 getfield #297 <ap/do S>
  476 bipush 13
  478 if_icmpeq 499 (+21)
  481 aload_0
  482 getfield #297 <ap/do S>
  485 bipush 109
  487 if_icmpeq 499 (+12)
  490 aload_0
  491 getfield #297 <ap/do S>
  494 bipush 50
  496 if_icmpne 553 (+57)
  499 aload_0
  500 getfield #19 <g/bh Lh;>
  503 getfield #270 <h/fG LSFMIDlet;>
  506 invokestatic #271 <javax/microedition/lcdui/Display/getDisplay(Ljavax/microedition/midlet/MIDlet;)Ljavax/microedition/lcdui/Display;>
  509 invokevirtual #441 <javax/microedition/lcdui/Display/getCurrent()Ljavax/microedition/lcdui/Displayable;>
  512 aload_0
  513 getfield #19 <g/bh Lh;>
  516 if_acmpne 553 (+37)
  519 aload_0
  520 dup
  521 getfield #442 <g/g1 S>
  524 iconst_1
  525 iadd
  526 i2s
  527 putfield #442 <g/g1 S>
  530 aload_0
  531 getfield #442 <g/g1 S>
  534 sipush 2000
  537 if_icmple 558 (+21)
  540 aload_0
  541 getfield #19 <g/bh Lh;>
  544 getfield #259 <h/i Lah;>
  547 invokevirtual #443 <ah/case()V>
  550 goto 558 (+8)
  553 aload_0
  554 iconst_0
  555 putfield #442 <g/g1 S>
  558 aload_0
  559 getfield #19 <g/bh Lh;>
  562 invokevirtual #444 <h/r()V>
  565 aload_0
  566 getfield #297 <ap/do S>
  569 iconst_5
  570 if_icmpeq 756 (+186)
  573 aload_0
  574 getfield #19 <g/bh Lh;>
  577 invokevirtual #445 <h/w()Z>
  580 ifeq 756 (+176)
  583 aload_0
  584 getfield #19 <g/bh Lh;>
  587 invokevirtual #446 <h/I()Z>
  590 ifeq 635 (+45)
  593 aload_0
  594 getfield #9 <g/int I>
  597 iconst_5
  598 bipush 6
  600 invokestatic #447 <h/if(II)I>
  603 irem
  604 ifne 635 (+31)
  607 aload_0
  608 getfield #19 <g/bh Lh;>
  611 pop
  612 getstatic #448 <h/co [Ljava/lang/String;>
  615 dup
  616 astore_1
  617 monitorenter
  618 aload_0
  619 getfield #19 <g/bh Lh;>
  622 invokevirtual #449 <h/d()V>
  625 aload_1
  626 monitorexit
  627 goto 635 (+8)
  630 astore_3
  631 aload_1
  632 monitorexit
  633 aload_3
  634 athrow
  635 aload_0
  636 getfield #19 <g/bh Lh;>
  639 invokevirtual #450 <h/goto()Z>
  642 ifeq 756 (+114)
  645 aload_0
  646 getfield #9 <g/int I>
  649 iconst_5
  650 bipush 6
  652 invokestatic #447 <h/if(II)I>
  655 irem
  656 ifne 756 (+100)
  659 aload_0
  660 getfield #19 <g/bh Lh;>
  663 pop
  664 getstatic #451 <h/bG [Ljava/lang/String;>
  667 dup
  668 astore_1
  669 monitorenter
  670 aload_0
  671 getfield #19 <g/bh Lh;>
  674 aload_0
  675 getfield #19 <g/bh Lh;>
  678 pop
  679 getstatic #451 <h/bG [Ljava/lang/String;>
  682 iconst_0
  683 aaload
  684 aload_0
  685 getfield #19 <g/bh Lh;>
  688 pop
  689 getstatic #452 <h/ds [S>
  692 iconst_0
  693 saload
  694 aload_0
  695 getfield #19 <g/bh Lh;>
  698 pop
  699 getstatic #453 <h/ej [B>
  702 iconst_0
  703 baload
  704 aload_0
  705 getfield #19 <g/bh Lh;>
  708 pop
  709 getstatic #454 <h/cy [B>
  712 iconst_0
  713 baload
  714 aload_0
  715 getfield #19 <g/bh Lh;>
  718 pop
  719 getstatic #455 <h/ec [S>
  722 iconst_0
  723 saload
  724 aload_0
  725 getfield #19 <g/bh Lh;>
  728 pop
  729 getstatic #456 <h/aa [B>
  732 iconst_0
  733 baload
  734 invokevirtual #457 <h/if(Ljava/lang/String;SBBSB)V>
  737 aload_1
  738 monitorexit
  739 goto 749 (+10)
  742 astore 4
  744 aload_1
  745 monitorexit
  746 aload 4
  748 athrow
  749 aload_0
  750 getfield #19 <g/bh Lh;>
  753 invokevirtual #458 <h/int()V>
  756 aload_0
  757 getfield #19 <g/bh Lh;>
  760 getfield #250 <h/cZ Lag;>
  763 getfield #289 <a3/a4 B>
  766 bipush 10
  768 if_icmpne 818 (+50)
  771 aload_0
  772 getfield #459 <g/ki Z>
  775 ifne 818 (+43)
  778 getstatic #460 <g/dD B>
  781 iconst_1
  782 if_icmpeq 792 (+10)
  785 getstatic #460 <g/dD B>
  788 iconst_4
  789 if_icmpne 818 (+29)
  792 getstatic #316 <g/dZ B>
  795 ifne 818 (+23)
  798 aload_0
  799 getfield #9 <g/int I>
  802 bipush 10
  804 irem
  805 ifne 818 (+13)
  808 aload_0
  809 getfield #19 <g/bh Lh;>
  812 getfield #250 <h/cZ Lag;>
  815 invokevirtual #461 <ag/A()V>
  818 aload_0
  819 getfield #19 <g/bh Lh;>
  822 getfield #462 <h/S Las;>
  825 getfield #463 <as/ad Z>
  828 ifeq 1129 (+301)
  831 aload_0
  832 getfield #19 <g/bh Lh;>
  835 getfield #250 <h/cZ Lag;>
  838 pop
  839 getstatic #324 <ag/hF S>
  842 iconst_2
  843 aload_0
  844 getfield #9 <g/int I>
  847 iconst_2
  848 irem
  849 ifne 856 (+7)
  852 iconst_m1
  853 goto 857 (+4)
  856 iconst_1
  857 imul
  858 iadd
  859 i2s
  860 putstatic #324 <ag/hF S>
  863 aload_0
  864 getfield #19 <g/bh Lh;>
  867 getfield #250 <h/cZ Lag;>
  870 pop
  871 getstatic #325 <ag/hE S>
  874 iconst_3
  875 aload_0
  876 getfield #9 <g/int I>
  879 iconst_2
  880 irem
  881 ifne 902 (+21)
  884 aload_0
  885 getfield #9 <g/int I>
  888 iconst_5
  889 irem
  890 iconst_3
  891 if_icmpge 898 (+7)
  894 iconst_1
  895 goto 917 (+22)
  898 iconst_m1
  899 goto 917 (+18)
  902 aload_0
  903 getfield #9 <g/int I>
  906 iconst_5
  907 irem
  908 iconst_3
  909 if_icmpge 916 (+7)
  912 iconst_m1
  913 goto 917 (+4)
  916 iconst_1
  917 imul
  918 iadd
  919 i2s
  920 putstatic #325 <ag/hE S>
  923 aload_0
  924 getfield #19 <g/bh Lh;>
  927 getfield #250 <h/cZ Lag;>
  930 pop
  931 getstatic #324 <ag/hF S>
  934 ifge 952 (+18)
  937 aload_0
  938 getfield #19 <g/bh Lh;>
  941 getfield #250 <h/cZ Lag;>
  944 pop
  945 iconst_0
  946 putstatic #324 <ag/hF S>
  949 goto 1026 (+77)
  952 aload_0
  953 getfield #19 <g/bh Lh;>
  956 getfield #250 <h/cZ Lag;>
  959 pop
  960 getstatic #324 <ag/hF S>
  963 getstatic #319 <h/dU S>
  966 iadd
  967 aload_0
  968 getfield #19 <g/bh Lh;>
  971 getfield #464 <h/ad S>
  974 if_icmplt 1026 (+52)
  977 aload_0
  978 getfield #19 <g/bh Lh;>
  981 getfield #250 <h/cZ Lag;>
  984 pop
  985 aload_0
  986 getfield #19 <g/bh Lh;>
  989 getfield #464 <h/ad S>
  992 getstatic #319 <h/dU S>
  995 isub
  996 i2s
  997 putstatic #324 <ag/hF S>
 1000 aload_0
 1001 getfield #19 <g/bh Lh;>
 1004 getfield #250 <h/cZ Lag;>
 1007 pop
 1008 getstatic #324 <ag/hF S>
 1011 ifge 1026 (+15)
 1014 aload_0
 1015 getfield #19 <g/bh Lh;>
 1018 getfield #250 <h/cZ Lag;>
 1021 pop
 1022 iconst_0
 1023 putstatic #324 <ag/hF S>
 1026 aload_0
 1027 getfield #19 <g/bh Lh;>
 1030 getfield #250 <h/cZ Lag;>
 1033 pop
 1034 getstatic #325 <ag/hE S>
 1037 ifge 1055 (+18)
 1040 aload_0
 1041 getfield #19 <g/bh Lh;>
 1044 getfield #250 <h/cZ Lag;>
 1047 pop
 1048 iconst_0
 1049 putstatic #325 <ag/hE S>
 1052 goto 1129 (+77)
 1055 aload_0
 1056 getfield #19 <g/bh Lh;>
 1059 getfield #250 <h/cZ Lag;>
 1062 pop
 1063 getstatic #325 <ag/hE S>
 1066 getstatic #20 <h/fp S>
 1069 iadd
 1070 aload_0
 1071 getfield #19 <g/bh Lh;>
 1074 getfield #465 <h/dz S>
 1077 if_icmple 1129 (+52)
 1080 aload_0
 1081 getfield #19 <g/bh Lh;>
 1084 getfield #250 <h/cZ Lag;>
 1087 pop
 1088 aload_0
 1089 getfield #19 <g/bh Lh;>
 1092 getfield #465 <h/dz S>
 1095 getstatic #20 <h/fp S>
 1098 isub
 1099 i2s
 1100 putstatic #325 <ag/hE S>
 1103 aload_0
 1104 getfield #19 <g/bh Lh;>
 1107 getfield #250 <h/cZ Lag;>
 1110 pop
 1111 getstatic #325 <ag/hE S>
 1114 ifge 1129 (+15)
 1117 aload_0
 1118 getfield #19 <g/bh Lh;>
 1121 getfield #250 <h/cZ Lag;>
 1124 pop
 1125 iconst_0
 1126 putstatic #325 <ag/hE S>
 1129 aload_0
 1130 dup
 1131 getfield #9 <g/int I>
 1134 iconst_1
 1135 iadd
 1136 dup_x1
 1137 putfield #9 <g/int I>
 1140 ldc_w #466 <2147483647>
 1143 if_icmpne 1151 (+8)
 1146 aload_0
 1147 iconst_0
 1148 putfield #9 <g/int I>
 1151 aload_0
 1152 getfield #297 <ap/do S>
 1155 tableswitch -125 to 127
             -125:  3192 (+2037)
             -124:  3263 (+2108)
             -123:  6585 (+5430)
             -122:  6824 (+5669)
             -121:  6824 (+5669)
             -120:  6793 (+5638)
             -119:  11999 (+10844)
             -118:  11999 (+10844)
             -117:  11999 (+10844)
             -116:  11999 (+10844)
             -115:  11999 (+10844)
             -114:  11999 (+10844)
             -113:  11999 (+10844)
             -112:  11999 (+10844)
             -111:  11999 (+10844)
             -110:  11999 (+10844)
             -109:  6763 (+5608)
             -108:  6733 (+5578)
             -107:  6657 (+5502)
             -106:  6555 (+5400)
             -105:  6531 (+5376)
             -104:  3399 (+2244)
             -103:  6985 (+5830)
             -102:  3991 (+2836)
             -101:  3641 (+2486)
             -100:  3684 (+2529)
             -99:  3684 (+2529)
             -98:  3684 (+2529)
             -97:  3684 (+2529)
             -96:  3684 (+2529)
             -95:  3684 (+2529)
             -94:  3796 (+2641)
             -93:  3707 (+2552)
             -92:  3694 (+2539)
             -91:  11999 (+10844)
             -90:  3707 (+2552)
             -89:  11999 (+10844)
             -88:  3707 (+2552)
             -87:  3707 (+2552)
             -86:  3816 (+2661)
             -85:  3720 (+2565)
             -84:  3925 (+2770)
             -83:  4661 (+3506)
             -82:  7046 (+5891)
             -81:  7019 (+5864)
             -80:  7070 (+5915)
             -79:  7121 (+5966)
             -78:  7105 (+5950)
             -77:  7121 (+5966)
             -76:  7145 (+5990)
             -75:  3836 (+2681)
             -74:  3855 (+2700)
             -73:  3925 (+2770)
             -72:  6064 (+4909)
             -71:  3892 (+2737)
             -70:  6340 (+5185)
             -69:  4004 (+2849)
             -68:  4004 (+2849)
             -67:  4004 (+2849)
             -66:  4004 (+2849)
             -65:  4004 (+2849)
             -64:  11999 (+10844)
             -63:  4004 (+2849)
             -62:  4004 (+2849)
             -61:  4004 (+2849)
             -60:  4004 (+2849)
             -59:  4004 (+2849)
             -58:  4004 (+2849)
             -57:  4004 (+2849)
             -56:  4004 (+2849)
             -55:  4004 (+2849)
             -54:  4004 (+2849)
             -53:  4004 (+2849)
             -52:  4004 (+2849)
             -51:  3879 (+2724)
             -50:  4128 (+2973)
             -49:  11999 (+10844)
             -48:  3944 (+2789)
             -47:  3905 (+2750)
             -46:  6353 (+5198)
             -45:  4128 (+2973)
             -44:  3915 (+2760)
             -43:  3915 (+2760)
             -42:  3915 (+2760)
             -41:  3925 (+2770)
             -40:  3915 (+2760)
             -39:  3963 (+2808)
             -38:  3991 (+2836)
             -37:  3991 (+2836)
             -36:  3991 (+2836)
             -35:  4004 (+2849)
             -34:  4004 (+2849)
             -33:  9324 (+8169)
             -32:  11999 (+10844)
             -31:  11999 (+10844)
             -30:  4283 (+3128)
             -29:  3053 (+1898)
             -28:  11999 (+10844)
             -27:  7238 (+6083)
             -26:  4240 (+3085)
             -25:  4240 (+3085)
             -24:  4240 (+3085)
             -23:  4201 (+3046)
             -22:  4214 (+3059)
             -21:  4227 (+3072)
             -20:  4240 (+3085)
             -19:  2214 (+1059)
             -18:  2252 (+1097)
             -17:  11999 (+10844)
             -16:  2180 (+1025)
             -15:  11999 (+10844)
             -14:  4240 (+3085)
             -13:  2729 (+1574)
             -12:  7251 (+6096)
             -11:  10111 (+8956)
             -10:  4240 (+3085)
             -9:  4266 (+3111)
             -8:  6875 (+5720)
             -7:  6915 (+5760)
             -6:  4802 (+3647)
             -5:  4884 (+3729)
             -4:  4941 (+3786)
             -3:  5008 (+3853)
             -2:  5042 (+3887)
             -1:  5076 (+3921)
             0:  10801 (+9646)
             1:  11791 (+10636)
             2:  11854 (+10699)
             3:  6489 (+5334)
             4:  10798 (+9643)
             5:  10242 (+9087)
             6:  7145 (+5990)
             7:  2897 (+1742)
             8:  7121 (+5966)
             9:  7105 (+5950)
             10:  7070 (+5915)
             11:  5447 (+4292)
             12:  4661 (+3506)
             13:  10158 (+9003)
             14:  11999 (+10844)
             15:  10101 (+8946)
             16:  11999 (+10844)
             17:  11999 (+10844)
             18:  4128 (+2973)
             19:  10002 (+8847)
             20:  9992 (+8837)
             21:  6859 (+5704)
             22:  6440 (+5285)
             23:  11999 (+10844)
             24:  11999 (+10844)
             25:  10125 (+8970)
             26:  6283 (+5128)
             27:  6150 (+4995)
             28:  11999 (+10844)
             29:  11999 (+10844)
             30:  6051 (+4896)
             31:  6051 (+4896)
             32:  6051 (+4896)
             33:  6051 (+4896)
             34:  3142 (+1987)
             35:  11999 (+10844)
             36:  9697 (+8542)
             37:  9713 (+8558)
             38:  9888 (+8733)
             39:  4084 (+2929)
             40:  4014 (+2859)
             41:  9592 (+8437)
             42:  6018 (+4863)
             43:  9360 (+8205)
             44:  9347 (+8192)
             45:  6051 (+4896)
             46:  7019 (+5864)
             47:  4266 (+3111)
             48:  4266 (+3111)
             49:  4266 (+3111)
             50:  9337 (+8182)
             51:  7046 (+5891)
             52:  11999 (+10844)
             53:  6227 (+5072)
             54:  4266 (+3111)
             55:  2917 (+1762)
             56:  11720 (+10565)
             57:  8844 (+7689)
             58:  8751 (+7596)
             59:  3004 (+1849)
             60:  2653 (+1498)
             61:  8173 (+7018)
             62:  7758 (+6603)
             63:  8789 (+7634)
             64:  9438 (+8283)
             65:  3575 (+2420)
             66:  4266 (+3111)
             67:  5447 (+4292)
             68:  4253 (+3098)
             69:  11999 (+10844)
             70:  7577 (+6422)
             71:  7251 (+6096)
             72:  7121 (+5966)
             73:  7542 (+6387)
             74:  6140 (+4985)
             75:  6077 (+4922)
             76:  7468 (+6313)
             77:  7505 (+6350)
             78:  2282 (+1127)
             79:  8298 (+7143)
             80:  9311 (+8156)
             81:  5447 (+4292)
             82:  7251 (+6096)
             83:  7251 (+6096)
             84:  4253 (+3098)
             85:  4253 (+3098)
             86:  4750 (+3595)
             87:  11999 (+10844)
             88:  5447 (+4292)
             89:  7428 (+6273)
             90:  11999 (+10844)
             91:  4792 (+3637)
             92:  5300 (+4145)
             93:  7382 (+6227)
             94:  7342 (+6187)
             95:  7238 (+6083)
             96:  7238 (+6083)
             97:  7238 (+6083)
             98:  7180 (+6025)
             99:  7264 (+6109)
             100:  5447 (+4292)
             101:  5210 (+4055)
             102:  7251 (+6096)
             103:  6872 (+5717)
             104:  11999 (+10844)
             105:  11999 (+10844)
             106:  6982 (+5827)
             107:  2837 (+1682)
             108:  6959 (+5804)
             109:  6972 (+5817)
             110:  6928 (+5773)
             111:  7238 (+6083)
             112:  7238 (+6083)
             113:  5981 (+4826)
             114:  5968 (+4813)
             115:  5769 (+4614)
             116:  5460 (+4305)
             117:  11999 (+10844)
             118:  6363 (+5208)
             119:  5147 (+3992)
             120:  5123 (+3968)
             121:  5096 (+3941)
             122:  11578 (+10423)
             123:  10111 (+8956)
             124:  5769 (+4614)
             125:  6489 (+5334)
             126:  4266 (+3111)
             127:  11649 (+10494)
             default:  11999 (+10844)
 2180 aload_0
 2181 invokevirtual #467 <g/E()V>
 2184 aload_0
 2185 ldc_w #468 <确认提交宠物?>
 2188 ldc_w #469 <是>
 2191 ldc_w #470 <否>
 2194 invokevirtual #471 <g/a(Ljava/lang/String;Ljava/lang/String;Ljava/lang/String;)V>
 2197 aload_0
 2198 getfield #19 <g/bh Lh;>
 2201 invokevirtual #472 <h/x()V>
 2204 aload_0
 2205 getfield #19 <g/bh Lh;>
 2208 invokevirtual #473 <h/c()V>
 2211 goto 11999 (+9788)
 2214 aload_0
 2215 invokevirtual #467 <g/E()V>
 2218 aload_0
 2219 getfield #19 <g/bh Lh;>
 2222 aload_0
 2223 getfield #474 <g/lr Ljava/lang/String;>
 2226 getstatic #296 <g/gf B>
 2229 iconst_4
 2230 iconst_0
 2231 invokevirtual #416 <h/a(Ljava/lang/String;IBZ)Z>
 2234 pop
 2235 aload_0
 2236 getfield #19 <g/bh Lh;>
 2239 invokevirtual #472 <h/x()V>
 2242 aload_0
 2243 getfield #19 <g/bh Lh;>
 2246 invokevirtual #473 <h/c()V>
 2249 goto 11999 (+9750)
 2252 aload_0
 2253 invokevirtual #467 <g/E()V>
 2256 aload_0
 2257 aload_0
 2258 getfield #40 <g/ip Ljava/util/Vector;>
 2261 iconst_1
 2262 invokevirtual #475 <g/a(Ljava/util/Vector;Z)V>
 2265 aload_0
 2266 getfield #19 <g/bh Lh;>
 2269 invokevirtual #472 <h/x()V>
 2272 aload_0
 2273 getfield #19 <g/bh Lh;>
 2276 invokevirtual #473 <h/c()V>
 2279 goto 11999 (+9720)
 2282 aload_0
 2283 getfield #19 <g/bh Lh;>
 2286 getfield #250 <h/cZ Lag;>
 2289 getfield #476 <ag/gj B>
 2292 tableswitch 1 to 4
             1:  2324 (+32)
             2:  2650 (+358)
             3:  2427 (+135)
             4:  2530 (+238)
             default:  2650 (+358)
 2324 aload_0
 2325 invokevirtual #467 <g/E()V>
 2328 aload_0
 2329 getfield #19 <g/bh Lh;>
 2332 new #401 <java/lang/StringBuffer>
 2335 dup
 2336 invokespecial #402 <java/lang/StringBuffer/<init>()V>
 2339 ldc_w #477 <输入>
 2342 invokevirtual #404 <java/lang/StringBuffer/append(Ljava/lang/String;)Ljava/lang/StringBuffer;>
 2345 aload_0
 2346 getfield #19 <g/bh Lh;>
 2349 getfield #250 <h/cZ Lag;>
 2352 getfield #478 <ag/dN B>
 2355 ifne 2364 (+9)
 2358 ldc_w #479 <买1手金>
 2361 goto 2367 (+6)
 2364 ldc_w #480 <卖1手金>
 2367 invokevirtual #404 <java/lang/StringBuffer/append(Ljava/lang/String;)Ljava/lang/StringBuffer;>
 2370 ldc_w #481 <的单价(1手金=100星币).>
 2373 invokevirtual #404 <java/lang/StringBuffer/append(Ljava/lang/String;)Ljava/lang/StringBuffer;>
 2376 invokevirtual #405 <java/lang/StringBuffer/toString()Ljava/lang/String;>
 2379 iconst_m1
 2380 iconst_4
 2381 iconst_0
 2382 invokevirtual #416 <h/a(Ljava/lang/String;IBZ)Z>
 2385 pop
 2386 aload_0
 2387 getfield #19 <g/bh Lh;>
 2390 getfield #250 <h/cZ Lag;>
 2393 getfield #476 <ag/gj B>
 2396 iconst_1
 2397 if_icmpne 2410 (+13)
 2400 aload_0
 2401 getfield #19 <g/bh Lh;>
 2404 getfield #482 <h/d9 Lw;>
 2407 invokevirtual #483 <w/a()V>
 2410 aload_0
 2411 getfield #19 <g/bh Lh;>
 2414 invokevirtual #472 <h/x()V>
 2417 aload_0
 2418 getfield #19 <g/bh Lh;>
 2421 invokevirtual #473 <h/c()V>
 2424 goto 2650 (+226)
 2427 aload_0
 2428 invokevirtual #467 <g/E()V>
 2431 aload_0
 2432 getfield #19 <g/bh Lh;>
 2435 new #401 <java/lang/StringBuffer>
 2438 dup
 2439 invokespecial #402 <java/lang/StringBuffer/<init>()V>
 2442 ldc_w #477 <输入>
 2445 invokevirtual #404 <java/lang/StringBuffer/append(Ljava/lang/String;)Ljava/lang/StringBuffer;>
 2448 aload_0
 2449 getfield #19 <g/bh Lh;>
 2452 getfield #250 <h/cZ Lag;>
 2455 getfield #478 <ag/dN B>
 2458 ifne 2467 (+9)
 2461 ldc_w #479 <买1手金>
 2464 goto 2470 (+6)
 2467 ldc_w #480 <卖1手金>
 2470 invokevirtual #404 <java/lang/StringBuffer/append(Ljava/lang/String;)Ljava/lang/StringBuffer;>
 2473 ldc_w #484 <的数量(1手金=100星币).>
 2476 invokevirtual #404 <java/lang/StringBuffer/append(Ljava/lang/String;)Ljava/lang/StringBuffer;>
 2479 invokevirtual #405 <java/lang/StringBuffer/toString()Ljava/lang/String;>
 2482 iconst_m1
 2483 iconst_4
 2484 iconst_0
 2485 invokevirtual #416 <h/a(Ljava/lang/String;IBZ)Z>
 2488 pop
 2489 aload_0
 2490 getfield #19 <g/bh Lh;>
 2493 getfield #250 <h/cZ Lag;>
 2496 getfield #476 <ag/gj B>
 2499 iconst_3
 2500 if_icmpne 2513 (+13)
 2503 aload_0
 2504 getfield #19 <g/bh Lh;>
 2507 getfield #482 <h/d9 Lw;>
 2510 invokevirtual #483 <w/a()V>
 2513 aload_0
 2514 getfield #19 <g/bh Lh;>
 2517 invokevirtual #472 <h/x()V>
 2520 aload_0
 2521 getfield #19 <g/bh Lh;>
 2524 invokevirtual #473 <h/c()V>
 2527 goto 2650 (+123)
 2530 aload_0
 2531 invokevirtual #467 <g/E()V>
 2534 aload_0
 2535 getfield #19 <g/bh Lh;>
 2538 new #401 <java/lang/StringBuffer>
 2541 dup
 2542 invokespecial #402 <java/lang/StringBuffer/<init>()V>
 2545 ldc_w #485 <您的交易信息为:>
 2548 invokevirtual #404 <java/lang/StringBuffer/append(Ljava/lang/String;)Ljava/lang/StringBuffer;>
 2551 aload_0
 2552 getfield #19 <g/bh Lh;>
 2555 getfield #250 <h/cZ Lag;>
 2558 getfield #478 <ag/dN B>
 2561 ifne 2569 (+8)
 2564 ldc #62 <买>
 2566 goto 2571 (+5)
 2569 ldc #63 <卖>
 2571 invokevirtual #404 <java/lang/StringBuffer/append(Ljava/lang/String;)Ljava/lang/StringBuffer;>
 2574 aload_0
 2575 getfield #19 <g/bh Lh;>
 2578 getfield #250 <h/cZ Lag;>
 2581 getfield #486 <ag/dP I>
 2584 getstatic #487 <a/C I>
 2587 invokestatic #488 <a3/do(II)I>
 2590 invokevirtual #489 <java/lang/StringBuffer/append(I)Ljava/lang/StringBuffer;>
 2593 ldc_w #490 <手金,单价>
 2596 invokevirtual #404 <java/lang/StringBuffer/append(Ljava/lang/String;)Ljava/lang/StringBuffer;>
 2599 aload_0
 2600 getfield #19 <g/bh Lh;>
 2603 getfield #250 <h/cZ Lag;>
 2606 getfield #491 <ag/gF I>
 2609 getstatic #487 <a/C I>
 2612 invokestatic #488 <a3/do(II)I>
 2615 invokevirtual #489 <java/lang/StringBuffer/append(I)Ljava/lang/StringBuffer;>
 2618 ldc_w #492 <游戏币.是否缴纳押金10星币提交交易请求? (交易不限时长,在线有效)成交则押金不予退还,撤单将扣除2星币平台使用费.>
 2621 invokevirtual #404 <java/lang/StringBuffer/append(Ljava/lang/String;)Ljava/lang/StringBuffer;>
 2624 invokevirtual #405 <java/lang/StringBuffer/toString()Ljava/lang/String;>
 2627 getstatic #296 <g/gf B>
 2630 iconst_4
 2631 iconst_0
 2632 invokevirtual #416 <h/a(Ljava/lang/String;IBZ)Z>
 2635 pop
 2636 aload_0
 2637 getfield #19 <g/bh Lh;>
 2640 invokevirtual #472 <h/x()V>
 2643 aload_0
 2644 getfield #19 <g/bh Lh;>
 2647 invokevirtual #473 <h/c()V>
 2650 goto 11999 (+9349)
 2653 aload_0
 2654 invokevirtual #467 <g/E()V>
 2657 aload_0
 2658 getfield #19 <g/bh Lh;>
 2661 ldc_w #493 <请选择要进行的操作?>
 2664 iconst_m1
 2665 iconst_4
 2666 iconst_0
 2667 invokevirtual #416 <h/a(Ljava/lang/String;IBZ)Z>
 2670 pop
 2671 aload_0
 2672 getfield #19 <g/bh Lh;>
 2675 aload_0
 2676 getfield #19 <g/bh Lh;>
 2679 pop
 2680 getstatic #319 <h/dU S>
 2683 bipush 50
 2685 isub
 2686 iconst_2
 2687 idiv
 2688 aload_0
 2689 getfield #19 <g/bh Lh;>
 2692 pop
 2693 getstatic #20 <h/fp S>
 2696 bipush 70
 2698 isub
 2699 iconst_2
 2700 idiv
 2701 aload_0
 2702 getfield #51 <g/gd B>
 2705 aload_0
 2706 getfield #46 <g/c9 [Ljava/lang/String;>
 2709 invokevirtual #494 <h/a(IIB[Ljava/lang/String;)V>
 2712 aload_0
 2713 getfield #19 <g/bh Lh;>
 2716 invokevirtual #472 <h/x()V>
 2719 aload_0
 2720 getfield #19 <g/bh Lh;>
 2723 invokevirtual #473 <h/c()V>
 2726 goto 11999 (+9273)
 2729 aload_0
 2730 invokevirtual #467 <g/E()V>
 2733 aload_0
 2734 getfield #19 <g/bh Lh;>
 2737 new #401 <java/lang/StringBuffer>
 2740 dup
 2741 invokespecial #402 <java/lang/StringBuffer/<init>()V>
 2744 ldc_w #495 <选择完成[>
 2747 invokevirtual #404 <java/lang/StringBuffer/append(Ljava/lang/String;)Ljava/lang/StringBuffer;>
 2750 aload_0
 2751 getfield #19 <g/bh Lh;>
 2754 getfield #496 <h/bR Lak;>
 2757 getfield #497 <ak/case Ljava/lang/String;>
 2760 invokevirtual #404 <java/lang/StringBuffer/append(Ljava/lang/String;)Ljava/lang/StringBuffer;>
 2763 ldc_w #498 <]提交的宠物?>
 2766 invokevirtual #404 <java/lang/StringBuffer/append(Ljava/lang/String;)Ljava/lang/StringBuffer;>
 2769 invokevirtual #405 <java/lang/StringBuffer/toString()Ljava/lang/String;>
 2772 iconst_m1
 2773 iconst_4
 2774 iconst_0
 2775 invokevirtual #416 <h/a(Ljava/lang/String;IBZ)Z>
 2778 pop
 2779 aload_0
 2780 getfield #19 <g/bh Lh;>
 2783 aload_0
 2784 getfield #19 <g/bh Lh;>
 2787 pop
 2788 getstatic #319 <h/dU S>
 2791 bipush 50
 2793 isub
 2794 iconst_2
 2795 idiv
 2796 aload_0
 2797 getfield #19 <g/bh Lh;>
 2800 pop
 2801 getstatic #20 <h/fp S>
 2804 bipush 70
 2806 isub
 2807 iconst_2
 2808 idiv
 2809 aload_0
 2810 getfield #51 <g/gd B>
 2813 aload_0
 2814 getfield #46 <g/c9 [Ljava/lang/String;>
 2817 invokevirtual #494 <h/a(IIB[Ljava/lang/String;)V>
 2820 aload_0
 2821 getfield #19 <g/bh Lh;>
 2824 invokevirtual #472 <h/x()V>
 2827 aload_0
 2828 getfield #19 <g/bh Lh;>
 2831 invokevirtual #473 <h/c()V>
 2834 goto 11999 (+9165)
 2837 aload_0
 2838 invokevirtual #467 <g/E()V>
 2841 aload_0
 2842 getfield #19 <g/bh Lh;>
 2845 iconst_2
 2846 iconst_0
 2847 iconst_0
 2848 aload_0
 2849 getfield #8 <g/dt Ljavax/microedition/lcdui/Image;>
 2852 invokevirtual #335 <javax/microedition/lcdui/Image/getWidth()I>
 2855 iconst_4
 2856 iadd
 2857 aload_0
 2858 getfield #8 <g/dt Ljavax/microedition/lcdui/Image;>
 2861 invokevirtual #336 <javax/microedition/lcdui/Image/getHeight()I>
 2864 iconst_4
 2865 iadd
 2866 iconst_1
 2867 invokevirtual #370 <h/a(BIIIIZ)V>
 2870 aload_0
 2871 getfield #19 <g/bh Lh;>
 2874 getfield #320 <h/fj Ljavax/microedition/lcdui/Graphics;>
 2877 aload_0
 2878 getfield #8 <g/dt Ljavax/microedition/lcdui/Image;>
 2881 iconst_2
 2882 iconst_2
 2883 iconst_0
 2884 invokevirtual #499 <javax/microedition/lcdui/Graphics/drawImage(Ljavax/microedition/lcdui/Image;III)V>
 2887 aload_0
 2888 getfield #19 <g/bh Lh;>
 2891 invokevirtual #473 <h/c()V>
 2894 goto 11999 (+9105)
 2897 aload_0
 2898 invokevirtual #467 <g/E()V>
 2901 aload_0
 2902 aload_0
 2903 getfield #500 <g/fA Ljava/lang/String;>
 2906 ldc_w #501 <查看>
 2909 ldc #171 <返回>
 2911 invokevirtual #471 <g/a(Ljava/lang/String;Ljava/lang/String;Ljava/lang/String;)V>
 2914 goto 11999 (+9085)
 2917 aload_0
 2918 invokevirtual #467 <g/E()V>
 2921 aload_0
 2922 getfield #19 <g/bh Lh;>
 2925 aload_0
 2926 getfield #502 <g/nt [Ljava/lang/String;>
 2929 aload_0
 2930 getfield #503 <g/fF B>
 2933 aaload
 2934 iconst_m1
 2935 iconst_4
 2936 iconst_0
 2937 invokevirtual #416 <h/a(Ljava/lang/String;IBZ)Z>
 2940 pop
 2941 aload_0
 2942 getfield #19 <g/bh Lh;>
 2945 aload_0
 2946 getfield #19 <g/bh Lh;>
 2949 pop
 2950 getstatic #319 <h/dU S>
 2953 bipush 50
 2955 isub
 2956 iconst_2
 2957 idiv
 2958 aload_0
 2959 getfield #19 <g/bh Lh;>
 2962 pop
 2963 getstatic #20 <h/fp S>
 2966 bipush 70
 2968 isub
 2969 iconst_2
 2970 idiv
 2971 aload_0
 2972 getfield #504 <g/d7 B>
 2975 aload_0
 2976 getfield #505 <g/fx [[Ljava/lang/String;>
 2979 aload_0
 2980 getfield #503 <g/fF B>
 2983 aaload
 2984 invokevirtual #494 <h/a(IIB[Ljava/lang/String;)V>
 2987 aload_0
 2988 getfield #19 <g/bh Lh;>
 2991 invokevirtual #472 <h/x()V>
 2994 aload_0
 2995 getfield #19 <g/bh Lh;>
 2998 invokevirtual #473 <h/c()V>
 3001 goto 11999 (+8998)
 3004 aload_0
 3005 invokevirtual #467 <g/E()V>
 3008 aload_0
 3009 getfield #19 <g/bh Lh;>
 3012 aload_0
 3013 getfield #506 <g/m7 Ljava/lang/String;>
 3016 getstatic #296 <g/gf B>
 3019 iconst_4
 3020 iconst_0
 3021 invokevirtual #416 <h/a(Ljava/lang/String;IBZ)Z>
 3024 ifeq 3043 (+19)
 3027 aload_0
 3028 iconst_4
 3029 putfield #3 <g/cJ S>
 3032 aload_0
 3033 sipush 168
 3036 putfield #4 <g/hv S>
 3039 aload_0
 3040 invokevirtual #507 <g/j()V>
 3043 aload_0
 3044 getfield #19 <g/bh Lh;>
 3047 invokevirtual #472 <h/x()V>
 3050 goto 11999 (+8949)
 3053 aload_0
 3054 invokevirtual #467 <g/E()V>
 3057 aload_0
 3058 getfield #19 <g/bh Lh;>
 3061 getfield #250 <h/cZ Lag;>
 3064 aload_0
 3065 getfield #19 <g/bh Lh;>
 3068 getfield #250 <h/cZ Lag;>
 3071 getfield #508 <a3/bo B>
 3074 aload_0
 3075 getfield #509 <g/dF B>
 3078 invokevirtual #510 <ag/int(BI)I>
 3081 istore_1
 3082 iconst_1
 3083 iload_1
 3084 invokestatic #308 <java/lang/Math/max(II)I>
 3087 istore_1
 3088 iload_1
 3089 iconst_1
 3090 iadd
 3091 iload_1
 3092 iconst_1
 3093 iadd
 3094 imul
 3095 iload_1
 3096 iconst_1
 3097 iadd
 3098 imul
 3099 bipush 100
 3101 imul
 3102 istore_2
 3103 aload_0
 3104 new #401 <java/lang/StringBuffer>
 3107 dup
 3108 invokespecial #402 <java/lang/StringBuffer/<init>()V>
 3111 ldc_w #511 <是否消耗职业熟练值>
 3114 invokevirtual #404 <java/lang/StringBuffer/append(Ljava/lang/String;)Ljava/lang/StringBuffer;>
 3117 iload_2
 3118 invokevirtual #489 <java/lang/StringBuffer/append(I)Ljava/lang/StringBuffer;>
 3121 ldc_w #512 <提升本技能?>
 3124 invokevirtual #404 <java/lang/StringBuffer/append(Ljava/lang/String;)Ljava/lang/StringBuffer;>
 3127 invokevirtual #405 <java/lang/StringBuffer/toString()Ljava/lang/String;>
 3130 ldc_w #469 <是>
 3133 ldc_w #470 <否>
 3136 invokevirtual #471 <g/a(Ljava/lang/String;Ljava/lang/String;Ljava/lang/String;)V>
 3139 goto 11999 (+8860)
 3142 aload_0
 3143 getfield #60 <g/kH B>
 3146 lookupswitch 2
             0:  3172 (+26)
             1:  3172 (+26)
             default:  3189 (+43)
 3172 aload_0
 3173 invokevirtual #467 <g/E()V>
 3176 aload_0
 3177 ldc_w #513 <新物质融合器:"是否已准备好启动融合?">
 3180 ldc_w #469 <是>
 3183 ldc_w #470 <否>
 3186 invokevirtual #471 <g/a(Ljava/lang/String;Ljava/lang/String;Ljava/lang/String;)V>
 3189 goto 11999 (+8810)
 3192 aload_0
 3193 invokevirtual #467 <g/E()V>
 3196 aload_0
 3197 getfield #514 <g/gP Z>
 3200 ifeq 3232 (+32)
 3203 aload_0
 3204 getfield #19 <g/bh Lh;>
 3207 aload_0
 3208 getfield #515 <g/i7 Ljava/lang/String;>
 3211 getstatic #296 <g/gf B>
 3214 aload_0
 3215 pop
 3216 iconst_4
 3217 iconst_0
 3218 invokevirtual #416 <h/a(Ljava/lang/String;IBZ)Z>
 3221 ifeq 11999 (+8778)
 3224 aload_0
 3225 iconst_0
 3226 putfield #514 <g/gP Z>
 3229 goto 11999 (+8770)
 3232 aload_0
 3233 aload_0
 3234 getfield #515 <g/i7 Ljava/lang/String;>
 3237 ldc_w #469 <是>
 3240 ldc_w #470 <否>
 3243 invokevirtual #471 <g/a(Ljava/lang/String;Ljava/lang/String;Ljava/lang/String;)V>
 3246 aload_0
 3247 getfield #19 <g/bh Lh;>
 3250 invokevirtual #472 <h/x()V>
 3253 aload_0
 3254 getfield #19 <g/bh Lh;>
 3257 invokevirtual #473 <h/c()V>
 3260 goto 11999 (+8739)
 3263 aload_0
 3264 invokevirtual #467 <g/E()V>
 3267 new #401 <java/lang/StringBuffer>
 3270 dup
 3271 invokespecial #402 <java/lang/StringBuffer/<init>()V>
 3274 ldc_w #516 <欢迎回到充满未知与激情的星战世界!您已离线超过>
 3277 invokevirtual #404 <java/lang/StringBuffer/append(Ljava/lang/String;)Ljava/lang/StringBuffer;>
 3280 aload_0
 3281 getfield #19 <g/bh Lh;>
 3284 getfield #517 <h/bD I>
 3287 invokevirtual #489 <java/lang/StringBuffer/append(I)Ljava/lang/StringBuffer;>
 3290 ldc_w #518 <小时,每小时可获得>
 3293 invokevirtual #404 <java/lang/StringBuffer/append(Ljava/lang/String;)Ljava/lang/StringBuffer;>
 3296 aload_0
 3297 getfield #19 <g/bh Lh;>
 3300 getfield #519 <h/ey I>
 3303 invokevirtual #489 <java/lang/StringBuffer/append(I)Ljava/lang/StringBuffer;>
 3306 ldc_w #520 <点离线经验(等级越高,获得越多),点击确认VIP用户即可获得总计>
 3309 invokevirtual #404 <java/lang/StringBuffer/append(Ljava/lang/String;)Ljava/lang/StringBuffer;>
 3312 aload_0
 3313 getfield #19 <g/bh Lh;>
 3316 getfield #521 <h/dl I>
 3319 invokevirtual #489 <java/lang/StringBuffer/append(I)Ljava/lang/StringBuffer;>
 3322 ldc_w #522 <点离线经验.>
 3325 invokevirtual #404 <java/lang/StringBuffer/append(Ljava/lang/String;)Ljava/lang/StringBuffer;>
 3328 invokevirtual #405 <java/lang/StringBuffer/toString()Ljava/lang/String;>
 3331 astore_3
 3332 aload_0
 3333 getfield #19 <g/bh Lh;>
 3336 getfield #523 <h/dL Z>
 3339 ifeq 3371 (+32)
 3342 aload_0
 3343 getfield #19 <g/bh Lh;>
 3346 aload_3
 3347 getstatic #296 <g/gf B>
 3350 aload_0
 3351 pop
 3352 iconst_4
 3353 iconst_0
 3354 invokevirtual #416 <h/a(Ljava/lang/String;IBZ)Z>
 3357 ifeq 11999 (+8642)
 3360 aload_0
 3361 getfield #19 <g/bh Lh;>
 3364 iconst_0
 3365 putfield #523 <h/dL Z>
 3368 goto 11999 (+8631)
 3371 aload_0
 3372 aload_3
 3373 ldc_w #469 <是>
 3376 ldc_w #470 <否>
 3379 invokevirtual #471 <g/a(Ljava/lang/String;Ljava/lang/String;Ljava/lang/String;)V>
 3382 aload_0
 3383 getfield #19 <g/bh Lh;>
 3386 invokevirtual #472 <h/x()V>
 3389 aload_0
 3390 getfield #19 <g/bh Lh;>
 3393 invokevirtual #473 <h/c()V>
 3396 goto 11999 (+8603)
 3399 aload_0
 3400 invokevirtual #467 <g/E()V>
 3403 aload_0
 3404 getfield #19 <g/bh Lh;>
 3407 aload_0
 3408 getfield #183 <g/dy Ljava/lang/String;>
 3411 getstatic #296 <g/gf B>
 3414 aload_0
 3415 pop
 3416 iconst_4
 3417 iconst_0
 3418 invokevirtual #416 <h/a(Ljava/lang/String;IBZ)Z>
 3421 ifeq 3424 (+3)
 3424 aload_0
 3425 getfield #19 <g/bh Lh;>
 3428 aload_0
 3429 pop
 3430 iconst_2
 3431 iconst_0
 3432 aload_0
 3433 getfield #19 <g/bh Lh;>
 3436 pop
 3437 getstatic #20 <h/fp S>
 3440 bipush 22
 3442 isub
 3443 bipush 45
 3445 bipush 22
 3447 iconst_1
 3448 invokevirtual #370 <h/a(BIIIIZ)V>
 3451 aload_0
 3452 getfield #19 <g/bh Lh;>
 3455 aload_0
 3456 pop
 3457 iconst_2
 3458 aload_0
 3459 getfield #19 <g/bh Lh;>
 3462 pop
 3463 getstatic #319 <h/dU S>
 3466 bipush 45
 3468 isub
 3469 aload_0
 3470 getfield #19 <g/bh Lh;>
 3473 pop
 3474 getstatic #20 <h/fp S>
 3477 bipush 22
 3479 isub
 3480 bipush 45
 3482 bipush 22
 3484 iconst_1
 3485 invokevirtual #370 <h/a(BIIIIZ)V>
 3488 aload_0
 3489 getfield #19 <g/bh Lh;>
 3492 getfield #320 <h/fj Ljavax/microedition/lcdui/Graphics;>
 3495 iconst_0
 3496 invokevirtual #322 <javax/microedition/lcdui/Graphics/setColor(I)V>
 3499 aload_0
 3500 getfield #19 <g/bh Lh;>
 3503 getfield #320 <h/fj Ljavax/microedition/lcdui/Graphics;>
 3506 ldc_w #524 <购买>
 3509 bipush 22
 3511 aload_0
 3512 getfield #19 <g/bh Lh;>
 3515 pop
 3516 getstatic #20 <h/fp S>
 3519 iconst_3
 3520 isub
 3521 bipush 33
 3523 invokevirtual #390 <javax/microedition/lcdui/Graphics/drawString(Ljava/lang/String;III)V>
 3526 aload_0
 3527 getfield #19 <g/bh Lh;>
 3530 getfield #320 <h/fj Ljavax/microedition/lcdui/Graphics;>
 3533 iconst_0
 3534 invokevirtual #322 <javax/microedition/lcdui/Graphics/setColor(I)V>
 3537 aload_0
 3538 getfield #19 <g/bh Lh;>
 3541 getfield #320 <h/fj Ljavax/microedition/lcdui/Graphics;>
 3544 ldc #64 <取消>
 3546 aload_0
 3547 getfield #19 <g/bh Lh;>
 3550 pop
 3551 getstatic #319 <h/dU S>
 3554 bipush 22
 3556 isub
 3557 aload_0
 3558 getfield #19 <g/bh Lh;>
 3561 pop
 3562 getstatic #20 <h/fp S>
 3565 iconst_3
 3566 isub
 3567 bipush 33
 3569 invokevirtual #390 <javax/microedition/lcdui/Graphics/drawString(Ljava/lang/String;III)V>
 3572 goto 11999 (+8427)
 3575 aload_0
 3576 invokevirtual #467 <g/E()V>
 3579 aload_0
 3580 getfield #19 <g/bh Lh;>
 3583 aload_0
 3584 getfield #500 <g/fA Ljava/lang/String;>
 3587 getstatic #296 <g/gf B>
 3590 aload_0
 3591 pop
 3592 iconst_4
 3593 iconst_0
 3594 invokevirtual #416 <h/a(Ljava/lang/String;IBZ)Z>
 3597 ifeq 11999 (+8402)
 3600 aload_0
 3601 getfield #525 <g/gI B>
 3604 ifne 3627 (+23)
 3607 aload_0
 3608 aconst_null
 3609 putfield #500 <g/fA Ljava/lang/String;>
 3612 aload_0
 3613 aconst_null
 3614 putfield #526 <g/fL Ljava/lang/String;>
 3617 aload_0
 3618 aload_0
 3619 pop
 3620 iconst_0
 3621 putfield #297 <ap/do S>
 3624 goto 11999 (+8375)
 3627 aload_0
 3628 iconst_0
 3629 putfield #418 <g/e3 B>
 3632 aload_0
 3633 bipush 7
 3635 putfield #297 <ap/do S>
 3638 goto 11999 (+8361)
 3641 aload_0
 3642 invokevirtual #467 <g/E()V>
 3645 aload_0
 3646 getfield #19 <g/bh Lh;>
 3649 getfield #527 <h/ck Lai;>
 3652 invokevirtual #528 <ai/int()V>
 3655 aload_0
 3656 aload_0
 3657 getfield #529 <g/iN Z>
 3660 ifeq 3669 (+9)
 3663 ldc_w #530 <查看下一页?>
 3666 goto 3672 (+6)
 3669 ldc_w #531 <查看上一页?>
 3672 ldc_w #469 <是>
 3675 ldc_w #470 <否>
 3678 invokevirtual #471 <g/a(Ljava/lang/String;Ljava/lang/String;Ljava/lang/String;)V>
 3681 goto 11999 (+8318)
 3684 aload_0
 3685 getfield #155 <g/ea Laf;>
 3688 invokevirtual #532 <af/new()V>
 3691 goto 11999 (+8308)
 3694 aload_0
 3695 getfield #19 <g/bh Lh;>
 3698 getfield #533 <h/bS Lau;>
 3701 invokevirtual #534 <au/a()V>
 3704 goto 11999 (+8295)
 3707 aload_0
 3708 getfield #19 <g/bh Lh;>
 3711 getfield #535 <h/fm Lan;>
 3714 invokevirtual #536 <an/do()V>
 3717 goto 11999 (+8282)
 3720 aload_0
 3721 invokevirtual #467 <g/E()V>
 3724 aload_0
 3725 getfield #19 <g/bh Lh;>
 3728 ldc_w #537 <设置什么职位?(可通过:系统->帮助->公会->职位 查看管理职位任命要求)>
 3731 iconst_m1
 3732 iconst_4
 3733 iconst_0
 3734 invokevirtual #416 <h/a(Ljava/lang/String;IBZ)Z>
 3737 pop
 3738 aload_0
 3739 getfield #19 <g/bh Lh;>
 3742 aload_0
 3743 getfield #19 <g/bh Lh;>
 3746 pop
 3747 getstatic #319 <h/dU S>
 3750 bipush 50
 3752 isub
 3753 iconst_2
 3754 idiv
 3755 aload_0
 3756 getfield #19 <g/bh Lh;>
 3759 pop
 3760 getstatic #20 <h/fp S>
 3763 bipush 70
 3765 isub
 3766 iconst_2
 3767 idiv
 3768 aload_0
 3769 getfield #51 <g/gd B>
 3772 aload_0
 3773 getfield #46 <g/c9 [Ljava/lang/String;>
 3776 invokevirtual #494 <h/a(IIB[Ljava/lang/String;)V>
 3779 aload_0
 3780 getfield #19 <g/bh Lh;>
 3783 invokevirtual #472 <h/x()V>
 3786 aload_0
 3787 getfield #19 <g/bh Lh;>
 3790 invokevirtual #473 <h/c()V>
 3793 goto 11999 (+8206)
 3796 aload_0
 3797 invokevirtual #467 <g/E()V>
 3800 aload_0
 3801 aload_0
 3802 getfield #17 <g/bu Ljava/lang/String;>
 3805 ldc_w #538 <确定>
 3808 ldc #64 <取消>
 3810 invokevirtual #471 <g/a(Ljava/lang/String;Ljava/lang/String;Ljava/lang/String;)V>
 3813 goto 11999 (+8186)
 3816 aload_0
 3817 invokevirtual #467 <g/E()V>
 3820 aload_0
 3821 aload_0
 3822 getfield #17 <g/bu Ljava/lang/String;>
 3825 ldc_w #538 <确定>
 3828 ldc #64 <取消>
 3830 invokevirtual #471 <g/a(Ljava/lang/String;Ljava/lang/String;Ljava/lang/String;)V>
 3833 goto 11999 (+8166)
 3836 aload_0
 3837 invokevirtual #467 <g/E()V>
 3840 aload_0
 3841 ldc_w #539 <确定使用该颜色?>
 3844 ldc_w #538 <确定>
 3847 ldc #64 <取消>
 3849 invokevirtual #471 <g/a(Ljava/lang/String;Ljava/lang/String;Ljava/lang/String;)V>
 3852 goto 11999 (+8147)
 3855 aload_0
 3856 getfield #157 <g/mM Lm;>
 3859 invokevirtual #540 <m/a()V>
 3862 aload_0
 3863 getfield #19 <g/bh Lh;>
 3866 invokevirtual #472 <h/x()V>
 3869 aload_0
 3870 getfield #19 <g/bh Lh;>
 3873 invokevirtual #473 <h/c()V>
 3876 goto 11999 (+8123)
 3879 aload_0
 3880 getfield #19 <g/bh Lh;>
 3883 getfield #541 <h/bf Lv;>
 3886 invokevirtual #542 <v/a()V>
 3889 goto 11999 (+8110)
 3892 aload_0
 3893 getfield #19 <g/bh Lh;>
 3896 getfield #543 <h/ct Lam;>
 3899 invokevirtual #544 <am/if()V>
 3902 goto 11999 (+8097)
 3905 aload_0
 3906 getfield #156 <g/iZ Lat;>
 3909 invokevirtual #545 <at/a()V>
 3912 goto 11999 (+8087)
 3915 aload_0
 3916 getfield #19 <g/bh Lh;>
 3919 invokevirtual #546 <h/b()V>
 3922 goto 11999 (+8077)
 3925 aload_0
 3926 invokevirtual #467 <g/E()V>
 3929 aload_0
 3930 ldc_w #547 <确定使用?>
 3933 ldc_w #538 <确定>
 3936 ldc #64 <取消>
 3938 invokevirtual #471 <g/a(Ljava/lang/String;Ljava/lang/String;Ljava/lang/String;)V>
 3941 goto 11999 (+8058)
 3944 aload_0
 3945 invokevirtual #467 <g/E()V>
 3948 aload_0
 3949 ldc_w #548 <确定兑换?>
 3952 ldc_w #538 <确定>
 3955 ldc #64 <取消>
 3957 invokevirtual #471 <g/a(Ljava/lang/String;Ljava/lang/String;Ljava/lang/String;)V>
 3960 goto 11999 (+8039)
 3963 aload_0
 3964 invokevirtual #467 <g/E()V>
 3967 aload_0
 3968 getfield #19 <g/bh Lh;>
 3971 invokevirtual #549 <h/long()V>
 3974 aload_0
 3975 getfield #19 <g/bh Lh;>
 3978 invokevirtual #472 <h/x()V>
 3981 aload_0
 3982 getfield #19 <g/bh Lh;>
 3985 invokevirtual #473 <h/c()V>
 3988 goto 11999 (+8011)
 3991 aload_0
 3992 getfield #19 <g/bh Lh;>
 3995 getfield #550 <h/bv Le;>
 3998 invokevirtual #551 <e/do()V>
 4001 goto 11999 (+7998)
 4004 aload_0
 4005 getfield #19 <g/bh Lh;>
 4008 invokevirtual #552 <h/y()V>
 4011 goto 11999 (+7988)
 4014 aload_0
 4015 new #401 <java/lang/StringBuffer>
 4018 dup
 4019 invokespecial #402 <java/lang/StringBuffer/<init>()V>
 4022 ldc_w #553 <使用唤醒模组?(>
 4025 invokevirtual #404 <java/lang/StringBuffer/append(Ljava/lang/String;)Ljava/lang/StringBuffer;>
 4028 bipush 10
 4030 aload_0
 4031 getfield #9 <g/int I>
 4034 bipush 10
 4036 idiv
 4037 bipush 10
 4039 irem
 4040 isub
 4041 invokevirtual #489 <java/lang/StringBuffer/append(I)Ljava/lang/StringBuffer;>
 4044 ldc_w #554 <)>
 4047 invokevirtual #404 <java/lang/StringBuffer/append(Ljava/lang/String;)Ljava/lang/StringBuffer;>
 4050 invokevirtual #405 <java/lang/StringBuffer/toString()Ljava/lang/String;>
 4053 ldc_w #469 <是>
 4056 ldc_w #470 <否>
 4059 invokevirtual #471 <g/a(Ljava/lang/String;Ljava/lang/String;Ljava/lang/String;)V>
 4062 aload_0
 4063 getfield #9 <g/int I>
 4066 bipush 100
 4068 if_icmple 11999 (+7931)
 4071 aload_0
 4072 iconst_1
 4073 putfield #418 <g/e3 B>
 4076 aload_0
 4077 iconst_5
 4078 invokevirtual #555 <g/if(I)V>
 4081 goto 11999 (+7918)
 4084 aload_0
 4085 getfield #19 <g/bh Lh;>
 4088 ldc_w #556 <使用唤醒模组?>
 4091 iconst_m1
 4092 aload_0
 4093 pop
 4094 iconst_4
 4095 iconst_0
 4096 invokevirtual #416 <h/a(Ljava/lang/String;IBZ)Z>
 4099 pop
 4100 aload_0
 4101 getfield #9 <g/int I>
 4104 bipush 10
 4106 if_icmple 11999 (+7893)
 4109 aload_0
 4110 bipush 40
 4112 putfield #297 <ap/do S>
 4115 aload_0
 4116 iconst_0
 4117 putfield #9 <g/int I>
 4120 aload_0
 4121 iconst_0
 4122 putfield #418 <g/e3 B>
 4125 goto 11999 (+7874)
 4128 aload_0
 4129 invokevirtual #467 <g/E()V>
 4132 aload_0
 4133 getfield #19 <g/bh Lh;>
 4136 iconst_2
 4137 iconst_0
 4138 iconst_0
 4139 aload_0
 4140 getfield #19 <g/bh Lh;>
 4143 pop
 4144 getstatic #319 <h/dU S>
 4147 aload_0
 4148 getfield #19 <g/bh Lh;>
 4151 pop
 4152 getstatic #20 <h/fp S>
 4155 iconst_0
 4156 invokevirtual #370 <h/a(BIIIIZ)V>
 4159 aload_0
 4160 getfield #19 <g/bh Lh;>
 4163 getfield #259 <h/i Lah;>
 4166 iconst_1
 4167 invokevirtual #557 <ah/do(Z)V>
 4170 aload_0
 4171 aload_0
 4172 getfield #297 <ap/do S>
 4175 bipush 206
 4177 if_icmpne 4186 (+9)
 4180 ldc_w #558 <装备位上是极品装备,强制卸下将导致装备丢弃,确定丢弃?(可使用特殊道具解除绑定)>
 4183 goto 4189 (+6)
 4186 ldc_w #559 <确定丢弃?>
 4189 ldc_w #469 <是>
 4192 ldc_w #470 <否>
 4195 invokevirtual #471 <g/a(Ljava/lang/String;Ljava/lang/String;Ljava/lang/String;)V>
 4198 goto 11999 (+7801)
 4201 aload_0
 4202 getfield #19 <g/bh Lh;>
 4205 ldc_w #560 <公会战结束,请稍候...>
 4208 invokevirtual #561 <h/k(Ljava/lang/String;)V>
 4211 goto 11999 (+7788)
 4214 aload_0
 4215 getfield #19 <g/bh Lh;>
 4218 ldc_w #562 <公会战即将开始...>
 4221 invokevirtual #561 <h/k(Ljava/lang/String;)V>
 4224 goto 11999 (+7775)
 4227 aload_0
 4228 getfield #19 <g/bh Lh;>
 4231 getfield #563 <h/dy Lr;>
 4234 invokevirtual #564 <r/a()V>
 4237 goto 11999 (+7762)
 4240 aload_0
 4241 getfield #19 <g/bh Lh;>
 4244 getfield #565 <h/ez Lal;>
 4247 invokevirtual #566 <al/a()V>
 4250 goto 11999 (+7749)
 4253 aload_0
 4254 getfield #19 <g/bh Lh;>
 4257 getfield #567 <h/long Lz;>
 4260 invokevirtual #568 <z/a()V>
 4263 goto 11999 (+7736)
 4266 aload_0
 4267 getfield #19 <g/bh Lh;>
 4270 getfield #569 <h/e0 Lav;>
 4273 aload_0
 4274 getfield #297 <ap/do S>
 4277 invokevirtual #570 <av/if(S)V>
 4280 goto 11999 (+7719)
 4283 aload_0
 4284 invokevirtual #467 <g/E()V>
 4287 aload_0
 4288 getfield #571 <g/mZ B>
 4291 ifne 4369 (+78)
 4294 aload_0
 4295 getfield #19 <g/bh Lh;>
 4298 ldc_w #572 <选择要进行的操作?>
 4301 iconst_m1
 4302 iconst_4
 4303 iconst_0
 4304 invokevirtual #416 <h/a(Ljava/lang/String;IBZ)Z>
 4307 pop
 4308 aload_0
 4309 getfield #19 <g/bh Lh;>
 4312 aload_0
 4313 getfield #19 <g/bh Lh;>
 4316 pop
 4317 getstatic #319 <h/dU S>
 4320 bipush 50
 4322 isub
 4323 iconst_2
 4324 idiv
 4325 aload_0
 4326 getfield #19 <g/bh Lh;>
 4329 pop
 4330 getstatic #20 <h/fp S>
 4333 bipush 70
 4335 isub
 4336 iconst_2
 4337 idiv
 4338 bipush 20
 4340 iadd
 4341 aload_0
 4342 getfield #51 <g/gd B>
 4345 aload_0
 4346 getfield #573 <g/cM [Ljava/lang/String;>
 4349 invokevirtual #494 <h/a(IIB[Ljava/lang/String;)V>
 4352 aload_0
 4353 getfield #19 <g/bh Lh;>
 4356 invokevirtual #472 <h/x()V>
 4359 aload_0
 4360 getfield #19 <g/bh Lh;>
 4363 invokevirtual #473 <h/c()V>
 4366 goto 11999 (+7633)
 4369 aload_0
 4370 getfield #571 <g/mZ B>
 4373 iconst_1
 4374 if_icmpne 4406 (+32)
 4377 aload_0
 4378 getfield #19 <g/bh Lh;>
 4381 aload_0
 4382 getfield #574 <g/eJ Ljava/lang/String;>
 4385 getstatic #296 <g/gf B>
 4388 iconst_4
 4389 iconst_0
 4390 invokevirtual #416 <h/a(Ljava/lang/String;IBZ)Z>
 4393 pop
 4394 aload_0
 4395 ldc_w #575 <升级>
 4398 ldc #171 <返回>
 4400 invokevirtual #576 <g/do(Ljava/lang/String;Ljava/lang/String;)V>
 4403 goto 11999 (+7596)
 4406 aload_0
 4407 getfield #571 <g/mZ B>
 4410 iconst_2
 4411 if_icmpne 4435 (+24)
 4414 aload_0
 4415 aload_0
 4416 getfield #40 <g/ip Ljava/util/Vector;>
 4419 iconst_1
 4420 invokevirtual #475 <g/a(Ljava/util/Vector;Z)V>
 4423 aload_0
 4424 ldc_w #577 <选择>
 4427 ldc #171 <返回>
 4429 invokevirtual #576 <g/do(Ljava/lang/String;Ljava/lang/String;)V>
 4432 goto 11999 (+7567)
 4435 aload_0
 4436 getfield #571 <g/mZ B>
 4439 iconst_3
 4440 if_icmpne 4464 (+24)
 4443 aload_0
 4444 aload_0
 4445 getfield #40 <g/ip Ljava/util/Vector;>
 4448 iconst_1
 4449 invokevirtual #475 <g/a(Ljava/util/Vector;Z)V>
 4452 aload_0
 4453 ldc_w #578 <使用>
 4456 ldc #171 <返回>
 4458 invokevirtual #576 <g/do(Ljava/lang/String;Ljava/lang/String;)V>
 4461 goto 11999 (+7538)
 4464 aload_0
 4465 getfield #571 <g/mZ B>
 4468 iconst_4
 4469 if_icmpne 4515 (+46)
 4472 aload_0
 4473 aload_0
 4474 getfield #40 <g/ip Ljava/util/Vector;>
 4477 iconst_0
 4478 invokevirtual #475 <g/a(Ljava/util/Vector;Z)V>
 4481 aload_0
 4482 getfield #19 <g/bh Lh;>
 4485 aload_0
 4486 getfield #579 <g/lG [Ljava/lang/String;>
 4489 aload_0
 4490 getfield #50 <g/hZ S>
 4493 aaload
 4494 getstatic #296 <g/gf B>
 4497 iconst_4
 4498 iconst_0
 4499 invokevirtual #416 <h/a(Ljava/lang/String;IBZ)Z>
 4502 pop
 4503 aload_0
 4504 ldc_w #580 <研发>
 4507 ldc #171 <返回>
 4509 invokevirtual #576 <g/do(Ljava/lang/String;Ljava/lang/String;)V>
 4512 goto 11999 (+7487)
 4515 aload_0
 4516 getfield #571 <g/mZ B>
 4519 bipush 6
 4521 if_icmpne 4572 (+51)
 4524 aload_0
 4525 aload_0
 4526 getfield #40 <g/ip Ljava/util/Vector;>
 4529 iconst_0
 4530 invokevirtual #475 <g/a(Ljava/util/Vector;Z)V>
 4533 aload_0
 4534 getfield #19 <g/bh Lh;>
 4537 aload_0
 4538 getfield #42 <g/ee Ljava/util/Vector;>
 4541 aload_0
 4542 getfield #50 <g/hZ S>
 4545 invokevirtual #394 <java/util/Vector/elementAt(I)Ljava/lang/Object;>
 4548 checkcast #23 <java/lang/String>
 4551 getstatic #296 <g/gf B>
 4554 iconst_4
 4555 iconst_0
 4556 invokevirtual #416 <h/a(Ljava/lang/String;IBZ)Z>
 4559 pop
 4560 aload_0
 4561 ldc_w #578 <使用>
 4564 ldc #171 <返回>
 4566 invokevirtual #576 <g/do(Ljava/lang/String;Ljava/lang/String;)V>
 4569 goto 11999 (+7430)
 4572 aload_0
 4573 getfield #571 <g/mZ B>
 4576 iconst_5
 4577 if_icmpne 4605 (+28)
 4580 aload_0
 4581 aload_0
 4582 getfield #40 <g/ip Ljava/util/Vector;>
 4585 iconst_0
 4586 invokevirtual #475 <g/a(Ljava/util/Vector;Z)V>
 4589 aload_0
 4590 ldc_w #581 <确定要研发此科技?>
 4593 ldc_w #469 <是>
 4596 ldc_w #470 <否>
 4599 invokevirtual #471 <g/a(Ljava/lang/String;Ljava/lang/String;Ljava/lang/String;)V>
 4602 goto 11999 (+7397)
 4605 aload_0
 4606 getfield #571 <g/mZ B>
 4609 bipush 7
 4611 if_icmpne 11999 (+7388)
 4614 aload_0
 4615 aload_0
 4616 getfield #40 <g/ip Ljava/util/Vector;>
 4619 iconst_0
 4620 invokevirtual #475 <g/a(Ljava/util/Vector;Z)V>
 4623 ldc_w #582 <激活科技需消耗公会贡献度1,是否要激活?(同时只能激活1种科技,若已激活其他科技,将自动解除)>
 4626 astore 4
 4628 aload_0
 4629 getfield #583 <g/fG [B>
 4632 aload_0
 4633 getfield #50 <g/hZ S>
 4636 baload
 4637 iconst_5
 4638 if_icmple 4646 (+8)
 4641 ldc_w #584 <确定使用该科技?>
 4644 astore 4
 4646 aload_0
 4647 aload 4
 4649 ldc_w #469 <是>
 4652 ldc_w #470 <否>
 4655 invokevirtual #471 <g/a(Ljava/lang/String;Ljava/lang/String;Ljava/lang/String;)V>
 4658 goto 11999 (+7341)
 4661 aload_0
 4662 invokevirtual #467 <g/E()V>
 4665 aload_0
 4666 getfield #19 <g/bh Lh;>
 4669 invokevirtual #549 <h/long()V>
 4672 aload_0
 4673 getfield #19 <g/bh Lh;>
 4676 aload_0
 4677 getfield #19 <g/bh Lh;>
 4680 pop
 4681 getstatic #319 <h/dU S>
 4684 bipush 50
 4686 isub
 4687 iconst_2
 4688 idiv
 4689 aload_0
 4690 getfield #19 <g/bh Lh;>
 4693 pop
 4694 getstatic #20 <h/fp S>
 4697 bipush 70
 4699 isub
 4700 iconst_2
 4701 idiv
 4702 bipush 20
 4704 iadd
 4705 aload_0
 4706 getfield #51 <g/gd B>
 4709 iconst_3
 4710 anewarray #23 <java/lang/String>
 4713 dup
 4714 iconst_0
 4715 ldc_w #524 <购买>
 4718 aastore
 4719 dup
 4720 iconst_1
 4721 ldc_w #501 <查看>
 4724 aastore
 4725 dup
 4726 iconst_2
 4727 ldc #171 <返回>
 4729 aastore
 4730 invokevirtual #494 <h/a(IIB[Ljava/lang/String;)V>
 4733 aload_0
 4734 getfield #19 <g/bh Lh;>
 4737 invokevirtual #472 <h/x()V>
 4740 aload_0
 4741 getfield #19 <g/bh Lh;>
 4744 invokevirtual #473 <h/c()V>
 4747 goto 11999 (+7252)
 4750 aload_0
 4751 getfield #137 <g/md Lae;>
 4754 invokevirtual #585 <ae/if()V>
 4757 aload_0
 4758 getfield #19 <g/bh Lh;>
 4761 bipush 22
 4763 aload_0
 4764 getfield #19 <g/bh Lh;>
 4767 pop
 4768 getstatic #106 <h/eA I>
 4771 iconst_2
 4772 imul
 4773 iconst_2
 4774 iadd
 4775 aload_0
 4776 getfield #51 <g/gd B>
 4779 aload_0
 4780 getfield #137 <g/md Lae;>
 4783 getfield #586 <ae/if [Ljava/lang/String;>
 4786 invokevirtual #494 <h/a(IIB[Ljava/lang/String;)V>
 4789 goto 11999 (+7210)
 4792 aload_0
 4793 getfield #137 <g/md Lae;>
 4796 invokevirtual #585 <ae/if()V>
 4799 goto 11999 (+7200)
 4802 aload_0
 4803 invokevirtual #467 <g/E()V>
 4806 aload_0
 4807 getfield #19 <g/bh Lh;>
 4810 iconst_2
 4811 iconst_0
 4812 iconst_0
 4813 aload_0
 4814 getfield #19 <g/bh Lh;>
 4817 pop
 4818 getstatic #319 <h/dU S>
 4821 aload_0
 4822 getfield #19 <g/bh Lh;>
 4825 pop
 4826 getstatic #20 <h/fp S>
 4829 iconst_0
 4830 invokevirtual #370 <h/a(BIIIIZ)V>
 4833 aload_0
 4834 aload_0
 4835 getfield #40 <g/ip Ljava/util/Vector;>
 4838 iconst_0
 4839 invokevirtual #475 <g/a(Ljava/util/Vector;Z)V>
 4842 aload_0
 4843 new #401 <java/lang/StringBuffer>
 4846 dup
 4847 invokespecial #402 <java/lang/StringBuffer/<init>()V>
 4850 ldc_w #587 <确认会长转移给>
 4853 invokevirtual #404 <java/lang/StringBuffer/append(Ljava/lang/String;)Ljava/lang/StringBuffer;>
 4856 aload_0
 4857 getfield #45 <g/b5 Ljava/lang/String;>
 4860 invokevirtual #404 <java/lang/StringBuffer/append(Ljava/lang/String;)Ljava/lang/StringBuffer;>
 4863 ldc_w #588 <?>
 4866 invokevirtual #404 <java/lang/StringBuffer/append(Ljava/lang/String;)Ljava/lang/StringBuffer;>
 4869 invokevirtual #405 <java/lang/StringBuffer/toString()Ljava/lang/String;>
 4872 ldc_w #469 <是>
 4875 ldc_w #470 <否>
 4878 invokevirtual #471 <g/a(Ljava/lang/String;Ljava/lang/String;Ljava/lang/String;)V>
 4881 goto 11999 (+7118)
 4884 aload_0
 4885 invokevirtual #467 <g/E()V>
 4888 aload_0
 4889 getfield #19 <g/bh Lh;>
 4892 iconst_2
 4893 iconst_0
 4894 iconst_0
 4895 aload_0
 4896 getfield #19 <g/bh Lh;>
 4899 pop
 4900 getstatic #319 <h/dU S>
 4903 aload_0
 4904 getfield #19 <g/bh Lh;>
 4907 pop
 4908 getstatic #20 <h/fp S>
 4911 iconst_0
 4912 invokevirtual #370 <h/a(BIIIIZ)V>
 4915 aload_0
 4916 aload_0
 4917 getfield #40 <g/ip Ljava/util/Vector;>
 4920 iconst_1
 4921 invokevirtual #475 <g/a(Ljava/util/Vector;Z)V>
 4924 aload_0
 4925 getfield #19 <g/bh Lh;>
 4928 invokevirtual #472 <h/x()V>
 4931 aload_0
 4932 getfield #19 <g/bh Lh;>
 4935 invokevirtual #473 <h/c()V>
 4938 goto 11999 (+7061)
 4941 aload_0
 4942 invokevirtual #467 <g/E()V>
 4945 aload_0
 4946 getfield #589 <g/mf B>
 4949 ifne 4993 (+44)
 4952 aload_0
 4953 new #401 <java/lang/StringBuffer>
 4956 dup
 4957 invokespecial #402 <java/lang/StringBuffer/<init>()V>
 4960 ldc_w #590 <强制退会需扣除金钱>
 4963 invokevirtual #404 <java/lang/StringBuffer/append(Ljava/lang/String;)Ljava/lang/StringBuffer;>
 4966 aload_0
 4967 getfield #591 <g/eb I>
 4970 invokevirtual #489 <java/lang/StringBuffer/append(I)Ljava/lang/StringBuffer;>
 4973 ldc_w #592 <,且将导致公会贡献度清0.确认操作？>
 4976 invokevirtual #404 <java/lang/StringBuffer/append(Ljava/lang/String;)Ljava/lang/StringBuffer;>
 4979 invokevirtual #405 <java/lang/StringBuffer/toString()Ljava/lang/String;>
 4982 ldc_w #593 <确认>
 4985 ldc #171 <返回>
 4987 invokevirtual #471 <g/a(Ljava/lang/String;Ljava/lang/String;Ljava/lang/String;)V>
 4990 goto 11999 (+7009)
 4993 aload_0
 4994 ldc_w #594 <退出公会会将公会贡献度清0,确认退会?>
 4997 ldc_w #593 <确认>
 5000 ldc #171 <返回>
 5002 invokevirtual #471 <g/a(Ljava/lang/String;Ljava/lang/String;Ljava/lang/String;)V>
 5005 goto 11999 (+6994)
 5008 aload_0
 5009 invokevirtual #467 <g/E()V>
 5012 aload_0
 5013 ldc_w #595 <选择退会方式?>
 5016 ldc_w #596 <申请退会>
 5019 ldc_w #597 <强制退会>
 5022 invokevirtual #471 <g/a(Ljava/lang/String;Ljava/lang/String;Ljava/lang/String;)V>
 5025 aload_0
 5026 getfield #19 <g/bh Lh;>
 5029 invokevirtual #472 <h/x()V>
 5032 aload_0
 5033 getfield #19 <g/bh Lh;>
 5036 invokevirtual #473 <h/c()V>
 5039 goto 11999 (+6960)
 5042 aload_0
 5043 invokevirtual #467 <g/E()V>
 5046 aload_0
 5047 ldc_w #595 <选择退会方式?>
 5050 ldc_w #598 <会长转移>
 5053 ldc_w #597 <强制退会>
 5056 invokevirtual #471 <g/a(Ljava/lang/String;Ljava/lang/String;Ljava/lang/String;)V>
 5059 aload_0
 5060 getfield #19 <g/bh Lh;>
 5063 invokevirtual #472 <h/x()V>
 5066 aload_0
 5067 getfield #19 <g/bh Lh;>
 5070 invokevirtual #473 <h/c()V>
 5073 goto 11999 (+6926)
 5076 aload_0
 5077 invokevirtual #467 <g/E()V>
 5080 aload_0
 5081 ldc_w #599 <公会只有你一人,解散公会?>
 5084 ldc_w #469 <是>
 5087 ldc_w #470 <否>
 5090 invokevirtual #471 <g/a(Ljava/lang/String;Ljava/lang/String;Ljava/lang/String;)V>
 5093 goto 11999 (+6906)
 5096 aload_0
 5097 invokevirtual #467 <g/E()V>
 5100 aload_0
 5101 getfield #19 <g/bh Lh;>
 5104 invokevirtual #600 <h/s()V>
 5107 aload_0
 5108 ldc_w #601 <确定开始合成?>
 5111 ldc_w #469 <是>
 5114 ldc_w #470 <否>
 5117 invokevirtual #471 <g/a(Ljava/lang/String;Ljava/lang/String;Ljava/lang/String;)V>
 5120 goto 11999 (+6879)
 5123 aload_0
 5124 invokevirtual #467 <g/E()V>
 5127 aload_0
 5128 getfield #19 <g/bh Lh;>
 5131 invokevirtual #600 <h/s()V>
 5134 aload_0
 5135 getfield #19 <g/bh Lh;>
 5138 getfield #482 <h/d9 Lw;>
 5141 invokevirtual #483 <w/a()V>
 5144 goto 11999 (+6855)
 5147 aload_0
 5148 getfield #9 <g/int I>
 5151 iconst_1
 5152 if_icmpne 5175 (+23)
 5155 aload_0
 5156 getfield #79 <g/dx S>
 5159 ifne 5175 (+16)
 5162 aload_0
 5163 ldc_w #602 <请选择合成主材料>
 5166 bipush 119
 5168 iconst_0
 5169 bipush 20
 5171 invokevirtual #603 <g/a(Ljava/lang/String;SZI)V>
 5174 return
 5175 aload_0
 5176 invokevirtual #467 <g/E()V>
 5179 aload_0
 5180 getfield #19 <g/bh Lh;>
 5183 invokevirtual #600 <h/s()V>
 5186 aload_0
 5187 getfield #79 <g/dx S>
 5190 ifle 5200 (+10)
 5193 aload_0
 5194 getfield #19 <g/bh Lh;>
 5197 invokevirtual #472 <h/x()V>
 5200 aload_0
 5201 getfield #19 <g/bh Lh;>
 5204 invokevirtual #473 <h/c()V>
 5207 goto 11999 (+6792)
 5210 aload_0
 5211 getfield #19 <g/bh Lh;>
 5214 ldc_w #604 <任务失败!>
 5217 iconst_m1
 5218 iconst_4
 5219 iconst_0
 5220 invokevirtual #416 <h/a(Ljava/lang/String;IBZ)Z>
 5223 pop
 5224 aload_0
 5225 getfield #9 <g/int I>
 5228 bipush 15
 5230 if_icmple 11999 (+6769)
 5233 aload_0
 5234 getfield #19 <g/bh Lh;>
 5237 getfield #250 <h/cZ Lag;>
 5240 iconst_0
 5241 putfield #605 <a3/T Z>
 5244 aload_0
 5245 getfield #19 <g/bh Lh;>
 5248 getfield #250 <h/cZ Lag;>
 5251 iconst_0
 5252 putfield #606 <a3/ao Z>
 5255 aload_0
 5256 getfield #19 <g/bh Lh;>
 5259 getfield #250 <h/cZ Lag;>
 5262 iconst_0
 5263 putfield #607 <ag/hU Z>
 5266 aload_0
 5267 getfield #19 <g/bh Lh;>
 5270 getfield #250 <h/cZ Lag;>
 5273 iconst_0
 5274 putfield #289 <a3/a4 B>
 5277 aload_0
 5278 getfield #19 <g/bh Lh;>
 5281 getfield #250 <h/cZ Lag;>
 5284 bipush 16
 5286 iconst_1
 5287 invokevirtual #608 <a3/if(BI)V>
 5290 aload_0
 5291 getfield #19 <g/bh Lh;>
 5294 invokevirtual #609 <h/o()V>
 5297 goto 11999 (+6702)
 5300 aload_0
 5301 invokevirtual #467 <g/E()V>
 5304 aload_0
 5305 getfield #53 <g/g6 [Ljava/lang/String;>
 5308 arraylength
 5309 ifle 5430 (+121)
 5312 aload_0
 5313 getfield #610 <g/eq B>
 5316 aload_0
 5317 getfield #53 <g/g6 [Ljava/lang/String;>
 5320 arraylength
 5321 iconst_1
 5322 isub
 5323 if_icmple 5338 (+15)
 5326 aload_0
 5327 aload_0
 5328 getfield #53 <g/g6 [Ljava/lang/String;>
 5331 arraylength
 5332 iconst_1
 5333 isub
 5334 i2b
 5335 putfield #610 <g/eq B>
 5338 aload_0
 5339 getfield #19 <g/bh Lh;>
 5342 bipush 27
 5344 aload_0
 5345 getfield #9 <g/int I>
 5348 iconst_5
 5349 irem
 5350 ifne 5357 (+7)
 5353 iconst_2
 5354 goto 5358 (+4)
 5357 iconst_0
 5358 iadd
 5359 bipush 22
 5361 aload_0
 5362 getfield #610 <g/eq B>
 5365 bipush 6
 5367 aload_0
 5368 getfield #19 <g/bh Lh;>
 5371 pop
 5372 getstatic #611 <h/a9 B>
 5375 ifne 5382 (+7)
 5378 iconst_3
 5379 goto 5385 (+6)
 5382 getstatic #106 <h/eA I>
 5385 iadd
 5386 imul
 5387 iadd
 5388 aload_0
 5389 getfield #19 <g/bh Lh;>
 5392 getfield #354 <h/aH [Ljavax/microedition/lcdui/Image;>
 5395 bipush 6
 5397 aaload
 5398 invokevirtual #335 <javax/microedition/lcdui/Image/getWidth()I>
 5401 aload_0
 5402 getfield #19 <g/bh Lh;>
 5405 getfield #354 <h/aH [Ljavax/microedition/lcdui/Image;>
 5408 bipush 6
 5410 aaload
 5411 invokevirtual #336 <javax/microedition/lcdui/Image/getHeight()I>
 5414 iconst_0
 5415 iconst_0
 5416 aload_0
 5417 getfield #19 <g/bh Lh;>
 5420 getfield #354 <h/aH [Ljavax/microedition/lcdui/Image;>
 5423 bipush 6
 5425 aaload
 5426 iconst_2
 5427 invokevirtual #337 <h/a(IIIIIILjavax/microedition/lcdui/Image;I)V>
 5430 aload_0
 5431 getfield #19 <g/bh Lh;>
 5434 invokevirtual #472 <h/x()V>
 5437 aload_0
 5438 getfield #19 <g/bh Lh;>
 5441 invokevirtual #473 <h/c()V>
 5444 goto 11999 (+6555)
 5447 aload_0
 5448 getfield #19 <g/bh Lh;>
 5451 getfield #527 <h/ck Lai;>
 5454 invokevirtual #612 <ai/if()V>
 5457 goto 11999 (+6542)
 5460 aload_0
 5461 getfield #19 <g/bh Lh;>
 5464 getfield #320 <h/fj Ljavax/microedition/lcdui/Graphics;>
 5467 iconst_0
 5468 invokevirtual #322 <javax/microedition/lcdui/Graphics/setColor(I)V>
 5471 aload_0
 5472 getfield #19 <g/bh Lh;>
 5475 getfield #320 <h/fj Ljavax/microedition/lcdui/Graphics;>
 5478 iconst_0
 5479 iconst_0
 5480 aload_0
 5481 getfield #19 <g/bh Lh;>
 5484 pop
 5485 getstatic #319 <h/dU S>
 5488 aload_0
 5489 getfield #19 <g/bh Lh;>
 5492 pop
 5493 getstatic #20 <h/fp S>
 5496 invokevirtual #411 <javax/microedition/lcdui/Graphics/fillRect(IIII)V>
 5499 bipush 8
 5501 istore 4
 5503 aload_0
 5504 getfield #19 <g/bh Lh;>
 5507 pop
 5508 getstatic #319 <h/dU S>
 5511 iconst_2
 5512 idiv
 5513 bipush 72
 5515 iconst_4
 5516 iload 4
 5518 imul
 5519 iadd
 5520 iconst_2
 5521 idiv
 5522 isub
 5523 istore 5
 5525 aload_0
 5526 getfield #19 <g/bh Lh;>
 5529 pop
 5530 getstatic #20 <h/fp S>
 5533 iconst_2
 5534 idiv
 5535 bipush 72
 5537 iconst_4
 5538 iload 4
 5540 imul
 5541 iadd
 5542 iconst_2
 5543 idiv
 5544 isub
 5545 istore 6
 5547 iconst_0
 5548 istore 7
 5550 iload 7
 5552 bipush 6
 5554 if_icmpge 5641 (+87)
 5557 iconst_0
 5558 istore 8
 5560 iload 8
 5562 bipush 6
 5564 if_icmpge 5631 (+67)
 5567 aload_0
 5568 getfield #19 <g/bh Lh;>
 5571 iload 5
 5573 iload 7
 5575 bipush 12
 5577 iload 4
 5579 iadd
 5580 imul
 5581 iadd
 5582 iload 6
 5584 iload 8
 5586 bipush 12
 5588 iload 4
 5590 iadd
 5591 imul
 5592 iadd
 5593 bipush 12
 5595 bipush 12
 5597 iload 7
 5599 bipush 12
 5601 imul
 5602 iload 8
 5604 bipush 12
 5606 imul
 5607 aload_0
 5608 getfield #19 <g/bh Lh;>
 5611 getfield #354 <h/aH [Ljavax/microedition/lcdui/Image;>
 5614 bipush 8
 5616 aaload
 5617 iconst_0
 5618 invokevirtual #337 <h/a(IIIIIILjavax/microedition/lcdui/Image;I)V>
 5621 iload 8
 5623 iconst_1
 5624 iadd
 5625 i2b
 5626 istore 8
 5628 goto 5560 (-68)
 5631 iload 7
 5633 iconst_1
 5634 iadd
 5635 i2b
 5636 istore 7
 5638 goto 5550 (-88)
 5641 aload_0
 5642 getfield #19 <g/bh Lh;>
 5645 getfield #320 <h/fj Ljavax/microedition/lcdui/Graphics;>
 5648 aload_0
 5649 getfield #19 <g/bh Lh;>
 5652 pop
 5653 getstatic #321 <h/b2 [[I>
 5656 aload_0
 5657 getfield #19 <g/bh Lh;>
 5660 pop
 5661 iconst_5
 5662 aaload
 5663 iconst_0
 5664 iaload
 5665 invokevirtual #322 <javax/microedition/lcdui/Graphics/setColor(I)V>
 5668 aload_0
 5669 getfield #19 <g/bh Lh;>
 5672 getfield #320 <h/fj Ljavax/microedition/lcdui/Graphics;>
 5675 iload 5
 5677 aload_0
 5678 getfield #127 <g/hq B>
 5681 bipush 12
 5683 iload 4
 5685 iadd
 5686 imul
 5687 iadd
 5688 iconst_4
 5689 isub
 5690 aload_0
 5691 getfield #9 <g/int I>
 5694 iconst_2
 5695 idiv
 5696 iconst_2
 5697 irem
 5698 iadd
 5699 iload 6
 5701 aload_0
 5702 getfield #128 <g/hp B>
 5705 bipush 12
 5707 iload 4
 5709 iadd
 5710 imul
 5711 iadd
 5712 iconst_4
 5713 isub
 5714 aload_0
 5715 getfield #9 <g/int I>
 5718 iconst_2
 5719 idiv
 5720 iconst_2
 5721 irem
 5722 iadd
 5723 bipush 18
 5725 iconst_2
 5726 aload_0
 5727 getfield #9 <g/int I>
 5730 iconst_2
 5731 idiv
 5732 iconst_2
 5733 irem
 5734 imul
 5735 isub
 5736 bipush 18
 5738 iconst_2
 5739 aload_0
 5740 getfield #9 <g/int I>
 5743 iconst_2
 5744 idiv
 5745 iconst_2
 5746 irem
 5747 imul
 5748 isub
 5749 invokevirtual #613 <javax/microedition/lcdui/Graphics/drawRect(IIII)V>
 5752 aload_0
 5753 getfield #19 <g/bh Lh;>
 5756 invokevirtual #472 <h/x()V>
 5759 aload_0
 5760 getfield #19 <g/bh Lh;>
 5763 invokevirtual #473 <h/c()V>
 5766 goto 11999 (+6233)
 5769 aload_0
 5770 getfield #9 <g/int I>
 5773 bipush 11
 5775 if_icmpgt 5925 (+150)
 5778 aload_0
 5779 getfield #19 <g/bh Lh;>
 5782 getfield #320 <h/fj Ljavax/microedition/lcdui/Graphics;>
 5785 iconst_0
 5786 invokevirtual #322 <javax/microedition/lcdui/Graphics/setColor(I)V>
 5789 aload_0
 5790 getfield #19 <g/bh Lh;>
 5793 getfield #320 <h/fj Ljavax/microedition/lcdui/Graphics;>
 5796 iconst_0
 5797 iconst_0
 5798 aload_0
 5799 getfield #19 <g/bh Lh;>
 5802 pop
 5803 getstatic #319 <h/dU S>
 5806 aload_0
 5807 getfield #19 <g/bh Lh;>
 5810 pop
 5811 getstatic #20 <h/fp S>
 5814 invokevirtual #411 <javax/microedition/lcdui/Graphics/fillRect(IIII)V>
 5817 aload_0
 5818 getfield #9 <g/int I>
 5821 iconst_5
 5822 if_icmplt 5877 (+55)
 5825 aload_0
 5826 getfield #19 <g/bh Lh;>
 5829 getfield #320 <h/fj Ljavax/microedition/lcdui/Graphics;>
 5832 ldc_w #614 <16777215>
 5835 invokevirtual #322 <javax/microedition/lcdui/Graphics/setColor(I)V>
 5838 aload_0
 5839 getfield #19 <g/bh Lh;>
 5842 getfield #320 <h/fj Ljavax/microedition/lcdui/Graphics;>
 5845 iconst_0
 5846 aload_0
 5847 getfield #19 <g/bh Lh;>
 5850 pop
 5851 getstatic #20 <h/fp S>
 5854 iconst_2
 5855 idiv
 5856 aload_0
 5857 getfield #19 <g/bh Lh;>
 5860 pop
 5861 getstatic #319 <h/dU S>
 5864 iconst_4
 5865 idiv
 5866 aload_0
 5867 getfield #9 <g/int I>
 5870 iconst_5
 5871 isub
 5872 imul
 5873 iconst_2
 5874 invokevirtual #411 <javax/microedition/lcdui/Graphics/fillRect(IIII)V>
 5877 aload_0
 5878 getfield #9 <g/int I>
 5881 bipush 11
 5883 if_icmpne 11999 (+6116)
 5886 aload_0
 5887 getfield #297 <ap/do S>
 5890 bipush 124
 5892 if_icmpne 5910 (+18)
 5895 aload_0
 5896 getfield #19 <g/bh Lh;>
 5899 getfield #250 <h/cZ Lag;>
 5902 bipush 12
 5904 putfield #289 <a3/a4 B>
 5907 goto 11999 (+6092)
 5910 aload_0
 5911 getfield #19 <g/bh Lh;>
 5914 getfield #250 <h/cZ Lag;>
 5917 bipush 11
 5919 putfield #289 <a3/a4 B>
 5922 goto 11999 (+6077)
 5925 aload_0
 5926 invokevirtual #467 <g/E()V>
 5929 aload_0
 5930 getfield #9 <g/int I>
 5933 aload_0
 5934 getfield #297 <ap/do S>
 5937 bipush 124
 5939 if_icmpne 5947 (+8)
 5942 bipush 18
 5944 goto 5949 (+5)
 5947 bipush 40
 5949 if_icmple 11999 (+6050)
 5952 aload_0
 5953 aload_0
 5954 getfield #12 <g/bl Ljava/lang/String;>
 5957 iconst_0
 5958 iconst_1
 5959 sipush 9999
 5962 invokevirtual #603 <g/a(Ljava/lang/String;SZI)V>
 5965 goto 11999 (+6034)
 5968 aload_0
 5969 getfield #19 <g/bh Lh;>
 5972 getfield #615 <h/du Li;>
 5975 invokevirtual #616 <i/a()V>
 5978 goto 11999 (+6021)
 5981 aload_0
 5982 getfield #19 <g/bh Lh;>
 5985 aload_0
 5986 getfield #17 <g/bu Ljava/lang/String;>
 5989 getstatic #296 <g/gf B>
 5992 iconst_4
 5993 iconst_0
 5994 invokevirtual #416 <h/a(Ljava/lang/String;IBZ)Z>
 5997 ifeq 11999 (+6002)
 6000 aload_0
 6001 getfield #19 <g/bh Lh;>
 6004 aload_0
 6005 aload_0
 6006 getfield #19 <g/bh Lh;>
 6009 getfield #617 <h/s Ly;>
 6012 invokevirtual #618 <h/a(Lap;Lap;)V>
 6015 goto 11999 (+5984)
 6018 aload_0
 6019 invokevirtual #467 <g/E()V>
 6022 aload_0
 6023 getfield #19 <g/bh Lh;>
 6026 aload_0
 6027 getfield #17 <g/bu Ljava/lang/String;>
 6030 getstatic #296 <g/gf B>
 6033 iconst_4
 6034 iconst_0
 6035 invokevirtual #416 <h/a(Ljava/lang/String;IBZ)Z>
 6038 ifeq 11999 (+5961)
 6041 aload_0
 6042 aload_0
 6043 pop
 6044 iconst_0
 6045 putfield #297 <ap/do S>
 6048 goto 11999 (+5951)
 6051 aload_0
 6052 getfield #19 <g/bh Lh;>
 6055 getfield #619 <h/br Lac;>
 6058 invokevirtual #620 <ac/a()V>
 6061 goto 11999 (+5938)
 6064 aload_0
 6065 getfield #19 <g/bh Lh;>
 6068 getfield #543 <h/ct Lam;>
 6071 invokevirtual #544 <am/if()V>
 6074 goto 11999 (+5925)
 6077 aload_0
 6078 invokevirtual #467 <g/E()V>
 6081 aload_0
 6082 getfield #19 <g/bh Lh;>
 6085 iconst_2
 6086 iconst_0
 6087 iconst_0
 6088 aload_0
 6089 getfield #19 <g/bh Lh;>
 6092 pop
 6093 getstatic #319 <h/dU S>
 6096 aload_0
 6097 getfield #19 <g/bh Lh;>
 6100 pop
 6101 getstatic #20 <h/fp S>
 6104 iconst_0
 6105 invokevirtual #370 <h/a(BIIIIZ)V>
 6108 aload_0
 6109 getfield #153 <g/e0 Lc;>
 6112 invokevirtual #621 <c/a()V>
 6115 aload_0
 6116 getfield #19 <g/bh Lh;>
 6119 bipush 72
 6121 iconst_0
 6122 aload_0
 6123 getfield #51 <g/gd B>
 6126 getstatic #622 <g/f1 [[Ljava/lang/String;>
 6129 aload_0
 6130 getfield #623 <g/gS B>
 6133 aaload
 6134 invokevirtual #494 <h/a(IIB[Ljava/lang/String;)V>
 6137 goto 11999 (+5862)
 6140 aload_0
 6141 getfield #153 <g/e0 Lc;>
 6144 invokevirtual #621 <c/a()V>
 6147 goto 11999 (+5852)
 6150 aload_0
 6151 invokevirtual #467 <g/E()V>
 6154 aload_0
 6155 aload_0
 6156 getfield #40 <g/ip Ljava/util/Vector;>
 6159 iconst_0
 6160 invokevirtual #475 <g/a(Ljava/util/Vector;Z)V>
 6163 aload_0
 6164 getfield #98 <g/hu Z>
 6167 iconst_1
 6168 if_icmpne 6180 (+12)
 6171 aload_0
 6172 aload_0
 6173 getfield #96 <g/nk Ljava/util/Vector;>
 6176 iconst_1
 6177 invokevirtual #475 <g/a(Ljava/util/Vector;Z)V>
 6180 aload_0
 6181 getfield #99 <g/dN Z>
 6184 iconst_1
 6185 if_icmpne 6197 (+12)
 6188 aload_0
 6189 aload_0
 6190 getfield #95 <g/j8 Ljava/util/Vector;>
 6193 iconst_1
 6194 invokevirtual #475 <g/a(Ljava/util/Vector;Z)V>
 6197 aload_0
 6198 getfield #19 <g/bh Lh;>
 6201 aload_0
 6202 getfield #19 <g/bh Lh;>
 6205 pop
 6206 getstatic #319 <h/dU S>
 6209 bipush 46
 6211 isub
 6212 iconst_0
 6213 aload_0
 6214 getfield #51 <g/gd B>
 6217 aload_0
 6218 getfield #46 <g/c9 [Ljava/lang/String;>
 6221 invokevirtual #494 <h/a(IIB[Ljava/lang/String;)V>
 6224 goto 11999 (+5775)
 6227 aload_0
 6228 invokevirtual #467 <g/E()V>
 6231 aload_0
 6232 getfield #19 <g/bh Lh;>
 6235 iconst_2
 6236 iconst_0
 6237 iconst_0
 6238 aload_0
 6239 getfield #19 <g/bh Lh;>
 6242 pop
 6243 getstatic #319 <h/dU S>
 6246 aload_0
 6247 getfield #19 <g/bh Lh;>
 6250 pop
 6251 getstatic #20 <h/fp S>
 6254 iconst_0
 6255 invokevirtual #370 <h/a(BIIIIZ)V>
 6258 aload_0
 6259 aload_0
 6260 getfield #40 <g/ip Ljava/util/Vector;>
 6263 iconst_1
 6264 invokevirtual #475 <g/a(Ljava/util/Vector;Z)V>
 6267 aload_0
 6268 ldc_w #624 <确定遗忘吗？>
 6271 ldc_w #469 <是>
 6274 ldc_w #470 <否>
 6277 invokevirtual #471 <g/a(Ljava/lang/String;Ljava/lang/String;Ljava/lang/String;)V>
 6280 goto 11999 (+5719)
 6283 aload_0
 6284 invokevirtual #467 <g/E()V>
 6287 aload_0
 6288 getfield #19 <g/bh Lh;>
 6291 iconst_2
 6292 iconst_0
 6293 iconst_0
 6294 aload_0
 6295 getfield #19 <g/bh Lh;>
 6298 pop
 6299 getstatic #319 <h/dU S>
 6302 aload_0
 6303 getfield #19 <g/bh Lh;>
 6306 pop
 6307 getstatic #20 <h/fp S>
 6310 iconst_0
 6311 invokevirtual #370 <h/a(BIIIIZ)V>
 6314 aload_0
 6315 aload_0
 6316 getfield #40 <g/ip Ljava/util/Vector;>
 6319 iconst_1
 6320 invokevirtual #475 <g/a(Ljava/util/Vector;Z)V>
 6323 aload_0
 6324 getfield #19 <g/bh Lh;>
 6327 invokevirtual #472 <h/x()V>
 6330 aload_0
 6331 getfield #19 <g/bh Lh;>
 6334 invokevirtual #473 <h/c()V>
 6337 goto 11999 (+5662)
 6340 aload_0
 6341 getfield #19 <g/bh Lh;>
 6344 getfield #543 <h/ct Lam;>
 6347 invokevirtual #544 <am/if()V>
 6350 goto 11999 (+5649)
 6353 aload_0
 6354 getfield #156 <g/iZ Lat;>
 6357 invokevirtual #545 <at/a()V>
 6360 goto 11999 (+5639)
 6363 aload_0
 6364 invokevirtual #467 <g/E()V>
 6367 aload_0
 6368 getfield #19 <g/bh Lh;>
 6371 aload_0
 6372 getfield #17 <g/bu Ljava/lang/String;>
 6375 getstatic #296 <g/gf B>
 6378 iconst_4
 6379 iconst_0
 6380 invokevirtual #416 <h/a(Ljava/lang/String;IBZ)Z>
 6383 ifeq 11999 (+5616)
 6386 aload_0
 6387 getfield #625 <g/bK B>
 6390 iconst_1
 6391 if_icmpne 6430 (+39)
 6394 aload_0
 6395 getfield #19 <g/bh Lh;>
 6398 getfield #250 <h/cZ Lag;>
 6401 getfield #344 <ag/fL I>
 6404 ifge 6420 (+16)
 6407 aload_0
 6408 getfield #19 <g/bh Lh;>
 6411 getfield #259 <h/i Lah;>
 6414 invokevirtual #626 <ah/else()V>
 6417 goto 11999 (+5582)
 6420 aload_0
 6421 aload_0
 6422 pop
 6423 iconst_0
 6424 putfield #297 <ap/do S>
 6427 goto 11999 (+5572)
 6430 aload_0
 6431 aload_0
 6432 pop
 6433 iconst_0
 6434 putfield #297 <ap/do S>
 6437 goto 11999 (+5562)
 6440 aload_0
 6441 invokevirtual #467 <g/E()V>
 6444 aload_0
 6445 getfield #19 <g/bh Lh;>
 6448 aload_0
 6449 getfield #17 <g/bu Ljava/lang/String;>
 6452 getstatic #296 <g/gf B>
 6455 iconst_4
 6456 iconst_0
 6457 invokevirtual #416 <h/a(Ljava/lang/String;IBZ)Z>
 6460 ifeq 11999 (+5539)
 6463 aload_0
 6464 getfield #19 <g/bh Lh;>
 6467 getfield #270 <h/fG LSFMIDlet;>
 6470 invokestatic #271 <javax/microedition/lcdui/Display/getDisplay(Ljavax/microedition/midlet/MIDlet;)Ljavax/microedition/lcdui/Display;>
 6473 aload_0
 6474 getfield #19 <g/bh Lh;>
 6477 getfield #259 <h/i Lah;>
 6480 getfield #627 <ah/h Ljavax/microedition/lcdui/Form;>
 6483 invokevirtual #272 <javax/microedition/lcdui/Display/setCurrent(Ljavax/microedition/lcdui/Displayable;)V>
 6486 goto 11999 (+5513)
 6489 aload_0
 6490 getfield #19 <g/bh Lh;>
 6493 ldc_w #628 <请稍候...>
 6496 invokevirtual #561 <h/k(Ljava/lang/String;)V>
 6499 aload_0
 6500 getfield #9 <g/int I>
 6503 sipush 2400
 6506 if_icmple 11999 (+5493)
 6509 aload_0
 6510 getfield #297 <ap/do S>
 6513 iconst_3
 6514 if_icmpne 11999 (+5485)
 6517 aload_0
 6518 ldc_w #629 <打开商店失败.>
 6521 iconst_0
 6522 iconst_0
 6523 bipush 30
 6525 invokevirtual #603 <g/a(Ljava/lang/String;SZI)V>
 6528 goto 11999 (+5471)
 6531 aload_0
 6532 invokevirtual #467 <g/E()V>
 6535 aload_0
 6536 getfield #19 <g/bh Lh;>
 6539 aload_0
 6540 getfield #630 <g/hz Ljava/lang/String;>
 6543 getstatic #296 <g/gf B>
 6546 iconst_4
 6547 iconst_0
 6548 invokevirtual #416 <h/a(Ljava/lang/String;IBZ)Z>
 6551 pop
 6552 goto 11999 (+5447)
 6555 aload_0
 6556 invokevirtual #467 <g/E()V>
 6559 aload_0
 6560 aload_0
 6561 getfield #92 <g/c8 Ljava/util/Vector;>
 6564 iconst_1
 6565 invokevirtual #475 <g/a(Ljava/util/Vector;Z)V>
 6568 aload_0
 6569 getfield #19 <g/bh Lh;>
 6572 invokevirtual #472 <h/x()V>
 6575 aload_0
 6576 getfield #19 <g/bh Lh;>
 6579 invokevirtual #473 <h/c()V>
 6582 goto 11999 (+5417)
 6585 aload_0
 6586 invokevirtual #467 <g/E()V>
 6589 ldc_w #631 <您当前还不是VIP用户.VIP用户可获得使用游戏币购买商城道具,登陆获得离线经验,增加现金背包等特权.是否申请成为VIP用户(最低仅需5元/月)?>
 6592 astore_3
 6593 aload_0
 6594 getfield #94 <g/bH Z>
 6597 ifeq 6629 (+32)
 6600 aload_0
 6601 getfield #19 <g/bh Lh;>
 6604 aload_3
 6605 getstatic #296 <g/gf B>
 6608 iconst_4
 6609 iconst_0
 6610 invokevirtual #416 <h/a(Ljava/lang/String;IBZ)Z>
 6613 ifeq 11999 (+5386)
 6616 aload_0
 6617 iconst_0
 6618 putfield #418 <g/e3 B>
 6621 aload_0
 6622 iconst_0
 6623 putfield #94 <g/bH Z>
 6626 goto 11999 (+5373)
 6629 aload_0
 6630 aload_3
 6631 ldc_w #469 <是>
 6634 ldc_w #470 <否>
 6637 invokevirtual #471 <g/a(Ljava/lang/String;Ljava/lang/String;Ljava/lang/String;)V>
 6640 aload_0
 6641 getfield #19 <g/bh Lh;>
 6644 invokevirtual #472 <h/x()V>
 6647 aload_0
 6648 getfield #19 <g/bh Lh;>
 6651 invokevirtual #473 <h/c()V>
 6654 goto 11999 (+5345)
 6657 aload_0
 6658 invokevirtual #467 <g/E()V>
 6661 aload_0
 6662 getfield #632 <g/lz B>
 6665 ifne 6702 (+37)
 6668 aload_0
 6669 getfield #19 <g/bh Lh;>
 6672 aload_0
 6673 getfield #93 <g/na Ljava/lang/String;>
 6676 getstatic #296 <g/gf B>
 6679 iconst_4
 6680 iconst_0
 6681 invokevirtual #416 <h/a(Ljava/lang/String;IBZ)Z>
 6684 ifeq 6692 (+8)
 6687 aload_0
 6688 iconst_0
 6689 putfield #297 <ap/do S>
 6692 aload_0
 6693 getfield #19 <g/bh Lh;>
 6696 invokevirtual #473 <h/c()V>
 6699 goto 11999 (+5300)
 6702 aload_0
 6703 aload_0
 6704 getfield #93 <g/na Ljava/lang/String;>
 6707 ldc_w #469 <是>
 6710 ldc_w #470 <否>
 6713 invokevirtual #471 <g/a(Ljava/lang/String;Ljava/lang/String;Ljava/lang/String;)V>
 6716 aload_0
 6717 getfield #19 <g/bh Lh;>
 6720 invokevirtual #472 <h/x()V>
 6723 aload_0
 6724 getfield #19 <g/bh Lh;>
 6727 invokevirtual #473 <h/c()V>
 6730 goto 11999 (+5269)
 6733 aload_0
 6734 invokevirtual #467 <g/E()V>
 6737 aload_0
 6738 aload_0
 6739 getfield #95 <g/j8 Ljava/util/Vector;>
 6742 iconst_1
 6743 invokevirtual #475 <g/a(Ljava/util/Vector;Z)V>
 6746 aload_0
 6747 getfield #19 <g/bh Lh;>
 6750 invokevirtual #472 <h/x()V>
 6753 aload_0
 6754 getfield #19 <g/bh Lh;>
 6757 invokevirtual #473 <h/c()V>
 6760 goto 11999 (+5239)
 6763 aload_0
 6764 invokevirtual #467 <g/E()V>
 6767 aload_0
 6768 aload_0
 6769 getfield #96 <g/nk Ljava/util/Vector;>
 6772 iconst_1
 6773 invokevirtual #475 <g/a(Ljava/util/Vector;Z)V>
 6776 aload_0
 6777 getfield #19 <g/bh Lh;>
 6780 invokevirtual #472 <h/x()V>
 6783 aload_0
 6784 getfield #19 <g/bh Lh;>
 6787 invokevirtual #473 <h/c()V>
 6790 goto 11999 (+5209)
 6793 aload_0
 6794 invokevirtual #467 <g/E()V>
 6797 aload_0
 6798 getfield #19 <g/bh Lh;>
 6801 aload_0
 6802 getfield #93 <g/na Ljava/lang/String;>
 6805 getstatic #296 <g/gf B>
 6808 iconst_4
 6809 iconst_0
 6810 invokevirtual #416 <h/a(Ljava/lang/String;IBZ)Z>
 6813 ifeq 11999 (+5186)
 6816 aload_0
 6817 iconst_0
 6818 putfield #297 <ap/do S>
 6821 goto 11999 (+5178)
 6824 aload_0
 6825 invokevirtual #467 <g/E()V>
 6828 aload_0
 6829 aload_0
 6830 getfield #633 <g/f9 Ljava/lang/String;>
 6833 ldc_w #469 <是>
 6836 ldc_w #470 <否>
 6839 invokevirtual #471 <g/a(Ljava/lang/String;Ljava/lang/String;Ljava/lang/String;)V>
 6842 aload_0
 6843 getfield #19 <g/bh Lh;>
 6846 invokevirtual #472 <h/x()V>
 6849 aload_0
 6850 getfield #19 <g/bh Lh;>
 6853 invokevirtual #473 <h/c()V>
 6856 goto 11999 (+5143)
 6859 aload_0
 6860 getfield #19 <g/bh Lh;>
 6863 ldc_w #628 <请稍候...>
 6866 invokevirtual #561 <h/k(Ljava/lang/String;)V>
 6869 goto 11999 (+5130)
 6872 goto 11999 (+5127)
 6875 aload_0
 6876 invokevirtual #467 <g/E()V>
 6879 aload_0
 6880 getfield #19 <g/bh Lh;>
 6883 aload_0
 6884 getfield #16 <g/k2 Ljava/lang/String;>
 6887 getstatic #296 <g/gf B>
 6890 aload_0
 6891 pop
 6892 iconst_4
 6893 iconst_0
 6894 invokevirtual #416 <h/a(Ljava/lang/String;IBZ)Z>
 6897 ifeq 11999 (+5102)
 6900 aload_0
 6901 aconst_null
 6902 putfield #16 <g/k2 Ljava/lang/String;>
 6905 aload_0
 6906 aload_0
 6907 pop
 6908 iconst_0
 6909 putfield #297 <ap/do S>
 6912 goto 11999 (+5087)
 6915 aload_0
 6916 getfield #19 <g/bh Lh;>
 6919 ldc_w #628 <请稍候...>
 6922 invokevirtual #561 <h/k(Ljava/lang/String;)V>
 6925 goto 11999 (+5074)
 6928 aload_0
 6929 invokevirtual #467 <g/E()V>
 6932 aload_0
 6933 getfield #19 <g/bh Lh;>
 6936 ldc_w #634 <等候超时!>
 6939 getstatic #296 <g/gf B>
 6942 aload_0
 6943 pop
 6944 iconst_4
 6945 iconst_0
 6946 invokevirtual #416 <h/a(Ljava/lang/String;IBZ)Z>
 6949 ifeq 11999 (+5050)
 6952 aload_0
 6953 invokevirtual #635 <g/J()V>
 6956 goto 11999 (+5043)
 6959 aload_0
 6960 getfield #19 <g/bh Lh;>
 6963 ldc_w #628 <请稍候...>
 6966 invokevirtual #561 <h/k(Ljava/lang/String;)V>
 6969 goto 11999 (+5030)
 6972 aload_0
 6973 getfield #158 <g/c7 Lk;>
 6976 invokevirtual #636 <k/a()V>
 6979 goto 11999 (+5020)
 6982 goto 11999 (+5017)
 6985 aload_0
 6986 invokevirtual #467 <g/E()V>
 6989 aload_0
 6990 aload_0
 6991 getfield #85 <g/lt Ljava/lang/String;>
 6994 ldc_w #538 <确定>
 6997 ldc #64 <取消>
 6999 invokevirtual #471 <g/a(Ljava/lang/String;Ljava/lang/String;Ljava/lang/String;)V>
 7002 aload_0
 7003 getfield #19 <g/bh Lh;>
 7006 invokevirtual #472 <h/x()V>
 7009 aload_0
 7010 getfield #19 <g/bh Lh;>
 7013 invokevirtual #473 <h/c()V>
 7016 goto 11999 (+4983)
 7019 aload_0
 7020 invokevirtual #467 <g/E()V>
 7023 aload_0
 7024 getfield #19 <g/bh Lh;>
 7027 invokevirtual #549 <h/long()V>
 7030 aload_0
 7031 ldc_w #637 <确定购买?>
 7034 ldc_w #469 <是>
 7037 ldc_w #470 <否>
 7040 invokevirtual #471 <g/a(Ljava/lang/String;Ljava/lang/String;Ljava/lang/String;)V>
 7043 goto 11999 (+4956)
 7046 aload_0
 7047 invokevirtual #467 <g/E()V>
 7050 aload_0
 7051 getfield #19 <g/bh Lh;>
 7054 invokevirtual #549 <h/long()V>
 7057 aload_0
 7058 getfield #19 <g/bh Lh;>
 7061 getfield #482 <h/d9 Lw;>
 7064 invokevirtual #483 <w/a()V>
 7067 goto 11999 (+4932)
 7070 aload_0
 7071 invokevirtual #467 <g/E()V>
 7074 aload_0
 7075 getfield #19 <g/bh Lh;>
 7078 invokevirtual #549 <h/long()V>
 7081 aload_0
 7082 getfield #79 <g/dx S>
 7085 ifle 7095 (+10)
 7088 aload_0
 7089 getfield #19 <g/bh Lh;>
 7092 invokevirtual #472 <h/x()V>
 7095 aload_0
 7096 getfield #19 <g/bh Lh;>
 7099 invokevirtual #473 <h/c()V>
 7102 goto 11999 (+4897)
 7105 aload_0
 7106 ldc_w #638 <确定摆摊?>
 7109 ldc_w #469 <是>
 7112 ldc_w #470 <否>
 7115 invokevirtual #471 <g/a(Ljava/lang/String;Ljava/lang/String;Ljava/lang/String;)V>
 7118 goto 11999 (+4881)
 7121 aload_0
 7122 invokevirtual #467 <g/E()V>
 7125 aload_0
 7126 getfield #19 <g/bh Lh;>
 7129 invokevirtual #600 <h/s()V>
 7132 aload_0
 7133 getfield #19 <g/bh Lh;>
 7136 getfield #482 <h/d9 Lw;>
 7139 invokevirtual #483 <w/a()V>
 7142 goto 11999 (+4857)
 7145 aload_0
 7146 invokevirtual #467 <g/E()V>
 7149 aload_0
 7150 getfield #19 <g/bh Lh;>
 7153 invokevirtual #600 <h/s()V>
 7156 aload_0
 7157 getfield #79 <g/dx S>
 7160 ifle 7170 (+10)
 7163 aload_0
 7164 getfield #19 <g/bh Lh;>
 7167 invokevirtual #472 <h/x()V>
 7170 aload_0
 7171 getfield #19 <g/bh Lh;>
 7174 invokevirtual #473 <h/c()V>
 7177 goto 11999 (+4822)
 7180 aload_0
 7181 invokevirtual #467 <g/E()V>
 7184 aload_0
 7185 getfield #19 <g/bh Lh;>
 7188 aload_0
 7189 getfield #85 <g/lt Ljava/lang/String;>
 7192 getstatic #296 <g/gf B>
 7195 aload_0
 7196 pop
 7197 iconst_4
 7198 aload_0
 7199 getfield #86 <g/new Z>
 7202 invokevirtual #416 <h/a(Ljava/lang/String;IBZ)Z>
 7205 ifne 7219 (+14)
 7208 aload_0
 7209 getfield #9 <g/int I>
 7212 aload_0
 7213 getfield #639 <g/eP I>
 7216 if_icmple 11999 (+4783)
 7219 aload_0
 7220 getfield #19 <g/bh Lh;>
 7223 aconst_null
 7224 putfield #295 <h/dk [Ljava/lang/String;>
 7227 aload_0
 7228 aload_0
 7229 getfield #640 <g/lb S>
 7232 putfield #297 <ap/do S>
 7235 goto 11999 (+4764)
 7238 aload_0
 7239 getfield #19 <g/bh Lh;>
 7242 getfield #641 <h/as Laa;>
 7245 invokevirtual #642 <aa/a()V>
 7248 goto 11999 (+4751)
 7251 aload_0
 7252 getfield #19 <g/bh Lh;>
 7255 getfield #643 <h/aI Lb;>
 7258 invokevirtual #644 <b/if()V>
 7261 goto 11999 (+4738)
 7264 aload_0
 7265 invokevirtual #467 <g/E()V>
 7268 aload_0
 7269 getfield #19 <g/bh Lh;>
 7272 aload_0
 7273 getfield #19 <g/bh Lh;>
 7276 getfield #462 <h/S Las;>
 7279 getfield #645 <as/F Ljava/lang/String;>
 7282 getstatic #296 <g/gf B>
 7285 iconst_1
 7286 isub
 7287 aload_0
 7288 pop
 7289 iconst_4
 7290 iconst_0
 7291 invokevirtual #416 <h/a(Ljava/lang/String;IBZ)Z>
 7294 pop
 7295 aload_0
 7296 getfield #19 <g/bh Lh;>
 7299 aload_0
 7300 getfield #19 <g/bh Lh;>
 7303 pop
 7304 getstatic #319 <h/dU S>
 7307 bipush 50
 7309 isub
 7310 iconst_2
 7311 idiv
 7312 aload_0
 7313 getfield #19 <g/bh Lh;>
 7316 pop
 7317 getstatic #20 <h/fp S>
 7320 bipush 70
 7322 isub
 7323 iconst_2
 7324 idiv
 7325 bipush 20
 7327 iadd
 7328 aload_0
 7329 getfield #51 <g/gd B>
 7332 aload_0
 7333 getfield #65 <g/cW [Ljava/lang/String;>
 7336 invokevirtual #494 <h/a(IIB[Ljava/lang/String;)V>
 7339 goto 11999 (+4660)
 7342 aload_0
 7343 invokevirtual #467 <g/E()V>
 7346 aload_0
 7347 getfield #19 <g/bh Lh;>
 7350 aload_0
 7351 getfield #19 <g/bh Lh;>
 7354 getfield #462 <h/S Las;>
 7357 getfield #645 <as/F Ljava/lang/String;>
 7360 getstatic #296 <g/gf B>
 7363 aload_0
 7364 pop
 7365 iconst_4
 7366 iconst_0
 7367 invokevirtual #416 <h/a(Ljava/lang/String;IBZ)Z>
 7370 ifeq 11999 (+4629)
 7373 aload_0
 7374 bipush 99
 7376 putfield #297 <ap/do S>
 7379 goto 11999 (+4620)
 7382 aload_0
 7383 invokevirtual #467 <g/E()V>
 7386 aload_0
 7387 new #401 <java/lang/StringBuffer>
 7390 dup
 7391 invokespecial #402 <java/lang/StringBuffer/<init>()V>
 7394 ldc_w #646 <进入 >
 7397 invokevirtual #404 <java/lang/StringBuffer/append(Ljava/lang/String;)Ljava/lang/StringBuffer;>
 7400 aload_0
 7401 getfield #2 <g/ez Ljava/lang/String;>
 7404 invokevirtual #404 <java/lang/StringBuffer/append(Ljava/lang/String;)Ljava/lang/StringBuffer;>
 7407 ldc_w #588 <?>
 7410 invokevirtual #404 <java/lang/StringBuffer/append(Ljava/lang/String;)Ljava/lang/StringBuffer;>
 7413 invokevirtual #405 <java/lang/StringBuffer/toString()Ljava/lang/String;>
 7416 ldc_w #469 <是>
 7419 ldc_w #470 <否>
 7422 invokevirtual #471 <g/a(Ljava/lang/String;Ljava/lang/String;Ljava/lang/String;)V>
 7425 goto 11999 (+4574)
 7428 aload_0
 7429 getfield #137 <g/md Lae;>
 7432 invokevirtual #647 <ae/for()V>
 7435 aload_0
 7436 getfield #19 <g/bh Lh;>
 7439 bipush 20
 7441 aload_0
 7442 getfield #137 <g/md Lae;>
 7445 getfield #648 <ae/null S>
 7448 bipush 20
 7450 iadd
 7451 aload_0
 7452 getfield #51 <g/gd B>
 7455 aload_0
 7456 getfield #137 <g/md Lae;>
 7459 getfield #649 <ae/case [Ljava/lang/String;>
 7462 invokevirtual #494 <h/a(IIB[Ljava/lang/String;)V>
 7465 goto 11999 (+4534)
 7468 aload_0
 7469 invokevirtual #467 <g/E()V>
 7472 aload_0
 7473 getfield #19 <g/bh Lh;>
 7476 ldc_w #650 <添加新任务!>
 7479 iconst_m1
 7480 aload_0
 7481 pop
 7482 iconst_4
 7483 iconst_0
 7484 invokevirtual #416 <h/a(Ljava/lang/String;IBZ)Z>
 7487 pop
 7488 aload_0
 7489 getfield #9 <g/int I>
 7492 bipush 20
 7494 if_icmple 11999 (+4505)
 7497 aload_0
 7498 iconst_5
 7499 invokevirtual #555 <g/if(I)V>
 7502 goto 11999 (+4497)
 7505 aload_0
 7506 invokevirtual #467 <g/E()V>
 7509 aload_0
 7510 getfield #19 <g/bh Lh;>
 7513 ldc_w #651 <该任务结束!>
 7516 iconst_m1
 7517 aload_0
 7518 pop
 7519 iconst_4
 7520 iconst_0
 7521 invokevirtual #416 <h/a(Ljava/lang/String;IBZ)Z>
 7524 pop
 7525 aload_0
 7526 getfield #9 <g/int I>
 7529 bipush 20
 7531 if_icmple 11999 (+4468)
 7534 aload_0
 7535 iconst_5
 7536 invokevirtual #555 <g/if(I)V>
 7539 goto 11999 (+4460)
 7542 aload_0
 7543 invokevirtual #467 <g/E()V>
 7546 aload_0
 7547 getfield #19 <g/bh Lh;>
 7550 aload_0
 7551 getfield #132 <g/jK Ljava/lang/String;>
 7554 getstatic #296 <g/gf B>
 7557 aload_0
 7558 pop
 7559 iconst_4
 7560 iconst_0
 7561 invokevirtual #416 <h/a(Ljava/lang/String;IBZ)Z>
 7564 ifeq 11999 (+4435)
 7567 aload_0
 7568 aload_0
 7569 pop
 7570 iconst_0
 7571 putfield #297 <ap/do S>
 7574 goto 11999 (+4425)
 7577 aload_0
 7578 invokevirtual #467 <g/E()V>
 7581 aload_0
 7582 getfield #19 <g/bh Lh;>
 7585 aload_0
 7586 getfield #500 <g/fA Ljava/lang/String;>
 7589 getstatic #296 <g/gf B>
 7592 aload_0
 7593 pop
 7594 iconst_4
 7595 iconst_0
 7596 invokevirtual #416 <h/a(Ljava/lang/String;IBZ)Z>
 7599 ifeq 7606 (+7)
 7602 iconst_0
 7603 putstatic #296 <g/gf B>
 7606 aload_0
 7607 getfield #19 <g/bh Lh;>
 7610 aload_0
 7611 pop
 7612 iconst_2
 7613 iconst_0
 7614 aload_0
 7615 getfield #19 <g/bh Lh;>
 7618 pop
 7619 getstatic #20 <h/fp S>
 7622 bipush 22
 7624 isub
 7625 bipush 45
 7627 bipush 22
 7629 iconst_1
 7630 invokevirtual #370 <h/a(BIIIIZ)V>
 7633 aload_0
 7634 getfield #19 <g/bh Lh;>
 7637 aload_0
 7638 pop
 7639 iconst_2
 7640 aload_0
 7641 getfield #19 <g/bh Lh;>
 7644 pop
 7645 getstatic #319 <h/dU S>
 7648 bipush 45
 7650 isub
 7651 aload_0
 7652 getfield #19 <g/bh Lh;>
 7655 pop
 7656 getstatic #20 <h/fp S>
 7659 bipush 22
 7661 isub
 7662 bipush 45
 7664 bipush 22
 7666 iconst_1
 7667 invokevirtual #370 <h/a(BIIIIZ)V>
 7670 aload_0
 7671 getfield #19 <g/bh Lh;>
 7674 getfield #320 <h/fj Ljavax/microedition/lcdui/Graphics;>
 7677 iconst_0
 7678 invokevirtual #322 <javax/microedition/lcdui/Graphics/setColor(I)V>
 7681 aload_0
 7682 getfield #19 <g/bh Lh;>
 7685 getfield #320 <h/fj Ljavax/microedition/lcdui/Graphics;>
 7688 ldc_w #501 <查看>
 7691 bipush 22
 7693 aload_0
 7694 getfield #19 <g/bh Lh;>
 7697 pop
 7698 getstatic #20 <h/fp S>
 7701 iconst_3
 7702 isub
 7703 bipush 33
 7705 invokevirtual #390 <javax/microedition/lcdui/Graphics/drawString(Ljava/lang/String;III)V>
 7708 aload_0
 7709 getfield #19 <g/bh Lh;>
 7712 getfield #320 <h/fj Ljavax/microedition/lcdui/Graphics;>
 7715 iconst_0
 7716 invokevirtual #322 <javax/microedition/lcdui/Graphics/setColor(I)V>
 7719 aload_0
 7720 getfield #19 <g/bh Lh;>
 7723 getfield #320 <h/fj Ljavax/microedition/lcdui/Graphics;>
 7726 ldc_w #652 <退出>
 7729 aload_0
 7730 getfield #19 <g/bh Lh;>
 7733 pop
 7734 getstatic #319 <h/dU S>
 7737 bipush 22
 7739 isub
 7740 aload_0
 7741 getfield #19 <g/bh Lh;>
 7744 pop
 7745 getstatic #20 <h/fp S>
 7748 iconst_3
 7749 isub
 7750 bipush 33
 7752 invokevirtual #390 <javax/microedition/lcdui/Graphics/drawString(Ljava/lang/String;III)V>
 7755 goto 11999 (+4244)
 7758 aload_0
 7759 invokevirtual #467 <g/E()V>
 7762 aload_0
 7763 getfield #19 <g/bh Lh;>
 7766 getfield #462 <h/S Las;>
 7769 getfield #653 <as/aB S>
 7772 ifeq 8126 (+354)
 7775 aload_0
 7776 getfield #19 <g/bh Lh;>
 7779 getfield #462 <h/S Las;>
 7782 getfield #654 <as/W B>
 7785 tableswitch 0 to 3
             0:  7816 (+31)
             1:  7971 (+186)
             2:  7816 (+31)
             3:  7971 (+186)
             default:  8123 (+338)
 7816 aload_0
 7817 getfield #19 <g/bh Lh;>
 7820 getfield #462 <h/S Las;>
 7823 getfield #653 <as/aB S>
 7826 aload_0
 7827 getfield #19 <g/bh Lh;>
 7830 getfield #462 <h/S Las;>
 7833 getfield #655 <as/ac B>
 7836 isub
 7837 ifgt 7898 (+61)
 7840 aload_0
 7841 getfield #19 <g/bh Lh;>
 7844 getfield #462 <h/S Las;>
 7847 getfield #656 <as/aD Ll;>
 7850 dup
 7851 getfield #249 <l/new S>
 7854 aload_0
 7855 getfield #19 <g/bh Lh;>
 7858 getfield #462 <h/S Las;>
 7861 getfield #653 <as/aB S>
 7864 getstatic #657 <a3/bp [B>
 7867 aload_0
 7868 getfield #19 <g/bh Lh;>
 7871 getfield #462 <h/S Las;>
 7874 getfield #654 <as/W B>
 7877 baload
 7878 imul
 7879 iadd
 7880 i2s
 7881 putfield #249 <l/new S>
 7884 aload_0
 7885 getfield #19 <g/bh Lh;>
 7888 getfield #462 <h/S Las;>
 7891 iconst_0
 7892 putfield #653 <as/aB S>
 7895 goto 8123 (+228)
 7898 aload_0
 7899 getfield #19 <g/bh Lh;>
 7902 getfield #462 <h/S Las;>
 7905 getfield #656 <as/aD Ll;>
 7908 dup
 7909 getfield #249 <l/new S>
 7912 aload_0
 7913 getfield #19 <g/bh Lh;>
 7916 getfield #462 <h/S Las;>
 7919 getfield #655 <as/ac B>
 7922 getstatic #657 <a3/bp [B>
 7925 aload_0
 7926 getfield #19 <g/bh Lh;>
 7929 getfield #462 <h/S Las;>
 7932 getfield #654 <as/W B>
 7935 baload
 7936 imul
 7937 iadd
 7938 i2s
 7939 putfield #249 <l/new S>
 7942 aload_0
 7943 getfield #19 <g/bh Lh;>
 7946 getfield #462 <h/S Las;>
 7949 dup
 7950 getfield #653 <as/aB S>
 7953 aload_0
 7954 getfield #19 <g/bh Lh;>
 7957 getfield #462 <h/S Las;>
 7960 getfield #655 <as/ac B>
 7963 isub
 7964 i2s
 7965 putfield #653 <as/aB S>
 7968 goto 8123 (+155)
 7971 aload_0
 7972 getfield #19 <g/bh Lh;>
 7975 getfield #462 <h/S Las;>
 7978 getfield #653 <as/aB S>
 7981 aload_0
 7982 getfield #19 <g/bh Lh;>
 7985 getfield #462 <h/S Las;>
 7988 getfield #655 <as/ac B>
 7991 isub
 7992 ifgt 8053 (+61)
 7995 aload_0
 7996 getfield #19 <g/bh Lh;>
 7999 getfield #462 <h/S Las;>
 8002 getfield #656 <as/aD Ll;>
 8005 dup
 8006 getfield #658 <l/try S>
 8009 aload_0
 8010 getfield #19 <g/bh Lh;>
 8013 getfield #462 <h/S Las;>
 8016 getfield #653 <as/aB S>
 8019 getstatic #659 <a3/bq [B>
 8022 aload_0
 8023 getfield #19 <g/bh Lh;>
 8026 getfield #462 <h/S Las;>
 8029 getfield #654 <as/W B>
 8032 baload
 8033 imul
 8034 iadd
 8035 i2s
 8036 putfield #658 <l/try S>
 8039 aload_0
 8040 getfield #19 <g/bh Lh;>
 8043 getfield #462 <h/S Las;>
 8046 iconst_0
 8047 putfield #653 <as/aB S>
 8050 goto 8123 (+73)
 8053 aload_0
 8054 getfield #19 <g/bh Lh;>
 8057 getfield #462 <h/S Las;>
 8060 getfield #656 <as/aD Ll;>
 8063 dup
 8064 getfield #658 <l/try S>
 8067 aload_0
 8068 getfield #19 <g/bh Lh;>
 8071 getfield #462 <h/S Las;>
 8074 getfield #655 <as/ac B>
 8077 getstatic #659 <a3/bq [B>
 8080 aload_0
 8081 getfield #19 <g/bh Lh;>
 8084 getfield #462 <h/S Las;>
 8087 getfield #654 <as/W B>
 8090 baload
 8091 imul
 8092 iadd
 8093 i2s
 8094 putfield #658 <l/try S>
 8097 aload_0
 8098 getfield #19 <g/bh Lh;>
 8101 getfield #462 <h/S Las;>
 8104 dup
 8105 getfield #653 <as/aB S>
 8108 aload_0
 8109 getfield #19 <g/bh Lh;>
 8112 getfield #462 <h/S Las;>
 8115 getfield #655 <as/ac B>
 8118 isub
 8119 i2s
 8120 putfield #653 <as/aB S>
 8123 goto 11999 (+3876)
 8126 aload_0
 8127 getfield #19 <g/bh Lh;>
 8130 getfield #660 <h/bV Lx;>
 8133 aload_0
 8134 getfield #19 <g/bh Lh;>
 8137 getfield #462 <h/S Las;>
 8140 getfield #661 <as/ar B>
 8143 iconst_0
 8144 aload_0
 8145 getfield #19 <g/bh Lh;>
 8148 getfield #462 <h/S Las;>
 8151 getfield #656 <as/aD Ll;>
 8154 getfield #662 <l/a [I>
 8157 invokevirtual #293 <x/a(II[I)V>
 8160 aload_0
 8161 getfield #19 <g/bh Lh;>
 8164 getfield #462 <h/S Las;>
 8167 invokevirtual #663 <as/a()V>
 8170 goto 11999 (+3829)
 8173 aload_0
 8174 invokevirtual #467 <g/E()V>
 8177 aload_0
 8178 getfield #19 <g/bh Lh;>
 8181 getfield #462 <h/S Las;>
 8184 getfield #656 <as/aD Ll;>
 8187 getfield #662 <l/a [I>
 8190 iconst_4
 8191 iaload
 8192 ifne 11999 (+3807)
 8195 aload_0
 8196 getfield #19 <g/bh Lh;>
 8199 getfield #462 <h/S Las;>
 8202 getfield #656 <as/aD Ll;>
 8205 getfield #662 <l/a [I>
 8208 iconst_4
 8209 iconst_1
 8210 iastore
 8211 aload_0
 8212 getfield #19 <g/bh Lh;>
 8215 getfield #462 <h/S Las;>
 8218 dup
 8219 getfield #664 <as/G B>
 8222 iconst_1
 8223 iadd
 8224 i2b
 8225 putfield #664 <as/G B>
 8228 aload_0
 8229 getfield #19 <g/bh Lh;>
 8232 getfield #462 <h/S Las;>
 8235 getfield #664 <as/G B>
 8238 aload_0
 8239 getfield #19 <g/bh Lh;>
 8242 getfield #462 <h/S Las;>
 8245 getfield #665 <as/aQ B>
 8248 if_icmplt 11999 (+3751)
 8251 aload_0
 8252 getfield #19 <g/bh Lh;>
 8255 getfield #660 <h/bV Lx;>
 8258 aload_0
 8259 getfield #19 <g/bh Lh;>
 8262 getfield #462 <h/S Las;>
 8265 getfield #661 <as/ar B>
 8268 iconst_0
 8269 aload_0
 8270 getfield #19 <g/bh Lh;>
 8273 getfield #462 <h/S Las;>
 8276 getfield #656 <as/aD Ll;>
 8279 getfield #662 <l/a [I>
 8282 invokevirtual #293 <x/a(II[I)V>
 8285 aload_0
 8286 getfield #19 <g/bh Lh;>
 8289 getfield #462 <h/S Las;>
 8292 invokevirtual #663 <as/a()V>
 8295 goto 11999 (+3704)
 8298 aload_0
 8299 invokevirtual #467 <g/E()V>
 8302 aload_0
 8303 getfield #19 <g/bh Lh;>
 8306 getfield #462 <h/S Las;>
 8309 getfield #653 <as/aB S>
 8312 ifeq 8704 (+392)
 8315 aload_0
 8316 getfield #19 <g/bh Lh;>
 8319 getfield #462 <h/S Las;>
 8322 getfield #655 <as/ac B>
 8325 ifle 8704 (+379)
 8328 aload_0
 8329 getfield #19 <g/bh Lh;>
 8332 getfield #462 <h/S Las;>
 8335 getfield #654 <as/W B>
 8338 tableswitch 0 to 3
             0:  8368 (+30)
             1:  8523 (+185)
             2:  8368 (+30)
             3:  8523 (+185)
             default:  8675 (+337)
 8368 aload_0
 8369 getfield #19 <g/bh Lh;>
 8372 getfield #462 <h/S Las;>
 8375 getfield #653 <as/aB S>
 8378 aload_0
 8379 getfield #19 <g/bh Lh;>
 8382 getfield #462 <h/S Las;>
 8385 getfield #655 <as/ac B>
 8388 isub
 8389 ifgt 8450 (+61)
 8392 aload_0
 8393 getfield #19 <g/bh Lh;>
 8396 getfield #462 <h/S Las;>
 8399 getfield #656 <as/aD Ll;>
 8402 dup
 8403 getfield #249 <l/new S>
 8406 aload_0
 8407 getfield #19 <g/bh Lh;>
 8410 getfield #462 <h/S Las;>
 8413 getfield #653 <as/aB S>
 8416 getstatic #657 <a3/bp [B>
 8419 aload_0
 8420 getfield #19 <g/bh Lh;>
 8423 getfield #462 <h/S Las;>
 8426 getfield #654 <as/W B>
 8429 baload
 8430 imul
 8431 iadd
 8432 i2s
 8433 putfield #249 <l/new S>
 8436 aload_0
 8437 getfield #19 <g/bh Lh;>
 8440 getfield #462 <h/S Las;>
 8443 iconst_0
 8444 putfield #653 <as/aB S>
 8447 goto 8675 (+228)
 8450 aload_0
 8451 getfield #19 <g/bh Lh;>
 8454 getfield #462 <h/S Las;>
 8457 getfield #656 <as/aD Ll;>
 8460 dup
 8461 getfield #249 <l/new S>
 8464 aload_0
 8465 getfield #19 <g/bh Lh;>
 8468 getfield #462 <h/S Las;>
 8471 getfield #655 <as/ac B>
 8474 getstatic #657 <a3/bp [B>
 8477 aload_0
 8478 getfield #19 <g/bh Lh;>
 8481 getfield #462 <h/S Las;>
 8484 getfield #654 <as/W B>
 8487 baload
 8488 imul
 8489 iadd
 8490 i2s
 8491 putfield #249 <l/new S>
 8494 aload_0
 8495 getfield #19 <g/bh Lh;>
 8498 getfield #462 <h/S Las;>
 8501 dup
 8502 getfield #653 <as/aB S>
 8505 aload_0
 8506 getfield #19 <g/bh Lh;>
 8509 getfield #462 <h/S Las;>
 8512 getfield #655 <as/ac B>
 8515 isub
 8516 i2s
 8517 putfield #653 <as/aB S>
 8520 goto 8675 (+155)
 8523 aload_0
 8524 getfield #19 <g/bh Lh;>
 8527 getfield #462 <h/S Las;>
 8530 getfield #653 <as/aB S>
 8533 aload_0
 8534 getfield #19 <g/bh Lh;>
 8537 getfield #462 <h/S Las;>
 8540 getfield #655 <as/ac B>
 8543 isub
 8544 ifgt 8605 (+61)
 8547 aload_0
 8548 getfield #19 <g/bh Lh;>
 8551 getfield #462 <h/S Las;>
 8554 getfield #656 <as/aD Ll;>
 8557 dup
 8558 getfield #658 <l/try S>
 8561 aload_0
 8562 getfield #19 <g/bh Lh;>
 8565 getfield #462 <h/S Las;>
 8568 getfield #653 <as/aB S>
 8571 getstatic #659 <a3/bq [B>
 8574 aload_0
 8575 getfield #19 <g/bh Lh;>
 8578 getfield #462 <h/S Las;>
 8581 getfield #654 <as/W B>
 8584 baload
 8585 imul
 8586 iadd
 8587 i2s
 8588 putfield #658 <l/try S>
 8591 aload_0
 8592 getfield #19 <g/bh Lh;>
 8595 getfield #462 <h/S Las;>
 8598 iconst_0
 8599 putfield #653 <as/aB S>
 8602 goto 8675 (+73)
 8605 aload_0
 8606 getfield #19 <g/bh Lh;>
 8609 getfield #462 <h/S Las;>
 8612 getfield #656 <as/aD Ll;>
 8615 dup
 8616 getfield #658 <l/try S>
 8619 aload_0
 8620 getfield #19 <g/bh Lh;>
 8623 getfield #462 <h/S Las;>
 8626 getfield #655 <as/ac B>
 8629 getstatic #659 <a3/bq [B>
 8632 aload_0
 8633 getfield #19 <g/bh Lh;>
 8636 getfield #462 <h/S Las;>
 8639 getfield #654 <as/W B>
 8642 baload
 8643 imul
 8644 iadd
 8645 i2s
 8646 putfield #658 <l/try S>
 8649 aload_0
 8650 getfield #19 <g/bh Lh;>
 8653 getfield #462 <h/S Las;>
 8656 dup
 8657 getfield #653 <as/aB S>
 8660 aload_0
 8661 getfield #19 <g/bh Lh;>
 8664 getfield #462 <h/S Las;>
 8667 getfield #655 <as/ac B>
 8670 isub
 8671 i2s
 8672 putfield #653 <as/aB S>
 8675 aload_0
 8676 getfield #19 <g/bh Lh;>
 8679 getfield #462 <h/S Las;>
 8682 dup
 8683 getfield #655 <as/ac B>
 8686 aload_0
 8687 getfield #19 <g/bh Lh;>
 8690 getfield #462 <h/S Las;>
 8693 getfield #666 <as/S B>
 8696 iadd
 8697 i2b
 8698 putfield #655 <as/ac B>
 8701 goto 11999 (+3298)
 8704 aload_0
 8705 getfield #19 <g/bh Lh;>
 8708 getfield #660 <h/bV Lx;>
 8711 aload_0
 8712 getfield #19 <g/bh Lh;>
 8715 getfield #462 <h/S Las;>
 8718 getfield #661 <as/ar B>
 8721 iconst_0
 8722 aload_0
 8723 getfield #19 <g/bh Lh;>
 8726 getfield #462 <h/S Las;>
 8729 getfield #656 <as/aD Ll;>
 8732 getfield #662 <l/a [I>
 8735 invokevirtual #293 <x/a(II[I)V>
 8738 aload_0
 8739 getfield #19 <g/bh Lh;>
 8742 getfield #462 <h/S Las;>
 8745 invokevirtual #663 <as/a()V>
 8748 goto 11999 (+3251)
 8751 aload_0
 8752 invokevirtual #467 <g/E()V>
 8755 aload_0
 8756 getfield #19 <g/bh Lh;>
 8759 aload_0
 8760 getfield #19 <g/bh Lh;>
 8763 getfield #462 <h/S Las;>
 8766 getfield #667 <as/C Ljava/lang/String;>
 8769 getstatic #296 <g/gf B>
 8772 iconst_4
 8773 iconst_0
 8774 invokevirtual #416 <h/a(Ljava/lang/String;IBZ)Z>
 8777 ifeq 11999 (+3222)
 8780 aload_0
 8781 bipush 63
 8783 putfield #297 <ap/do S>
 8786 goto 11999 (+3213)
 8789 aload_0
 8790 aload_0
 8791 getfield #19 <g/bh Lh;>
 8794 getfield #462 <h/S Las;>
 8797 getfield #668 <as/av B>
 8800 putfield #418 <g/e3 B>
 8803 aload_0
 8804 aload_0
 8805 getfield #19 <g/bh Lh;>
 8808 getfield #462 <h/S Las;>
 8811 getfield #667 <as/C Ljava/lang/String;>
 8814 aload_0
 8815 getfield #19 <g/bh Lh;>
 8818 getfield #462 <h/S Las;>
 8821 getfield #669 <as/ai [Ljava/lang/String;>
 8824 iconst_0
 8825 aaload
 8826 aload_0
 8827 getfield #19 <g/bh Lh;>
 8830 getfield #462 <h/S Las;>
 8833 getfield #669 <as/ai [Ljava/lang/String;>
 8836 iconst_1
 8837 aaload
 8838 invokevirtual #471 <g/a(Ljava/lang/String;Ljava/lang/String;Ljava/lang/String;)V>
 8841 goto 11999 (+3158)
 8844 aload_0
 8845 getfield #19 <g/bh Lh;>
 8848 getfield #250 <h/cZ Lag;>
 8851 pop
 8852 getstatic #324 <ag/hF S>
 8855 iflt 8932 (+77)
 8858 aload_0
 8859 getfield #19 <g/bh Lh;>
 8862 getfield #250 <h/cZ Lag;>
 8865 pop
 8866 getstatic #325 <ag/hE S>
 8869 iflt 8932 (+63)
 8872 aload_0
 8873 getfield #19 <g/bh Lh;>
 8876 getfield #250 <h/cZ Lag;>
 8879 pop
 8880 getstatic #324 <ag/hF S>
 8883 aload_0
 8884 getfield #19 <g/bh Lh;>
 8887 pop
 8888 getstatic #319 <h/dU S>
 8891 iadd
 8892 aload_0
 8893 getfield #19 <g/bh Lh;>
 8896 getfield #464 <h/ad S>
 8899 if_icmpgt 8932 (+33)
 8902 aload_0
 8903 getfield #19 <g/bh Lh;>
 8906 getfield #250 <h/cZ Lag;>
 8909 pop
 8910 getstatic #325 <ag/hE S>
 8913 aload_0
 8914 getfield #19 <g/bh Lh;>
 8917 pop
 8918 getstatic #20 <h/fp S>
 8921 iadd
 8922 aload_0
 8923 getfield #19 <g/bh Lh;>
 8926 getfield #465 <h/dz S>
 8929 if_icmple 8943 (+14)
 8932 aload_0
 8933 getfield #19 <g/bh Lh;>
 8936 getfield #462 <h/S Las;>
 8939 iconst_0
 8940 putfield #670 <as/aC S>
 8943 aload_0
 8944 getfield #19 <g/bh Lh;>
 8947 getfield #462 <h/S Las;>
 8950 getfield #670 <as/aC S>
 8953 ifeq 9298 (+345)
 8956 aload_0
 8957 getfield #19 <g/bh Lh;>
 8960 getfield #250 <h/cZ Lag;>
 8963 getfield #671 <ag/eO B>
 8966 tableswitch 0 to 3
             0:  8996 (+30)
             1:  9145 (+179)
             2:  8996 (+30)
             3:  9145 (+179)
             default:  9291 (+325)
 8996 aload_0
 8997 getfield #19 <g/bh Lh;>
 9000 getfield #462 <h/S Las;>
 9003 getfield #670 <as/aC S>
 9006 aload_0
 9007 getfield #19 <g/bh Lh;>
 9010 getfield #462 <h/S Las;>
 9013 getfield #672 <as/D B>
 9016 isub
 9017 ifle 9090 (+73)
 9020 aload_0
 9021 getfield #19 <g/bh Lh;>
 9024 getfield #250 <h/cZ Lag;>
 9027 pop
 9028 getstatic #325 <ag/hE S>
 9031 aload_0
 9032 getfield #19 <g/bh Lh;>
 9035 getfield #462 <h/S Las;>
 9038 getfield #672 <as/D B>
 9041 getstatic #657 <a3/bp [B>
 9044 aload_0
 9045 getfield #19 <g/bh Lh;>
 9048 getfield #462 <h/S Las;>
 9051 getfield #673 <as/A B>
 9054 baload
 9055 imul
 9056 iadd
 9057 i2s
 9058 putstatic #325 <ag/hE S>
 9061 aload_0
 9062 getfield #19 <g/bh Lh;>
 9065 getfield #462 <h/S Las;>
 9068 dup
 9069 getfield #670 <as/aC S>
 9072 aload_0
 9073 getfield #19 <g/bh Lh;>
 9076 getfield #462 <h/S Las;>
 9079 getfield #672 <as/D B>
 9082 isub
 9083 i2s
 9084 putfield #670 <as/aC S>
 9087 goto 9291 (+204)
 9090 aload_0
 9091 getfield #19 <g/bh Lh;>
 9094 getfield #250 <h/cZ Lag;>
 9097 pop
 9098 getstatic #325 <ag/hE S>
 9101 aload_0
 9102 getfield #19 <g/bh Lh;>
 9105 getfield #462 <h/S Las;>
 9108 getfield #670 <as/aC S>
 9111 getstatic #657 <a3/bp [B>
 9114 aload_0
 9115 getfield #19 <g/bh Lh;>
 9118 getfield #462 <h/S Las;>
 9121 getfield #673 <as/A B>
 9124 baload
 9125 imul
 9126 iadd
 9127 i2s
 9128 putstatic #325 <ag/hE S>
 9131 aload_0
 9132 getfield #19 <g/bh Lh;>
 9135 getfield #462 <h/S Las;>
 9138 iconst_0
 9139 putfield #670 <as/aC S>
 9142 goto 9291 (+149)
 9145 aload_0
 9146 getfield #19 <g/bh Lh;>
 9149 getfield #462 <h/S Las;>
 9152 getfield #670 <as/aC S>
 9155 aload_0
 9156 getfield #19 <g/bh Lh;>
 9159 getfield #462 <h/S Las;>
 9162 getfield #672 <as/D B>
 9165 isub
 9166 ifle 9239 (+73)
 9169 aload_0
 9170 getfield #19 <g/bh Lh;>
 9173 getfield #250 <h/cZ Lag;>
 9176 pop
 9177 getstatic #324 <ag/hF S>
 9180 aload_0
 9181 getfield #19 <g/bh Lh;>
 9184 getfield #462 <h/S Las;>
 9187 getfield #672 <as/D B>
 9190 getstatic #659 <a3/bq [B>
 9193 aload_0
 9194 getfield #19 <g/bh Lh;>
 9197 getfield #462 <h/S Las;>
 9200 getfield #673 <as/A B>
 9203 baload
 9204 imul
 9205 iadd
 9206 i2s
 9207 putstatic #324 <ag/hF S>
 9210 aload_0
 9211 getfield #19 <g/bh Lh;>
 9214 getfield #462 <h/S Las;>
 9217 dup
 9218 getfield #670 <as/aC S>
 9221 aload_0
 9222 getfield #19 <g/bh Lh;>
 9225 getfield #462 <h/S Las;>
 9228 getfield #672 <as/D B>
 9231 isub
 9232 i2s
 9233 putfield #670 <as/aC S>
 9236 goto 9291 (+55)
 9239 aload_0
 9240 getfield #19 <g/bh Lh;>
 9243 getfield #250 <h/cZ Lag;>
 9246 pop
 9247 getstatic #324 <ag/hF S>
 9250 aload_0
 9251 getfield #19 <g/bh Lh;>
 9254 getfield #462 <h/S Las;>
 9257 getfield #670 <as/aC S>
 9260 getstatic #659 <a3/bq [B>
 9263 aload_0
 9264 getfield #19 <g/bh Lh;>
 9267 getfield #462 <h/S Las;>
 9270 getfield #673 <as/A B>
 9273 baload
 9274 imul
 9275 iadd
 9276 i2s
 9277 putstatic #324 <ag/hF S>
 9280 aload_0
 9281 getfield #19 <g/bh Lh;>
 9284 getfield #462 <h/S Las;>
 9287 iconst_0
 9288 putfield #670 <as/aC S>
 9291 aload_0
 9292 invokevirtual #467 <g/E()V>
 9295 goto 11999 (+2704)
 9298 aload_0
 9299 getfield #19 <g/bh Lh;>
 9302 getfield #462 <h/S Las;>
 9305 invokevirtual #663 <as/a()V>
 9308 goto 11999 (+2691)
 9311 aload_0
 9312 getfield #19 <g/bh Lh;>
 9315 getfield #674 <h/ex Laj;>
 9318 invokevirtual #675 <aj/a()V>
 9321 goto 11999 (+2678)
 9324 aload_0
 9325 getfield #19 <g/bh Lh;>
 9328 getfield #676 <h/dJ Lo;>
 9331 invokevirtual #677 <o/a()V>
 9334 goto 11999 (+2665)
 9337 aload_0
 9338 getfield #154 <g/jj Ln;>
 9341 invokevirtual #678 <n/a()V>
 9344 goto 11999 (+2655)
 9347 aload_0
 9348 getfield #19 <g/bh Lh;>
 9351 ldc_w #679 <退出中,请稍候...>
 9354 invokevirtual #561 <h/k(Ljava/lang/String;)V>
 9357 goto 11999 (+2642)
 9360 aload_0
 9361 invokevirtual #467 <g/E()V>
 9364 aload_0
 9365 getfield #19 <g/bh Lh;>
 9368 aload_0
 9369 getfield #680 <g/h7 Ljava/lang/String;>
 9372 getstatic #296 <g/gf B>
 9375 iconst_4
 9376 iconst_0
 9377 invokevirtual #416 <h/a(Ljava/lang/String;IBZ)Z>
 9380 ifeq 11999 (+2619)
 9383 aload_0
 9384 getfield #681 <ap/if S>
 9387 iconst_2
 9388 if_icmpne 9420 (+32)
 9391 aload_0
 9392 getfield #680 <g/h7 Ljava/lang/String;>
 9395 ldc_w #682 <疾冲>
 9398 invokevirtual #683 <java/lang/String/indexOf(Ljava/lang/String;)I>
 9401 iconst_m1
 9402 if_icmpeq 9420 (+18)
 9405 aload_0
 9406 iconst_2
 9407 putfield #684 <g/je B>
 9410 aload_0
 9411 iconst_0
 9412 putfield #11 <g/kc B>
 9415 aload_0
 9416 iconst_0
 9417 putfield #9 <g/int I>
 9420 aload_0
 9421 aconst_null
 9422 putfield #680 <g/h7 Ljava/lang/String;>
 9425 aload_0
 9426 getfield #19 <g/bh Lh;>
 9429 getfield #462 <h/S Las;>
 9432 invokevirtual #663 <as/a()V>
 9435 goto 11999 (+2564)
 9438 aload_0
 9439 getfield #19 <g/bh Lh;>
 9442 getfield #320 <h/fj Ljavax/microedition/lcdui/Graphics;>
 9445 aload_0
 9446 getfield #19 <g/bh Lh;>
 9449 pop
 9450 getstatic #321 <h/b2 [[I>
 9453 aload_0
 9454 getfield #19 <g/bh Lh;>
 9457 pop
 9458 iconst_3
 9459 aaload
 9460 iconst_1
 9461 iaload
 9462 invokevirtual #322 <javax/microedition/lcdui/Graphics/setColor(I)V>
 9465 aload_0
 9466 getfield #19 <g/bh Lh;>
 9469 getfield #320 <h/fj Ljavax/microedition/lcdui/Graphics;>
 9472 iconst_0
 9473 iconst_0
 9474 aload_0
 9475 getfield #19 <g/bh Lh;>
 9478 pop
 9479 getstatic #319 <h/dU S>
 9482 aload_0
 9483 getfield #19 <g/bh Lh;>
 9486 pop
 9487 getstatic #20 <h/fp S>
 9490 invokevirtual #411 <javax/microedition/lcdui/Graphics/fillRect(IIII)V>
 9493 aload_0
 9494 getfield #19 <g/bh Lh;>
 9497 aload_0
 9498 getfield #685 <g/fS Ljava/lang/String;>
 9501 getstatic #296 <g/gf B>
 9504 iconst_4
 9505 iconst_0
 9506 invokevirtual #416 <h/a(Ljava/lang/String;IBZ)Z>
 9509 ifeq 11999 (+2490)
 9512 aload_0
 9513 getfield #686 <g/ns B>
 9516 ifne 9527 (+11)
 9519 aload_0
 9520 iconst_0
 9521 putfield #297 <ap/do S>
 9524 goto 11999 (+2475)
 9527 aload_0
 9528 getfield #19 <g/bh Lh;>
 9531 getfield #270 <h/fG LSFMIDlet;>
 9534 new #401 <java/lang/StringBuffer>
 9537 dup
 9538 invokespecial #402 <java/lang/StringBuffer/<init>()V>
 9541 ldc_w #687 <http://gameta.cn/sot_bill_index.jsp?owner=1&user=>
 9544 invokevirtual #404 <java/lang/StringBuffer/append(Ljava/lang/String;)Ljava/lang/StringBuffer;>
 9547 aload_0
 9548 getfield #19 <g/bh Lh;>
 9551 getfield #688 <h/dv Ljava/lang/String;>
 9554 invokevirtual #404 <java/lang/StringBuffer/append(Ljava/lang/String;)Ljava/lang/StringBuffer;>
 9557 ldc_w #689 <&zone=>
 9560 invokevirtual #404 <java/lang/StringBuffer/append(Ljava/lang/String;)Ljava/lang/StringBuffer;>
 9563 aload_0
 9564 getfield #19 <g/bh Lh;>
 9567 getfield #690 <h/fA B>
 9570 invokevirtual #489 <java/lang/StringBuffer/append(I)Ljava/lang/StringBuffer;>
 9573 invokevirtual #405 <java/lang/StringBuffer/toString()Ljava/lang/String;>
 9576 invokevirtual #691 <javax/microedition/midlet/MIDlet/platformRequest(Ljava/lang/String;)Z>
 9579 pop
 9580 aload_0
 9581 invokevirtual #635 <g/J()V>
 9584 goto 11999 (+2415)
 9587 astore 7
 9589 goto 11999 (+2410)
 9592 aload_0
 9593 getfield #19 <g/bh Lh;>
 9596 getfield #320 <h/fj Ljavax/microedition/lcdui/Graphics;>
 9599 aload_0
 9600 getfield #19 <g/bh Lh;>
 9603 pop
 9604 getstatic #321 <h/b2 [[I>
 9607 aload_0
 9608 getfield #19 <g/bh Lh;>
 9611 pop
 9612 iconst_3
 9613 aaload
 9614 iconst_1
 9615 iaload
 9616 invokevirtual #322 <javax/microedition/lcdui/Graphics/setColor(I)V>
 9619 aload_0
 9620 getfield #19 <g/bh Lh;>
 9623 getfield #320 <h/fj Ljavax/microedition/lcdui/Graphics;>
 9626 iconst_0
 9627 iconst_0
 9628 aload_0
 9629 getfield #19 <g/bh Lh;>
 9632 pop
 9633 getstatic #319 <h/dU S>
 9636 aload_0
 9637 getfield #19 <g/bh Lh;>
 9640 pop
 9641 getstatic #20 <h/fp S>
 9644 invokevirtual #411 <javax/microedition/lcdui/Graphics/fillRect(IIII)V>
 9647 aload_0
 9648 getfield #19 <g/bh Lh;>
 9651 ldc_w #693 <网络超时!请重新登录.>
 9654 getstatic #296 <g/gf B>
 9657 iconst_4
 9658 iconst_0
 9659 invokevirtual #416 <h/a(Ljava/lang/String;IBZ)Z>
 9662 ifeq 11999 (+2337)
 9665 aload_0
 9666 getfield #694 <g/gz Z>
 9669 ifeq 9690 (+21)
 9672 aload_0
 9673 getfield #19 <g/bh Lh;>
 9676 aload_0
 9677 aload_0
 9678 getfield #19 <g/bh Lh;>
 9681 getfield #617 <h/s Ly;>
 9684 invokevirtual #618 <h/a(Lap;Lap;)V>
 9687 goto 11999 (+2312)
 9690 aload_0
 9691 invokevirtual #635 <g/J()V>
 9694 goto 11999 (+2305)
 9697 aload_0
 9698 ldc_w #695 <需要休息?>
 9701 ldc_w #469 <是>
 9704 ldc_w #470 <否>
 9707 invokevirtual #471 <g/a(Ljava/lang/String;Ljava/lang/String;Ljava/lang/String;)V>
 9710 goto 11999 (+2289)
 9713 aload_0
 9714 dup
 9715 getfield #696 <g/c3 B>
 9718 iconst_1
 9719 iadd
 9720 i2b
 9721 putfield #696 <g/c3 B>
 9724 aload_0
 9725 getfield #696 <g/c3 B>
 9728 bipush 15
 9730 if_icmple 9821 (+91)
 9733 aload_0
 9734 iconst_0
 9735 putfield #696 <g/c3 B>
 9738 iconst_0
 9739 istore 7
 9741 iload 7
 9743 aload_0
 9744 getfield #19 <g/bh Lh;>
 9747 pop
 9748 getstatic #319 <h/dU S>
 9751 if_icmpge 9770 (+19)
 9754 aload_0
 9755 getfield #133 <g/bZ [I>
 9758 iload 7
 9760 ldc_w #697 <-16777216>
 9763 iastore
 9764 iinc 7 by 1
 9767 goto 9741 (-26)
 9770 aload_0
 9771 getfield #19 <g/bh Lh;>
 9774 getfield #250 <h/cZ Lag;>
 9777 invokevirtual #698 <ag/N()V>
 9780 aload_0
 9781 getfield #19 <g/bh Lh;>
 9784 getfield #250 <h/cZ Lag;>
 9787 getstatic #699 <ag/g2 I>
 9790 getstatic #700 <a/t I>
 9793 invokestatic #701 <a3/new(II)I>
 9796 putfield #702 <ag/hh I>
 9799 aload_0
 9800 getfield #19 <g/bh Lh;>
 9803 getfield #250 <h/cZ Lag;>
 9806 invokevirtual #703 <ag/d()V>
 9809 aload_0
 9810 getfield #19 <g/bh Lh;>
 9813 getfield #250 <h/cZ Lag;>
 9816 iconst_2
 9817 putfield #704 <a3/try B>
 9820 return
 9821 iconst_0
 9822 istore 7
 9824 iload 7
 9826 aload_0
 9827 getfield #19 <g/bh Lh;>
 9830 pop
 9831 getstatic #319 <h/dU S>
 9834 if_icmpge 9856 (+22)
 9837 aload_0
 9838 getfield #133 <g/bZ [I>
 9841 iload 7
 9843 dup2
 9844 iaload
 9845 ldc_w #705 <285212672>
 9848 iadd
 9849 iastore
 9850 iinc 7 by 1
 9853 goto 9824 (-29)
 9856 aload_0
 9857 getfield #19 <g/bh Lh;>
 9860 aload_0
 9861 getfield #133 <g/bZ [I>
 9864 iconst_0
 9865 iconst_0
 9866 aload_0
 9867 getfield #19 <g/bh Lh;>
 9870 pop
 9871 getstatic #319 <h/dU S>
 9874 aload_0
 9875 getfield #19 <g/bh Lh;>
 9878 pop
 9879 getstatic #20 <h/fp S>
 9882 invokevirtual #706 <h/a([IIIII)V>
 9885 goto 11999 (+2114)
 9888 aload_0
 9889 invokevirtual #467 <g/E()V>
 9892 aload_0
 9893 dup
 9894 getfield #696 <g/c3 B>
 9897 iconst_1
 9898 iadd
 9899 i2b
 9900 putfield #696 <g/c3 B>
 9903 aload_0
 9904 getfield #696 <g/c3 B>
 9907 bipush 6
 9909 if_icmple 9925 (+16)
 9912 aload_0
 9913 aload_0
 9914 pop
 9915 iconst_0
 9916 putfield #297 <ap/do S>
 9919 aload_0
 9920 aconst_null
 9921 putfield #133 <g/bZ [I>
 9924 return
 9925 iconst_0
 9926 istore 7
 9928 iload 7
 9930 aload_0
 9931 getfield #19 <g/bh Lh;>
 9934 pop
 9935 getstatic #319 <h/dU S>
 9938 if_icmpge 9960 (+22)
 9941 aload_0
 9942 getfield #133 <g/bZ [I>
 9945 iload 7
 9947 dup2
 9948 iaload
 9949 ldc_w #707 <570425344>
 9952 isub
 9953 iastore
 9954 iinc 7 by 1
 9957 goto 9928 (-29)
 9960 aload_0
 9961 getfield #19 <g/bh Lh;>
 9964 aload_0
 9965 getfield #133 <g/bZ [I>
 9968 iconst_0
 9969 iconst_0
 9970 aload_0
 9971 getfield #19 <g/bh Lh;>
 9974 pop
 9975 getstatic #319 <h/dU S>
 9978 aload_0
 9979 getfield #19 <g/bh Lh;>
 9982 pop
 9983 getstatic #20 <h/fp S>
 9986 invokevirtual #706 <h/a([IIIII)V>
 9989 goto 11999 (+2010)
 9992 aload_0
 9993 getfield #136 <g/g7 Ls;>
 9996 invokevirtual #708 <s/if()V>
 9999 goto 11999 (+2000)
10002 aload_0
10003 invokevirtual #467 <g/E()V>
10006 aload_0
10007 getfield #19 <g/bh Lh;>
10010 getfield #320 <h/fj Ljavax/microedition/lcdui/Graphics;>
10013 ldc_w #614 <16777215>
10016 invokevirtual #322 <javax/microedition/lcdui/Graphics/setColor(I)V>
10019 aload_0
10020 getfield #19 <g/bh Lh;>
10023 getfield #320 <h/fj Ljavax/microedition/lcdui/Graphics;>
10026 iconst_0
10027 aload_0
10028 getfield #19 <g/bh Lh;>
10031 pop
10032 getstatic #20 <h/fp S>
10035 iconst_2
10036 idiv
10037 aload_0
10038 getfield #19 <g/bh Lh;>
10041 pop
10042 getstatic #319 <h/dU S>
10045 bipush 20
10047 invokevirtual #411 <javax/microedition/lcdui/Graphics/fillRect(IIII)V>
10050 aload_0
10051 getfield #19 <g/bh Lh;>
10054 getfield #320 <h/fj Ljavax/microedition/lcdui/Graphics;>
10057 iconst_0
10058 invokevirtual #322 <javax/microedition/lcdui/Graphics/setColor(I)V>
10061 aload_0
10062 getfield #19 <g/bh Lh;>
10065 getfield #320 <h/fj Ljavax/microedition/lcdui/Graphics;>
10068 ldc_w #709 <任务失败>
10071 aload_0
10072 getfield #19 <g/bh Lh;>
10075 pop
10076 getstatic #319 <h/dU S>
10079 iconst_2
10080 idiv
10081 aload_0
10082 getfield #19 <g/bh Lh;>
10085 pop
10086 getstatic #20 <h/fp S>
10089 iconst_2
10090 idiv
10091 iconst_1
10092 iadd
10093 bipush 17
10095 invokevirtual #390 <javax/microedition/lcdui/Graphics/drawString(Ljava/lang/String;III)V>
10098 goto 11999 (+1901)
10101 aload_0
10102 getfield #137 <g/md Lae;>
10105 invokevirtual #647 <ae/for()V>
10108 goto 11999 (+1891)
10111 aload_0
10112 invokevirtual #467 <g/E()V>
10115 aload_0
10116 getfield #19 <g/bh Lh;>
10119 invokevirtual #473 <h/c()V>
10122 goto 11999 (+1877)
10125 aload_0
10126 invokevirtual #467 <g/E()V>
10129 aload_0
10130 getfield #138 <g/eZ Lt;>
10133 invokevirtual #710 <t/a()V>
10136 aload_0
10137 getfield #19 <g/bh Lh;>
10140 bipush 72
10142 iconst_0
10143 aload_0
10144 getfield #51 <g/gd B>
10147 aload_0
10148 pop
10149 getstatic #711 <g/b2 [Ljava/lang/String;>
10152 invokevirtual #494 <h/a(IIB[Ljava/lang/String;)V>
10155 goto 11999 (+1844)
10158 aload_0
10159 invokevirtual #467 <g/E()V>
10162 aload_0
10163 getfield #19 <g/bh Lh;>
10166 iconst_2
10167 iconst_0
10168 iconst_0
10169 aload_0
10170 getfield #19 <g/bh Lh;>
10173 pop
10174 getstatic #319 <h/dU S>
10177 aload_0
10178 getfield #19 <g/bh Lh;>
10181 pop
10182 getstatic #20 <h/fp S>
10185 iconst_0
10186 invokevirtual #370 <h/a(BIIIIZ)V>
10189 aload_0
10190 getfield #138 <g/eZ Lt;>
10193 invokevirtual #710 <t/a()V>
10196 aload_0
10197 getfield #712 <g/mz B>
10200 ifne 10232 (+32)
10203 aload_0
10204 getfield #19 <g/bh Lh;>
10207 getfield #250 <h/cZ Lag;>
10210 bipush 36
10212 invokevirtual #288 <a3/a(B)I>
10215 ifgt 10225 (+10)
10218 aload_0
10219 getfield #7 <g/gn Ljavax/microedition/lcdui/Image;>
10222 ifnull 10232 (+10)
10225 aload_0
10226 getfield #19 <g/bh Lh;>
10229 invokevirtual #472 <h/x()V>
10232 aload_0
10233 getfield #19 <g/bh Lh;>
10236 invokevirtual #473 <h/c()V>
10239 goto 11999 (+1760)
10242 aload_0
10243 getfield #299 <g/j0 B>
10246 ifne 10263 (+17)
10249 aload_0
10250 getfield #19 <g/bh Lh;>
10253 aload_0
10254 getfield #101 <g/kh Ljava/lang/String;>
10257 invokevirtual #561 <h/k(Ljava/lang/String;)V>
10260 goto 10284 (+24)
10263 aload_0
10264 invokevirtual #467 <g/E()V>
10267 aload_0
10268 getfield #19 <g/bh Lh;>
10271 aload_0
10272 getfield #101 <g/kh Ljava/lang/String;>
10275 iconst_m1
10276 aload_0
10277 pop
10278 iconst_4
10279 iconst_0
10280 invokevirtual #416 <h/a(Ljava/lang/String;IBZ)Z>
10283 pop
10284 aload_0
10285 getfield #713 <g/j5 Z>
10288 ifne 10697 (+409)
10291 aload_0
10292 iconst_m1
10293 putfield #714 <g/ca B>
10296 aload_0
10297 iconst_0
10298 putfield #10 <g/gR I>
10301 aload_0
10302 iconst_1
10303 putfield #713 <g/j5 Z>
10306 aload_0
10307 getfield #19 <g/bh Lh;>
10310 pop
10311 getstatic #715 <h/dc Z>
10314 ifeq 10340 (+26)
10317 aload_0
10318 getfield #19 <g/bh Lh;>
10321 aload_0
10322 getfield #681 <ap/if S>
10325 invokevirtual #716 <h/F(S)I>
10328 iconst_m1
10329 if_icmple 10340 (+11)
10332 aload_0
10333 iconst_1
10334 putfield #717 <g/jl Z>
10337 goto 10364 (+27)
10340 aload_0
10341 getfield #19 <g/bh Lh;>
10344 aload_0
10345 getfield #681 <ap/if S>
10348 invokevirtual #718 <h/c(S)Z>
10351 ifeq 10364 (+13)
10354 aload_0
10355 iconst_1
10356 putfield #719 <g/mY Z>
10359 aload_0
10360 iconst_1
10361 putfield #717 <g/jl Z>
10364 aload_0
10365 getfield #19 <g/bh Lh;>
10368 pop
10369 aload_0
10370 getfield #19 <g/bh Lh;>
10373 aload_0
10374 getfield #681 <ap/if S>
10377 invokevirtual #720 <h/A(S)S>
10380 istore 7
10382 iload 7
10384 iconst_m1
10385 if_icmpeq 10499 (+114)
10388 aload_0
10389 getfield #19 <g/bh Lh;>
10392 getfield #721 <h/d8 [B>
10395 aload_0
10396 getfield #681 <ap/if S>
10399 baload
10400 iload 7
10402 if_icmpne 10499 (+97)
10405 aload_0
10406 getfield #19 <g/bh Lh;>
10409 aload_0
10410 getfield #19 <g/bh Lh;>
10413 aload_0
10414 getfield #681 <ap/if S>
10417 invokevirtual #722 <h/else(S)S>
10420 putfield #723 <h/am S>
10423 aload_0
10424 getfield #19 <g/bh Lh;>
10427 getfield #723 <h/am S>
10430 iconst_m1
10431 if_icmpeq 10499 (+68)
10434 aload_0
10435 aload_0
10436 getfield #19 <g/bh Lh;>
10439 aload_0
10440 getfield #19 <g/bh Lh;>
10443 getfield #723 <h/am S>
10446 invokevirtual #724 <h/i(S)[B>
10449 putfield #725 <g/lR [B>
10452 aload_0
10453 getfield #725 <g/lR [B>
10456 ifnull 10494 (+38)
10459 aload_0
10460 getfield #725 <g/lR [B>
10463 iconst_0
10464 aload_0
10465 getfield #725 <g/lR [B>
10468 arraylength
10469 invokestatic #726 <q/a([BII)I>
10472 aload_0
10473 getfield #19 <g/bh Lh;>
10476 aload_0
10477 getfield #681 <ap/if S>
10480 invokevirtual #727 <h/P(S)I>
10483 if_icmpne 10494 (+11)
10486 aload_0
10487 iconst_1
10488 putfield #728 <g/bo Z>
10491 goto 10499 (+8)
10494 aload_0
10495 aconst_null
10496 putfield #725 <g/lR [B>
10499 aload_0
10500 getfield #681 <ap/if S>
10503 iconst_4
10504 if_icmpge 10565 (+61)
10507 new #729 <java/io/DataInputStream>
10510 dup
10511 aload_0
10512 invokevirtual #730 <java/lang/Object/getClass()Ljava/lang/Class;>
10515 new #401 <java/lang/StringBuffer>
10518 dup
10519 invokespecial #402 <java/lang/StringBuffer/<init>()V>
10522 ldc_w #731 <scene>
10525 invokevirtual #404 <java/lang/StringBuffer/append(Ljava/lang/String;)Ljava/lang/StringBuffer;>
10528 aload_0
10529 getfield #681 <ap/if S>
10532 invokevirtual #489 <java/lang/StringBuffer/append(I)Ljava/lang/StringBuffer;>
10535 ldc_w #732 <.pak>
10538 invokevirtual #404 <java/lang/StringBuffer/append(Ljava/lang/String;)Ljava/lang/StringBuffer;>
10541 invokevirtual #405 <java/lang/StringBuffer/toString()Ljava/lang/String;>
10544 invokevirtual #733 <java/lang/Class/getResourceAsStream(Ljava/lang/String;)Ljava/io/InputStream;>
10547 invokespecial #734 <java/io/DataInputStream/<init>(Ljava/io/InputStream;)V>
10550 astore 7
10552 aload_0
10553 sipush 2508
10556 iconst_0
10557 aload 7
10559 invokevirtual #735 <g/a(IILjava/io/DataInputStream;)V>
10562 goto 11999 (+1437)
10565 aload_0
10566 getfield #717 <g/jl Z>
10569 ifeq 10639 (+70)
10572 aload_0
10573 getfield #728 <g/bo Z>
10576 ifeq 10597 (+21)
10579 aload_0
10580 getfield #19 <g/bh Lh;>
10583 getfield #736 <h/d7 Z>
10586 ifne 10597 (+11)
10589 aload_0
10590 iconst_0
10591 putfield #714 <g/ca B>
10594 goto 10683 (+89)
10597 aload_0
10598 iconst_0
10599 putfield #728 <g/bo Z>
10602 aload_0
10603 aconst_null
10604 putfield #725 <g/lR [B>
10607 aload_0
10608 aload_0
10609 aload_0
10610 getfield #681 <ap/if S>
10613 invokevirtual #737 <g/a(S)Z>
10616 dup_x1
10617 putfield #738 <g/l0 Z>
10620 ifeq 10631 (+11)
10623 aload_0
10624 iconst_5
10625 putfield #714 <g/ca B>
10628 goto 10683 (+55)
10631 aload_0
10632 iconst_2
10633 putfield #714 <g/ca B>
10636 goto 10683 (+47)
10639 aload_0
10640 getfield #728 <g/bo Z>
10643 ifeq 10654 (+11)
10646 aload_0
10647 iconst_3
10648 putfield #714 <g/ca B>
10651 goto 10683 (+32)
10654 aload_0
10655 aload_0
10656 aload_0
10657 getfield #681 <ap/if S>
10660 invokevirtual #737 <g/a(S)Z>
10663 dup_x1
10664 putfield #738 <g/l0 Z>
10667 ifeq 10678 (+11)
10670 aload_0
10671 iconst_4
10672 putfield #714 <g/ca B>
10675 goto 10683 (+8)
10678 aload_0
10679 iconst_1
10680 putfield #714 <g/ca B>
10683 aload_0
10684 getfield #19 <g/bh Lh;>
10687 aload_0
10688 getfield #714 <g/ca B>
10691 invokevirtual #739 <h/x(B)V>
10694 goto 11999 (+1305)
10697 aload_0
10698 dup
10699 getfield #10 <g/gR I>
10702 iconst_1
10703 iadd
10704 putfield #10 <g/gR I>
10707 aload_0
10708 getfield #10 <g/gR I>
10711 ldc_w #740 <120000>
10714 aload_0
10715 getfield #19 <g/bh Lh;>
10718 pop
10719 getstatic #741 <h/bn I>
10722 idiv
10723 if_icmple 10749 (+26)
10726 iconst_0
10727 putstatic #296 <g/gf B>
10730 aload_0
10731 iconst_0
10732 putfield #9 <g/int I>
10735 aload_0
10736 iconst_0
10737 putfield #694 <g/gz Z>
10740 aload_0
10741 aload_0
10742 pop
10743 bipush 41
10745 putfield #297 <ap/do S>
10748 return
10749 aload_0
10750 getfield #714 <g/ca B>
10753 ifne 10783 (+30)
10756 aload_0
10757 getfield #19 <g/bh Lh;>
10760 getfield #736 <h/d7 Z>
10763 ifne 10783 (+20)
10766 aload_0
10767 getfield #19 <g/bh Lh;>
10770 iconst_1
10771 putfield #736 <h/d7 Z>
10774 aload_0
10775 sipush 2508
10778 iconst_0
10779 aconst_null
10780 invokevirtual #735 <g/a(IILjava/io/DataInputStream;)V>
10783 aload_0
10784 getfield #298 <ap/for Z>
10787 ifeq 11999 (+1212)
10790 aload_0
10791 iconst_0
10792 invokevirtual #742 <g/int(B)V>
10795 goto 11999 (+1204)
10798 goto 11999 (+1201)
10801 getstatic #423 <h/cz Z>
10804 ifeq 10952 (+148)
10807 aload_0
10808 getfield #681 <ap/if S>
10811 iconst_1
10812 if_icmpne 10952 (+140)
10815 aload_0
10816 getfield #19 <g/bh Lh;>
10819 getfield #427 <h/aG Lq;>
10822 sipush 1002
10825 invokevirtual #743 <q/int(I)Z>
10828 ifeq 10928 (+100)
10831 aload_0
10832 getfield #19 <g/bh Lh;>
10835 getfield #427 <h/aG Lq;>
10838 ldc #5
10840 invokevirtual #744 <q/if(Ljava/lang/String;)V>
10843 aload_0
10844 getfield #19 <g/bh Lh;>
10847 getfield #427 <h/aG Lq;>
10850 ldc #5
10852 invokevirtual #744 <q/if(Ljava/lang/String;)V>
10855 aload_0
10856 getfield #19 <g/bh Lh;>
10859 getfield #427 <h/aG Lq;>
10862 ldc #5
10864 invokevirtual #744 <q/if(Ljava/lang/String;)V>
10867 aload_0
10868 getfield #19 <g/bh Lh;>
10871 getfield #427 <h/aG Lq;>
10874 iconst_0
10875 invokevirtual #745 <q/do(I)V>
10878 aload_0
10879 getfield #19 <g/bh Lh;>
10882 getfield #427 <h/aG Lq;>
10885 iconst_0
10886 invokevirtual #745 <q/do(I)V>
10889 aload_0
10890 getfield #19 <g/bh Lh;>
10893 getfield #427 <h/aG Lq;>
10896 ldc_w #746 <13000000000>
10899 invokestatic #747 <java/lang/Long/parseLong(Ljava/lang/String;)J>
10902 invokevirtual #748 <q/a(J)V>
10905 aload_0
10906 getfield #19 <g/bh Lh;>
10909 getfield #427 <h/aG Lq;>
10912 ldc_w #749 <getInitName>
10915 invokevirtual #744 <q/if(Ljava/lang/String;)V>
10918 aload_0
10919 getfield #19 <g/bh Lh;>
10922 getfield #427 <h/aG Lq;>
10925 invokevirtual #750 <q/if()V>
10928 aload_0
10929 bipush 21
10931 putfield #297 <ap/do S>
10934 aload_0
10935 getfield #19 <g/bh Lh;>
10938 getfield #270 <h/fG LSFMIDlet;>
10941 invokestatic #271 <javax/microedition/lcdui/Display/getDisplay(Ljavax/microedition/midlet/MIDlet;)Ljavax/microedition/lcdui/Display;>
10944 aload_0
10945 getfield #19 <g/bh Lh;>
10948 invokevirtual #272 <javax/microedition/lcdui/Display/setCurrent(Ljavax/microedition/lcdui/Displayable;)V>
10951 return
10952 aload_0
10953 getfield #131 <g/hV Ljava/util/Vector;>
10956 dup
10957 astore 7
10959 monitorenter
10960 aload_0
10961 getfield #131 <g/hV Ljava/util/Vector;>
10964 invokevirtual #391 <java/util/Vector/isEmpty()Z>
10967 ifne 11021 (+54)
10970 aload_0
10971 getfield #19 <g/bh Lh;>
10974 getfield #250 <h/cZ Lag;>
10977 getfield #607 <ag/hU Z>
10980 ifne 11021 (+41)
10983 aload_0
10984 aload_0
10985 getfield #131 <g/hV Ljava/util/Vector;>
10988 invokevirtual #751 <java/util/Vector/firstElement()Ljava/lang/Object;>
10991 checkcast #23 <java/lang/String>
10994 putfield #132 <g/jK Ljava/lang/String;>
10997 aload_0
10998 getfield #131 <g/hV Ljava/util/Vector;>
11001 iconst_0
11002 invokevirtual #752 <java/util/Vector/removeElementAt(I)V>
11005 iconst_0
11006 putstatic #296 <g/gf B>
11009 aload_0
11010 aload_0
11011 pop
11012 bipush 73
11014 putfield #297 <ap/do S>
11017 aload 7
11019 monitorexit
11020 return
11021 aload 7
11023 monitorexit
11024 goto 11035 (+11)
11027 astore 9
11029 aload 7
11031 monitorexit
11032 aload 9
11034 athrow
11035 aload_0
11036 getfield #182 <g/nh Z>
11039 ifeq 11058 (+19)
11042 aload_0
11043 iconst_0
11044 putfield #182 <g/nh Z>
11047 iconst_0
11048 putstatic #296 <g/gf B>
11051 aload_0
11052 bipush 152
11054 putfield #297 <ap/do S>
11057 return
11058 aload_0
11059 getfield #753 <g/ho Z>
11062 ifne 11082 (+20)
11065 aload_0
11066 iconst_1
11067 putfield #753 <g/ho Z>
11070 iconst_0
11071 putstatic #296 <g/gf B>
11074 aload_0
11075 aload_0
11076 pop
11077 bipush 65
11079 putfield #297 <ap/do S>
11082 aload_0
11083 getfield #19 <g/bh Lh;>
11086 getfield #754 <h/bq Z>
11089 ifeq 11124 (+35)
11092 aload_0
11093 getfield #19 <g/bh Lh;>
11096 iconst_1
11097 putfield #523 <h/dL Z>
11100 aload_0
11101 getfield #19 <g/bh Lh;>
11104 iconst_0
11105 putfield #754 <h/bq Z>
11108 iconst_0
11109 putstatic #296 <g/gf B>
11112 aload_0
11113 iconst_0
11114 putfield #418 <g/e3 B>
11117 aload_0
11118 bipush 132
11120 putfield #297 <ap/do S>
11123 return
11124 aload_0
11125 getfield #19 <g/bh Lh;>
11128 pop
11129 getstatic #715 <h/dc Z>
11132 ifeq 11172 (+40)
11135 aload_0
11136 getfield #19 <g/bh Lh;>
11139 getfield #755 <h/q Z>
11142 ifne 11172 (+30)
11145 aload_0
11146 getfield #9 <g/int I>
11149 bipush 10
11151 irem
11152 ifne 11172 (+20)
11155 aload_0
11156 getfield #19 <g/bh Lh;>
11159 getfield #756 <h/dM Lkava/lang/Threak;>
11162 ifnonnull 11172 (+10)
11165 aload_0
11166 getfield #19 <g/bh Lh;>
11169 invokevirtual #757 <h/S()V>
11172 aload_0
11173 getfield #19 <g/bh Lh;>
11176 getfield #250 <h/cZ Lag;>
11179 getfield #289 <a3/a4 B>
11182 bipush 13
11184 if_icmpeq 11292 (+108)
11187 aload_0
11188 getfield #19 <g/bh Lh;>
11191 getfield #250 <h/cZ Lag;>
11194 getfield #289 <a3/a4 B>
11197 bipush 14
11199 if_icmpeq 11292 (+93)
11202 aload_0
11203 getfield #19 <g/bh Lh;>
11206 getfield #250 <h/cZ Lag;>
11209 getfield #289 <a3/a4 B>
11212 bipush 15
11214 if_icmpeq 11292 (+78)
11217 aload_0
11218 getfield #19 <g/bh Lh;>
11221 getfield #250 <h/cZ Lag;>
11224 getfield #289 <a3/a4 B>
11227 bipush 16
11229 if_icmpeq 11292 (+63)
11232 aload_0
11233 getfield #19 <g/bh Lh;>
11236 getfield #250 <h/cZ Lag;>
11239 getfield #758 <ag/eT Z>
11242 ifne 11292 (+50)
11245 aload_0
11246 getfield #19 <g/bh Lh;>
11249 getfield #250 <h/cZ Lag;>
11252 getfield #759 <ag/fE Z>
11255 ifne 11292 (+37)
11258 aload_0
11259 getfield #19 <g/bh Lh;>
11262 getfield #250 <h/cZ Lag;>
11265 getfield #760 <ag/hv Z>
11268 ifne 11292 (+24)
11271 aload_0
11272 getfield #9 <g/int I>
11275 getstatic #761 <a/T I>
11278 irem
11279 ifne 11292 (+13)
11282 aload_0
11283 getfield #19 <g/bh Lh;>
11286 getfield #250 <h/cZ Lag;>
11289 invokevirtual #461 <ag/A()V>
11292 aload_0
11293 invokevirtual #762 <g/o()V>
11296 aload_0
11297 getfield #297 <ap/do S>
11300 aload_0
11301 pop
11302 iconst_0
11303 if_icmpne 11344 (+41)
11306 aload_0
11307 getfield #88 <g/jB S>
11310 iconst_m1
11311 if_icmpeq 11344 (+33)
11314 aload_0
11315 getfield #87 <g/eL Z>
11318 ifne 11344 (+26)
11321 aload_0
11322 iconst_1
11323 putfield #87 <g/eL Z>
11326 aload_0
11327 getfield #19 <g/bh Lh;>
11330 getfield #462 <h/S Las;>
11333 aload_0
11334 getfield #88 <g/jB S>
11337 aload_0
11338 invokevirtual #763 <as/a(ILap;)V>
11341 goto 11999 (+658)
11344 aload_0
11345 getfield #681 <ap/if S>
11348 iconst_2
11349 if_icmpne 11999 (+650)
11352 aload_0
11353 getfield #9 <g/int I>
11356 sipush 200
11359 irem
11360 ifne 11396 (+36)
11363 aload_0
11364 getfield #684 <g/je B>
11367 iconst_1
11368 if_icmpne 11381 (+13)
11371 aload_0
11372 ldc_w #764 <按住确认键或数字5键发动连续攻击，点击数字1、3键使用技能.>
11375 invokevirtual #765 <g/do(Ljava/lang/String;)V>
11378 goto 11396 (+18)
11381 aload_0
11382 getfield #684 <g/je B>
11385 iconst_2
11386 if_icmpne 11396 (+10)
11389 aload_0
11390 ldc_w #766 <向同一个方向快速点击两次方向键启动疾冲.>
11393 invokevirtual #765 <g/do(Ljava/lang/String;)V>
11396 aload_0
11397 getfield #684 <g/je B>
11400 iconst_2
11401 if_icmpne 11999 (+598)
11404 iconst_5
11405 istore 7
11407 bipush 30
11409 istore 8
11411 aload_0
11412 getfield #19 <g/bh Lh;>
11415 getfield #320 <h/fj Ljavax/microedition/lcdui/Graphics;>
11418 ldc_w #767 <15724527>
11421 invokevirtual #322 <javax/microedition/lcdui/Graphics/setColor(I)V>
11424 aload_0
11425 getfield #19 <g/bh Lh;>
11428 getfield #320 <h/fj Ljavax/microedition/lcdui/Graphics;>
11431 ldc_w #768 <完成>
11434 iload 7
11436 iload 8
11438 bipush 20
11440 invokevirtual #390 <javax/microedition/lcdui/Graphics/drawString(Ljava/lang/String;III)V>
11443 iload 7
11445 getstatic #106 <h/eA I>
11448 iconst_2
11449 imul
11450 iconst_1
11451 iadd
11452 iadd
11453 i2s
11454 istore 7
11456 aload_0
11457 getfield #19 <g/bh Lh;>
11460 getfield #320 <h/fj Ljavax/microedition/lcdui/Graphics;>
11463 ldc_w #769 <16711680>
11466 invokevirtual #322 <javax/microedition/lcdui/Graphics/setColor(I)V>
11469 aload_0
11470 getfield #19 <g/bh Lh;>
11473 getfield #320 <h/fj Ljavax/microedition/lcdui/Graphics;>
11476 new #401 <java/lang/StringBuffer>
11479 dup
11480 invokespecial #402 <java/lang/StringBuffer/<init>()V>
11483 ldc #5
11485 invokevirtual #404 <java/lang/StringBuffer/append(Ljava/lang/String;)Ljava/lang/StringBuffer;>
11488 aload_0
11489 getfield #11 <g/kc B>
11492 invokevirtual #489 <java/lang/StringBuffer/append(I)Ljava/lang/StringBuffer;>
11495 invokevirtual #405 <java/lang/StringBuffer/toString()Ljava/lang/String;>
11498 iload 7
11500 iload 8
11502 bipush 20
11504 invokevirtual #390 <javax/microedition/lcdui/Graphics/drawString(Ljava/lang/String;III)V>
11507 iload 7
11509 getstatic #326 <h/dA Ljavax/microedition/lcdui/Font;>
11512 new #401 <java/lang/StringBuffer>
11515 dup
11516 invokespecial #402 <java/lang/StringBuffer/<init>()V>
11519 ldc #5
11521 invokevirtual #404 <java/lang/StringBuffer/append(Ljava/lang/String;)Ljava/lang/StringBuffer;>
11524 aload_0
11525 getfield #11 <g/kc B>
11528 invokevirtual #489 <java/lang/StringBuffer/append(I)Ljava/lang/StringBuffer;>
11531 invokevirtual #405 <java/lang/StringBuffer/toString()Ljava/lang/String;>
11534 invokevirtual #327 <javax/microedition/lcdui/Font/stringWidth(Ljava/lang/String;)I>
11537 iconst_1
11538 iadd
11539 iadd
11540 i2s
11541 istore 7
11543 aload_0
11544 getfield #19 <g/bh Lh;>
11547 getfield #320 <h/fj Ljavax/microedition/lcdui/Graphics;>
11550 ldc_w #767 <15724527>
11553 invokevirtual #322 <javax/microedition/lcdui/Graphics/setColor(I)V>
11556 aload_0
11557 getfield #19 <g/bh Lh;>
11560 getfield #320 <h/fj Ljavax/microedition/lcdui/Graphics;>
11563 ldc_w #770 <次>
11566 iload 7
11568 iload 8
11570 bipush 20
11572 invokevirtual #390 <javax/microedition/lcdui/Graphics/drawString(Ljava/lang/String;III)V>
11575 goto 11999 (+424)
11578 aload_0
11579 invokevirtual #467 <g/E()V>
11582 aload_0
11583 getfield #19 <g/bh Lh;>
11586 iconst_2
11587 iconst_0
11588 iconst_0
11589 aload_0
11590 getfield #19 <g/bh Lh;>
11593 pop
11594 getstatic #319 <h/dU S>
11597 aload_0
11598 getfield #19 <g/bh Lh;>
11601 pop
11602 getstatic #20 <h/fp S>
11605 iconst_0
11606 invokevirtual #370 <h/a(BIIIIZ)V>
11609 aload_0
11610 getfield #19 <g/bh Lh;>
11613 invokevirtual #771 <h/F()V>
11616 aload_0
11617 getfield #19 <g/bh Lh;>
11620 iconst_1
11621 invokevirtual #772 <h/do(Z)V>
11624 aload_0
11625 getfield #19 <g/bh Lh;>
11628 iconst_1
11629 invokevirtual #773 <h/if(Z)V>
11632 aload_0
11633 getfield #19 <g/bh Lh;>
11636 invokevirtual #472 <h/x()V>
11639 aload_0
11640 getfield #19 <g/bh Lh;>
11643 invokevirtual #473 <h/c()V>
11646 goto 11999 (+353)
11649 aload_0
11650 invokevirtual #467 <g/E()V>
11653 aload_0
11654 getfield #19 <g/bh Lh;>
11657 iconst_2
11658 iconst_0
11659 iconst_0
11660 aload_0
11661 getfield #19 <g/bh Lh;>
11664 pop
11665 getstatic #319 <h/dU S>
11668 aload_0
11669 getfield #19 <g/bh Lh;>
11672 pop
11673 getstatic #20 <h/fp S>
11676 iconst_0
11677 invokevirtual #370 <h/a(BIIIIZ)V>
11680 aload_0
11681 getfield #19 <g/bh Lh;>
11684 invokevirtual #771 <h/F()V>
11687 aload_0
11688 getfield #19 <g/bh Lh;>
11691 iconst_1
11692 invokevirtual #772 <h/do(Z)V>
11695 aload_0
11696 getfield #19 <g/bh Lh;>
11699 iconst_1
11700 invokevirtual #774 <h/for(Z)V>
11703 aload_0
11704 getfield #19 <g/bh Lh;>
11707 invokevirtual #472 <h/x()V>
11710 aload_0
11711 getfield #19 <g/bh Lh;>
11714 invokevirtual #473 <h/c()V>
11717 goto 11999 (+282)
11720 aload_0
11721 invokevirtual #467 <g/E()V>
11724 aload_0
11725 getfield #19 <g/bh Lh;>
11728 iconst_2
11729 iconst_0
11730 iconst_0
11731 aload_0
11732 getfield #19 <g/bh Lh;>
11735 pop
11736 getstatic #319 <h/dU S>
11739 aload_0
11740 getfield #19 <g/bh Lh;>
11743 pop
11744 getstatic #20 <h/fp S>
11747 iconst_0
11748 invokevirtual #370 <h/a(BIIIIZ)V>
11751 aload_0
11752 getfield #19 <g/bh Lh;>
11755 invokevirtual #771 <h/F()V>
11758 aload_0
11759 getfield #19 <g/bh Lh;>
11762 iconst_1
11763 invokevirtual #772 <h/do(Z)V>
11766 aload_0
11767 getfield #19 <g/bh Lh;>
11770 iconst_1
11771 invokevirtual #775 <h/int(Z)V>
11774 aload_0
11775 getfield #19 <g/bh Lh;>
11778 invokevirtual #472 <h/x()V>
11781 aload_0
11782 getfield #19 <g/bh Lh;>
11785 invokevirtual #473 <h/c()V>
11788 goto 11999 (+211)
11791 aload_0
11792 invokevirtual #467 <g/E()V>
11795 aload_0
11796 getfield #19 <g/bh Lh;>
11799 iconst_2
11800 iconst_0
11801 iconst_0
11802 aload_0
11803 getfield #19 <g/bh Lh;>
11806 pop
11807 getstatic #319 <h/dU S>
11810 aload_0
11811 getfield #19 <g/bh Lh;>
11814 pop
11815 getstatic #20 <h/fp S>
11818 iconst_0
11819 invokevirtual #370 <h/a(BIIIIZ)V>
11822 aload_0
11823 getfield #19 <g/bh Lh;>
11826 invokevirtual #771 <h/F()V>
11829 aload_0
11830 getfield #19 <g/bh Lh;>
11833 iconst_0
11834 invokevirtual #772 <h/do(Z)V>
11837 aload_0
11838 getfield #19 <g/bh Lh;>
11841 invokevirtual #472 <h/x()V>
11844 aload_0
11845 getfield #19 <g/bh Lh;>
11848 invokevirtual #473 <h/c()V>
11851 goto 11999 (+148)
11854 aload_0
11855 invokevirtual #467 <g/E()V>
11858 aload_0
11859 getfield #19 <g/bh Lh;>
11862 iconst_2
11863 iconst_0
11864 iconst_0
11865 aload_0
11866 getfield #19 <g/bh Lh;>
11869 pop
11870 getstatic #319 <h/dU S>
11873 aload_0
11874 getfield #19 <g/bh Lh;>
11877 pop
11878 getstatic #20 <h/fp S>
11881 iconst_0
11882 invokevirtual #370 <h/a(BIIIIZ)V>
11885 aload_0
11886 getfield #19 <g/bh Lh;>
11889 invokevirtual #771 <h/F()V>
11892 aload_0
11893 getfield #19 <g/bh Lh;>
11896 iconst_1
11897 invokevirtual #772 <h/do(Z)V>
11900 aload_0
11901 getfield #19 <g/bh Lh;>
11904 getfield #250 <h/cZ Lag;>
11907 getfield #317 <ag/gE Z>
11910 ifeq 11937 (+27)
11913 aload_0
11914 getfield #776 <g/fQ B>
11917 iconst_2
11918 if_icmpne 11937 (+19)
11921 aload_0
11922 getfield #777 <g/f3 B>
11925 iconst_1
11926 if_icmpne 11937 (+11)
11929 aload_0
11930 getfield #19 <g/bh Lh;>
11933 iconst_0
11934 invokevirtual #775 <h/int(Z)V>
11937 aload_0
11938 getfield #776 <g/fQ B>
11941 iconst_2
11942 if_icmpne 11961 (+19)
11945 aload_0
11946 getfield #777 <g/f3 B>
11949 iconst_2
11950 if_icmpne 11961 (+11)
11953 aload_0
11954 getfield #19 <g/bh Lh;>
11957 iconst_0
11958 invokevirtual #773 <h/if(Z)V>
11961 aload_0
11962 getfield #776 <g/fQ B>
11965 iconst_2
11966 if_icmpne 11985 (+19)
11969 aload_0
11970 getfield #777 <g/f3 B>
11973 iconst_5
11974 if_icmpne 11985 (+11)
11977 aload_0
11978 getfield #19 <g/bh Lh;>
11981 iconst_0
11982 invokevirtual #774 <h/for(Z)V>
11985 aload_0
11986 getfield #19 <g/bh Lh;>
11989 invokevirtual #472 <h/x()V>
11992 aload_0
11993 getfield #19 <g/bh Lh;>
11996 invokevirtual #473 <h/c()V>
11999 aload_0
12000 getfield #297 <ap/do S>
12003 bipush 20
12005 if_icmpeq 12016 (+11)
12008 aload_0
12009 getfield #297 <ap/do S>
12012 iconst_5
12013 if_icmpne 12032 (+19)
12016 aload_0
12017 getfield #297 <ap/do S>
12020 iconst_5
12021 if_icmpne 12046 (+25)
12024 aload_0
12025 getfield #299 <g/j0 B>
12028 iconst_1
12029 if_icmpne 12046 (+17)
12032 aload_0
12033 getfield #19 <g/bh Lh;>
12036 invokevirtual #778 <h/h()V>
12039 aload_0
12040 getfield #19 <g/bh Lh;>
12043 invokevirtual #779 <h/k()V>
12046 aload_0
12047 getfield #780 <g/lm Z>
12050 ifeq 12098 (+48)
12053 aload_0
12054 dup
12055 getfield #781 <g/ja I>
12058 iconst_1
12059 iadd
12060 putfield #781 <g/ja I>
12063 aload_0
12064 getfield #781 <g/ja I>
12067 ldc_w #782 <40000>
12070 getstatic #741 <h/bn I>
12073 idiv
12074 if_icmplt 12098 (+24)
12077 aload_0
12078 getfield #19 <g/bh Lh;>
12081 aload_0
12082 aload_0
12083 getfield #19 <g/bh Lh;>
12086 getfield #617 <h/s Ly;>
12089 invokevirtual #618 <h/a(Lap;Lap;)V>
12092 aload_0
12093 iconst_0
12094 putfield #780 <g/lm Z>
12097 return
12098 iconst_0
12099 aload_0
12100 getfield #9 <g/int I>
12103 bipush 40
12105 irem
12106 if_icmpne 12571 (+465)
12109 aload_0
12110 getfield #780 <g/lm Z>
12113 ifeq 12117 (+4)
12116 return
12117 aload_0
12118 getfield #297 <ap/do S>
12121 aload_0
12122 pop
12123 iconst_5
12124 if_icmpeq 12571 (+447)
12127 aload_0
12128 getfield #681 <ap/if S>
12131 iconst_2
12132 if_icmple 12571 (+439)
12135 aload_0
12136 aload_0
12137 getfield #681 <ap/if S>
12140 putfield #783 <g/gO I>
12143 aload_0
12144 getfield #19 <g/bh Lh;>
12147 getfield #427 <h/aG Lq;>
12150 sipush 2507
12153 invokevirtual #743 <q/int(I)Z>
12156 ifeq 12571 (+415)
12159 iconst_0
12160 istore_1
12161 aload_0
12162 getfield #19 <g/bh Lh;>
12165 getfield #250 <h/cZ Lag;>
12168 invokevirtual #784 <ag/else()Z>
12171 ifeq 12179 (+8)
12174 iload_1
12175 iconst_1
12176 ior
12177 i2s
12178 istore_1
12179 aload_0
12180 getfield #19 <g/bh Lh;>
12183 getfield #250 <h/cZ Lag;>
12186 getfield #440 <a3/a8 Z>
12189 ifeq 12198 (+9)
12192 iload_1
12193 bipush 8
12195 ior
12196 i2s
12197 istore_1
12198 aload_0
12199 getfield #19 <g/bh Lh;>
12202 getfield #250 <h/cZ Lag;>
12205 getfield #785 <ag/dU Z>
12208 ifeq 12217 (+9)
12211 iload_1
12212 bipush 16
12214 ior
12215 i2s
12216 istore_1
12217 aload_0
12218 getfield #19 <g/bh Lh;>
12221 getfield #250 <h/cZ Lag;>
12224 getfield #344 <ag/fL I>
12227 iflt 12251 (+24)
12230 aload_0
12231 getfield #19 <g/bh Lh;>
12234 getfield #250 <h/cZ Lag;>
12237 getfield #786 <ag/fj B>
12240 bipush 17
12242 if_icmpne 12251 (+9)
12245 iload_1
12246 bipush 32
12248 ior
12249 i2s
12250 istore_1
12251 aload_0
12252 getfield #19 <g/bh Lh;>
12255 getfield #250 <h/cZ Lag;>
12258 getfield #438 <ag/he Z>
12261 ifeq 12270 (+9)
12264 iload_1
12265 bipush 64
12267 ior
12268 i2s
12269 istore_1
12270 aload_0
12271 getfield #19 <g/bh Lh;>
12274 getfield #787 <h/fI Z>
12277 ifne 12293 (+16)
12280 aload_0
12281 getfield #19 <g/bh Lh;>
12284 getfield #250 <h/cZ Lag;>
12287 getfield #438 <ag/he Z>
12290 ifeq 12300 (+10)
12293 iload_1
12294 sipush 128
12297 ior
12298 i2s
12299 istore_1
12300 aload_0
12301 getfield #788 <g/e7 Z>
12304 ifeq 12314 (+10)
12307 iload_1
12308 sipush 256
12311 ior
12312 i2s
12313 istore_1
12314 aload_0
12315 getfield #459 <g/ki Z>
12318 ifeq 12328 (+10)
12321 iload_1
12322 sipush 512
12325 ior
12326 i2s
12327 istore_1
12328 aload_0
12329 getfield #19 <g/bh Lh;>
12332 getfield #250 <h/cZ Lag;>
12335 getfield #440 <a3/a8 Z>
12338 ifeq 12362 (+24)
12341 aload_0
12342 getfield #19 <g/bh Lh;>
12345 getfield #250 <h/cZ Lag;>
12348 getfield #789 <a3/d B>
12351 iconst_1
12352 if_icmpne 12362 (+10)
12355 iload_1
12356 sipush 1024
12359 ior
12360 i2s
12361 istore_1
12362 aload_0
12363 getfield #19 <g/bh Lh;>
12366 getfield #427 <h/aG Lq;>
12369 iload_1
12370 invokevirtual #790 <q/new(I)V>
12373 aload_0
12374 pop
12375 getstatic #316 <g/dZ B>
12378 ifne 12456 (+78)
12381 aload_0
12382 pop
12383 getstatic #460 <g/dD B>
12386 iconst_2
12387 if_icmpne 12404 (+17)
12390 aload_0
12391 getfield #19 <g/bh Lh;>
12394 getfield #427 <h/aG Lq;>
12397 iconst_1
12398 invokevirtual #745 <q/do(I)V>
12401 goto 12467 (+66)
12404 aload_0
12405 pop
12406 getstatic #460 <g/dD B>
12409 iconst_4
12410 if_icmpne 12427 (+17)
12413 aload_0
12414 getfield #19 <g/bh Lh;>
12417 getfield #427 <h/aG Lq;>
12420 iconst_0
12421 invokevirtual #745 <q/do(I)V>
12424 goto 12467 (+43)
12427 aload_0
12428 getfield #19 <g/bh Lh;>
12431 getfield #427 <h/aG Lq;>
12434 aload_0
12435 getfield #19 <g/bh Lh;>
12438 getfield #309 <h/cv B>
12441 iconst_2
12442 if_icmpne 12449 (+7)
12445 iconst_1
12446 goto 12450 (+4)
12449 iconst_0
12450 invokevirtual #745 <q/do(I)V>
12453 goto 12467 (+14)
12456 aload_0
12457 getfield #19 <g/bh Lh;>
12460 getfield #427 <h/aG Lq;>
12463 iconst_0
12464 invokevirtual #745 <q/do(I)V>
12467 aload_0
12468 getfield #19 <g/bh Lh;>
12471 getfield #427 <h/aG Lq;>
12474 aload_0
12475 getfield #19 <g/bh Lh;>
12478 getfield #791 <h/b3 B>
12481 invokevirtual #745 <q/do(I)V>
12484 aload_0
12485 getfield #19 <g/bh Lh;>
12488 getfield #250 <h/cZ Lag;>
12491 getfield #286 <ag/gR La3;>
12494 ifnull 12550 (+56)
12497 aload_0
12498 getfield #19 <g/bh Lh;>
12501 getfield #427 <h/aG Lq;>
12504 aload_0
12505 getfield #19 <g/bh Lh;>
12508 aload_0
12509 getfield #19 <g/bh Lh;>
12512 getfield #250 <h/cZ Lag;>
12515 getfield #286 <ag/gR La3;>
12518 invokevirtual #792 <h/if(La3;)B>
12521 invokevirtual #745 <q/do(I)V>
12524 aload_0
12525 getfield #19 <g/bh Lh;>
12528 getfield #427 <h/aG Lq;>
12531 aload_0
12532 getfield #19 <g/bh Lh;>
12535 getfield #250 <h/cZ Lag;>
12538 getfield #286 <ag/gR La3;>
12541 getfield #314 <a3/O Ljava/lang/String;>
12544 invokevirtual #744 <q/if(Ljava/lang/String;)V>
12547 goto 12561 (+14)
12550 aload_0
12551 getfield #19 <g/bh Lh;>
12554 getfield #427 <h/aG Lq;>
12557 iconst_m1
12558 invokevirtual #745 <q/do(I)V>
12561 aload_0
12562 getfield #19 <g/bh Lh;>
12565 getfield #427 <h/aG Lq;>
12568 invokevirtual #750 <q/if()V>
12571 aload_0
12572 getfield #19 <g/bh Lh;>
12575 getfield #250 <h/cZ Lag;>
12578 getfield #317 <ag/gE Z>
12581 ifeq 12656 (+75)
12584 aload_0
12585 getfield #9 <g/int I>
12588 aload_0
12589 getfield #19 <g/bh Lh;>
12592 pop
12593 getstatic #793 <h/ff Z>
12596 ifeq 12604 (+8)
12599 bipush 100
12601 goto 12606 (+5)
12604 bipush 100
12606 irem
12607 ifne 12656 (+49)
12610 aload_0
12611 getfield #19 <g/bh Lh;>
12614 getfield #427 <h/aG Lq;>
12617 sipush 3505
12620 invokevirtual #743 <q/int(I)Z>
12623 ifeq 12656 (+33)
12626 aload_0
12627 getfield #19 <g/bh Lh;>
12630 getfield #427 <h/aG Lq;>
12633 aload_0
12634 getfield #19 <g/bh Lh;>
12637 getfield #250 <h/cZ Lag;>
12640 getfield #794 <ag/gz I>
12643 invokevirtual #795 <q/for(I)V>
12646 aload_0
12647 getfield #19 <g/bh Lh;>
12650 getfield #427 <h/aG Lq;>
12653 invokevirtual #750 <q/if()V>
12656 aload_0
12657 getfield #681 <ap/if S>
12660 iconst_2
12661 if_icmple 12674 (+13)
12664 aload_0
12665 dup
12666 getfield #796 <g/b4 I>
12669 iconst_1
12670 iadd
12671 putfield #796 <g/b4 I>
12674 aload_0
12675 getfield #796 <g/b4 I>
12678 sipush 8000
12681 if_icmple 12705 (+24)
12684 aload_0
12685 iconst_0
12686 putfield #9 <g/int I>
12689 iconst_0
12690 putstatic #296 <g/gf B>
12693 aload_0
12694 iconst_1
12695 putfield #694 <g/gz Z>
12698 aload_0
12699 bipush 41
12701 putfield #297 <ap/do S>
12704 return
12705 iconst_0
12706 istore_1
12707 iload_1
12708 aload_0
12709 getfield #19 <g/bh Lh;>
12712 getfield #797 <h/dS [[I>
12715 arraylength
12716 if_icmpge 12746 (+30)
12719 aload_0
12720 getfield #19 <g/bh Lh;>
12723 getfield #798 <h/c0 Lx;>
12726 aload_0
12727 getfield #19 <g/bh Lh;>
12730 getfield #797 <h/dS [[I>
12733 iload_1
12734 aaload
12735 invokevirtual #362 <x/a([I)V>
12738 iload_1
12739 iconst_1
12740 iadd
12741 i2b
12742 istore_1
12743 goto 12707 (-36)
12746 return
