import javax.microedition.lcdui.Graphics;

public class a3
{
  public static h bE = null;
  public byte bH = 30;
  public static final byte bL = 0;
  public static final byte aq = 1;
  public static final byte az = 2;
  public static final byte bk = 3;
  public static final byte[] bq = { 0, 1, 0, -1 };
  public static final byte[] bp = { -1, 0, 1, 0 };
  public static final byte a6 = 0;
  public static final byte S = 54;
  public static final byte N = 55;
  public static final byte at = 56;
  public static final byte C = 57;
  public static final byte bu = 58;
  public static final byte m = 59;
  public static final byte jdField_int = 0;
  public static final byte bO = 1;
  public static final byte R = 2;
  public static final byte q = 3;
  public static final byte L = 4;
  public static final byte ae = 5;
  public static final byte aA = 0;
  public static final byte bI = 1;
  public static final byte a0 = 112;
  public static final int[][] jdField_goto = { { 5055329, 6173555, 7029118, 7621000 }, { 4210752, 8421504, 12632256, 15790062 }, { 2228269, 4525911, 7617159, 9461408 }, { 14431798, 14439734, 14447989, 16707310 }, { 16746240, 16776996, 16777215, 16777215 }, { 2097407, 2146559, 8454143, 12648447 }, { 14474294, 16776996, 16645538, 16776176 }, { 65329, 5701238, 16777215, 170908465 } };
  public x af = null;
  public short t = -1;
  public String O;
  public int jdField_for;
  public byte e;
  public byte bo = 0;
  public byte a4;
  public short aP;
  public short aM;
  public short a2;
  public short a1;
  public short aK;
  public short bA;
  public byte aI;
  public boolean ao;
  public byte bb;
  public byte jdField_try;
  public byte G;
  public byte bC;
  public boolean bP;
  public short aN;
  public boolean bc;
  public byte bF;
  protected byte au = 1;
  public boolean T = false;
  public boolean j = false;
  private byte aG;
  private boolean aF = false;
  private boolean aE = false;
  private boolean aC = false;
  private short aB;
  private short ay;
  private short aw;
  private short ap;
  public int b = jdMethod_new(0, 4);
  public a3 aD = null;
  public byte z;
  public byte jdField_if;
  public byte v;
  short[] a7 = null;
  int[] H = null;
  public byte bj;
  public byte bi;
  public byte bh;
  public byte ac;
  public short[][] an;
  protected short jdField_new = 0;
  public static final byte[] bt = { 6, 3, 5, 0 };
  public boolean bz;
  short jdField_void;
  byte c;
  short h;
  short g;
  short B;
  short bm;
  public boolean a8 = false;
  public byte d;
  public int[] al = new int[5];
  private int[] aj = null;
  private int[] ai = null;
  private int[] ab = null;
  public short bg;
  byte ag;
  private static final byte aa = 25;
  private static final byte Z = 4;
  private static final byte Y = 16;
  public boolean bv = false;
  private short X = 0;
  private short[][] W = (short[][])null;
  private short[][] V = (short[][])null;
  private short[][] U = (short[][])null;
  private byte[][] aZ = (byte[][])null;
  private byte aX;
  public short[][] w = (short[][])null;
  public short a5 = 0;
  public byte jdField_char = 0;
  private byte aV = 0;
  public boolean bD;
  private short[][] aT = (short[][])null;
  private short[][] aS = (short[][])null;
  boolean by;
  private static final byte[][][] aR = { { { 0, 0 }, { 0, 0 }, { 0, 0 } }, { { -15, 0 }, { -25, 0 }, { -35, 0 } }, { { 0, 10 }, { 0, 20 }, { 0, -10 } }, { { -20, 10 }, { 20, -10 }, { 0, -20 } }, { { -10, -10 }, { -10, 10 }, { -10, 0 } }, { { 10, 0 }, { -10, 0 }, { 0, -10 } }, { { 15, 0 }, { -15, 0 }, { -7, -25 }, { 7, -25 } }, { { 10, -20 }, { 10, 20 }, { 0, -5 } }, { { 10, 0 }, { -10, 0 }, { -5, -5 } }, { { -80, -40 }, { 20, -60 }, { -60, 40 } }, { { 0, -12 }, { 12, 0 }, { -12, 0 } }, { { 10, 0 }, { -10, 0 }, { 0, 0 } }, { { 0, 10 }, { 0, 20 }, { 0, -10 } } };
  private int[] aQ = null;
  private byte aO = 0;
  short f;
  short ak;
  short bx;
  boolean D;
  public static final byte jdField_long = 0;
  public static final byte ar = 4;
  public static final byte jdField_do = 8;
  public static final byte Q = 12;
  public static final byte p = 14;
  public static final byte jdField_byte = 16;
  public static final byte av = 20;
  public static final byte aU = 24;
  public static final byte k = 26;
  public static final byte bK = 28;
  public static final byte a3 = 30;
  public static final byte u = 32;
  public static final byte bM = 34;
  public static final byte bw = 36;
  public static final byte br = 38;
  public static final byte M = 40;
  public static final byte as = 42;
  public static final byte a = 44;
  public static final byte a9 = 46;
  public static final byte ah = 48;
  public static final byte jdField_else = 50;
  public static final byte be = 0;
  public static final byte bN = 14;
  public static final byte bs = 4;
  public static final byte aY = 12;
  public static final byte bd = 40;
  public static final byte ba = 46;
  public static final byte ax = 38;
  public static final byte bl = 36;
  public static final byte i = 48;
  public static final byte bn = 42;
  public static final byte P = 44;
  public static final byte r = 28;
  public static final byte bJ = 30;
  public static final byte am = 32;
  public static final byte s = 34;
  public static final byte aW = 16;
  public static final byte l = 0;
  public static final byte K = 1;
  public static final byte bB = 2;
  public static final String[] bG = { "封印", "回收", "释放" };
  public static final byte A = 0;
  public static final byte o = 1;
  public static final byte aL = 2;
  public static final String[] n = { "攻击", "防御", "回复" };
  public static final byte aH = 0;
  public static final byte bf = 1;
  public static final byte aJ = 2;
  public static final String[] ad = { "物理", "魔法", "双性" };
  public byte[] jdField_case = new byte[54];
  public static final byte jdField_null = 54;
  private static final int J = 3;
  private static final int I = 16383;
  private static final int F = 14;
  private static final int E = 3;
  private static final int y = 536870911;
  private static final int x = 30;
  
  public void a(byte paramByte1, int paramInt1, int paramInt2, byte paramByte2, byte paramByte3)
  {
    if (this.bD) {
      return;
    }
    this.jdField_char = paramByte1;
    this.aV = paramByte2;
    this.a5 = 0;
    this.by = false;
    if ((this.jdField_char == 1) || (this.jdField_char == 11))
    {
      if (paramByte3 > a.i)
      {
        paramByte3 = (byte)a.char;
        this.by = true;
      }
      else
      {
        this.by = false;
      }
    }
    else if ((this.jdField_char == a.L) && (paramByte3 > a.i)) {
      paramByte3 = (byte)a.J;
    }
    this.w = a(paramInt1, paramInt2, paramByte3);
    this.bv = false;
    byte b1;
    int i1;
    switch (this.jdField_char)
    {
    case 0: 
      a((short)a.ac, (short)a.ac, (byte)a.t, a.ac);
      break;
    case 1: 
      a((short)a.ac, (short)-a.T, (byte)a.char, this.au % a.C);
      break;
    case 2: 
      break;
    case 3: 
      this.aT = new short[paramByte3][3];
      this.aS = new short[paramByte3][3];
      for (b1 = 0; b1 < paramByte3; b1 = (byte)(b1 + 1)) {
        for (i1 = 0; i1 < a.i; i1 = (byte)(i1 + 1))
        {
          this.aT[b1][i1] = ((short)(h.jdMethod_new(i1 * a.s) * a.ad / a.y));
          this.aS[b1][i1] = ((short)(h.jdMethod_do(i1 * a.s) * a.ad / a.y));
        }
      }
      a((short)a.ac, (short)a.ac, (byte)a.t, a.ac);
      break;
    case 4: 
      this.aT = new short[paramByte3][3];
      this.aS = new short[paramByte3][3];
      for (b1 = 0; b1 < paramByte3; b1 = (byte)(b1 + 1)) {
        for (i1 = 0; i1 < a.i; i1 = (byte)(i1 + 1))
        {
          this.aT[b1][i1] = ((short)(h.jdMethod_new(i1 * a.s) * a.C / a.y));
          this.aS[b1][i1] = ((short)(h.jdMethod_do(i1 * a.s) * a.C / a.y));
        }
      }
      a((short)a.ac, (short)a.ac, (byte)a.i, a.ac);
      break;
    case 5: 
      a((short)a.ac, (short)-this.bA, (byte)a.C, a.ac);
      break;
    case 6: 
      a((short)a.ac, (short)a.ac, (byte)a.ac, a.ac);
      break;
    case 7: 
      a((short)a.ac, (short)a.ac, (byte)a.i, a.ac);
      break;
    case 8: 
      break;
    case 9: 
      break;
    case 10: 
      a((short)a.ac, (short)a.ac, (byte)a.L, a.ac);
      break;
    case 11: 
      a((short)a.ac, (short)a.ac, (byte)a.t, a.ac);
      break;
    case 12: 
      break;
    default: 
      this.bv = false;
      if (this.jdField_char < 0)
      {
        this.aO = ((byte)(Math.abs(this.jdField_char) - 1));
        this.aQ = new int[5];
        this.aQ[1] = -1;
        bE.dF.a(this.aO, 0, this.aQ);
      }
      break;
    }
    this.bD = true;
  }
  
  private short[][] a(int paramInt1, int paramInt2, byte paramByte)
  {
    short[][] arrayOfShort = new short[paramByte][2];
    arrayOfShort[0][0] = ((short)paramInt1);
    if ((this.jdField_char < 0) && (this.au == 3))
    {
      int tmp38_37 = 0;
      short[] tmp38_36 = arrayOfShort[0];
      tmp38_36[tmp38_37] = ((short)(tmp38_36[tmp38_37] - bE.dF.jdField_for[2]));
    }
    arrayOfShort[0][1] = ((short)paramInt2);
    for (byte b1 = 1; b1 < paramByte; b1 = (byte)(b1 + 1))
    {
      int i1 = 0;
      int i2 = 0;
      if (this.jdField_char >= 0)
      {
        i1 = aR[this.jdField_char][(b1 - 1)][0];
        i2 = aR[this.jdField_char][(b1 - 1)][1];
      }
      else
      {
        i1 = 10;
      }
      arrayOfShort[b1][0] = ((short)(arrayOfShort[0][0] + i1 * (this.au == 3 ? -1 : 1)));
      arrayOfShort[b1][1] = ((short)(arrayOfShort[0][1] + i2));
    }
    return arrayOfShort;
  }
  
  private void a(short paramShort1, short paramShort2, byte paramByte, int paramInt)
  {
    int i1 = 25;
    if (paramByte == 4) {
      i1 = (byte)(i1 * 2);
    } else if (paramByte == 5) {
      i1 = (byte)(h.fp / 10);
    } else if (paramByte == 6) {
      i1 = (byte)(i1 / 2);
    }
    this.aX = paramByte;
    this.W = new short[this.w.length][i1];
    this.V = new short[this.w.length][i1];
    this.aZ = new byte[this.w.length][i1];
    this.U = new short[this.w.length][i1];
    for (int i2 = 0; i2 < this.w.length; i2 = (byte)(i2 + 1)) {
      for (int i3 = 0; i3 < i1; i3 = (byte)(i3 + 1))
      {
        int i4;
        switch (paramByte)
        {
        case 0: 
          if (i3 < i1 / 2)
          {
            this.W[i2][i3] = ((short)(this.w[i2][0] + paramShort1 + h.jdMethod_if(-15, -5)));
            this.U[i2][i3] = ((short)h.jdMethod_if(280, 330));
          }
          else
          {
            this.W[i2][i3] = ((short)(this.w[i2][0] + paramShort1 + h.jdMethod_if(5, 15)));
            this.U[i2][i3] = ((short)h.jdMethod_if(210, 260));
          }
          this.V[i2][i3] = ((short)(this.w[i2][1] + paramShort2 + h.jdMethod_if(-25, 0)));
          this.aZ[i2][i3] = ((byte)(4 + h.jdMethod_if(0, 12)));
          break;
        case 1: 
          i4 = 0;
          switch (paramInt)
          {
          case 0: 
            i4 = 270;
            break;
          case 2: 
            i4 = 90;
            break;
          case 3: 
            i4 = 180;
            break;
          case 1: 
            i4 = 360;
          }
          int i5 = h.jdMethod_if(i4 - 20, i4 + 20);
          this.U[i2][i3] = ((short)i5);
          this.W[i2][i3] = ((short)(this.w[i2][0] + paramShort1));
          this.V[i2][i3] = ((short)(this.w[i2][1] + paramShort2));
          if (Math.abs(i4 - i5) < 12) {
            this.aZ[i2][i3] = ((byte)h.jdMethod_if(8, 16));
          } else {
            this.aZ[i2][i3] = ((byte)h.jdMethod_if(4, 12));
          }
          break;
        case 2: 
          this.W[i2][i3] = ((short)(this.w[i2][0] + paramShort1));
          this.U[i2][i3] = ((short)h.jdMethod_if(0, 360));
          this.V[i2][i3] = ((short)(this.w[i2][1] + paramShort2 - 10));
          this.aZ[i2][i3] = ((byte)(4 + h.jdMethod_if(0, 12)));
          break;
        case 3: 
          this.W[i2][i3] = ((short)(this.w[i2][0] + paramShort1));
          if (this.au == 3) {
            this.U[i2][i3] = ((short)h.jdMethod_if(120, 250));
          } else {
            this.U[i2][i3] = ((short)h.jdMethod_if(-70, 70));
          }
          this.V[i2][i3] = ((short)(this.w[i2][1] + paramShort2 - 10 + h.jdMethod_if(-5, 5)));
          this.aZ[i2][i3] = ((byte)(4 + h.jdMethod_if(0, 12)));
          break;
        case 4: 
          this.aZ[i2][i3] = ((byte)(4 + h.jdMethod_if(0, 12)));
          int i6 = (short)h.jdMethod_if(0, 360);
          int i7 = (short)h.jdMethod_if(50, 80);
          this.W[i2][i3] = ((short)(this.w[i2][0] + paramShort1 + i7 * h.jdMethod_new(i6) / 256));
          this.V[i2][i3] = ((short)(this.w[i2][1] + paramShort2 + i7 * h.jdMethod_do(i6) / 256));
          this.U[i2][i3] = ((short)(i6 + 180));
          break;
        case 5: 
          i4 = 360;
          this.W[i2][i3] = ((short)(0 - h.jdMethod_if(10, h.dU + 20)));
          this.V[i2][i3] = ((short)h.jdMethod_if(0, h.fp));
          this.U[i2][i3] = i4;
          this.aZ[i2][i3] = ((byte)h.jdMethod_if(20, 35));
          break;
        case 6: 
          this.W[i2][i3] = ((short)(this.w[i2][0] + paramShort1 + h.jdMethod_if(-15, 15)));
          this.U[i2][i3] = 'Ď';
          this.V[i2][i3] = ((short)(this.w[i2][1] + paramShort2 + h.jdMethod_if(-8, 0)));
          this.aZ[i2][i3] = ((byte)h.jdMethod_if(3, 7));
        }
      }
    }
    this.X = 0;
    this.bv = true;
  }
  
  private boolean jdMethod_for(byte paramByte)
  {
    if (!this.bv) {
      return true;
    }
    for (int i1 = 0; i1 < this.W[paramByte].length; i1 = (byte)(i1 + 1)) {
      switch (this.aX)
      {
      case 0: 
      case 1: 
      case 2: 
      case 3: 
      case 4: 
        if (this.aZ[paramByte][i1] > 0)
        {
          if (i1 % 2 == 0) {
            bE.fj.setColor(goto[this.aV][0]);
          } else {
            bE.fj.setColor(goto[this.aV][3]);
          }
          if ((this == bE.cZ) || (bE.cv == 0)) {
            bE.fj.fillArc(this.W[paramByte][i1] - ag.hF, this.V[paramByte][i1] - ag.hE, Math.max(1, this.aZ[paramByte][i1] / 3), Math.max(1, this.aZ[paramByte][i1] / 3), 0, 360);
          }
          int tmp220_219 = i1;
          short[] tmp220_218 = this.W[paramByte];
          tmp220_218[tmp220_219] = ((short)(tmp220_218[tmp220_219] + this.aZ[paramByte][i1] * h.jdMethod_new(this.U[paramByte][i1]) / 256));
          int tmp256_255 = i1;
          short[] tmp256_254 = this.V[paramByte];
          tmp256_254[tmp256_255] = ((short)(tmp256_254[tmp256_255] + this.aZ[paramByte][i1] * h.jdMethod_do(this.U[paramByte][i1]) / 256));
          int tmp292_291 = i1;
          byte[] tmp292_290 = this.aZ[paramByte];
          tmp292_290[tmp292_291] = ((byte)(tmp292_290[tmp292_291] - 2));
          if (this.aZ[paramByte][i1] < 0) {
            this.aZ[paramByte][i1] = 0;
          }
        }
        if ((this.X >= 8) && (i1 == this.W[paramByte].length - 1)) {
          this.bv = false;
        }
        break;
      case 5: 
        bE.fj.setColor(goto[this.aV][0]);
        int i2 = 0;
        int i3 = 1;
        if (this.aZ[paramByte][i1] > 25)
        {
          i2 = 20;
          i3 = 6;
        }
        else
        {
          i2 = 10;
          i3 = 4;
        }
        if ((this == bE.cZ) || (bE.cv == 0)) {
          bE.fj.fillArc(this.W[paramByte][i1] - ag.hF, this.V[paramByte][i1] - ag.hE, i2, i2 / 3, 0, 360);
        }
        int tmp471_470 = i1;
        short[] tmp471_469 = this.W[paramByte];
        tmp471_469[tmp471_470] = ((short)(tmp471_469[tmp471_470] + this.aZ[paramByte][i1] * h.jdMethod_new(this.U[paramByte][i1]) / 256));
        int tmp507_506 = i1;
        short[] tmp507_505 = this.V[paramByte];
        tmp507_505[tmp507_506] = ((short)(tmp507_505[tmp507_506] + this.aZ[paramByte][i1] * h.jdMethod_do(this.U[paramByte][i1]) / 256));
        if (this.X > 40) {
          this.bv = false;
        }
        break;
      case 6: 
        if (this.aZ[paramByte][i1] > 0)
        {
          if (this.aZ[paramByte][i1] >= 2)
          {
            if (this.aZ[paramByte][i1] > 3) {
              bE.fj.setColor(goto[this.aV][1]);
            } else {
              bE.fj.setColor(goto[this.aV][0]);
            }
            int i4;
            int i5;
            int i6;
            int i7;
            int i8;
            int i9;
            int i10;
            int i11;
            if ((this.X + i1) % 2 == 0)
            {
              i4 = this.W[paramByte][i1];
              i5 = this.V[paramByte][i1] - 2;
              i6 = this.W[paramByte][i1];
              i7 = this.V[paramByte][i1] + 3;
              i8 = this.W[paramByte][i1] - 2;
              i9 = this.V[paramByte][i1];
              i10 = this.W[paramByte][i1] + 3;
              i11 = this.V[paramByte][i1];
            }
            else
            {
              i4 = this.W[paramByte][i1] - 2;
              i5 = this.V[paramByte][i1] - 2;
              i6 = this.W[paramByte][i1] + 3;
              i7 = this.V[paramByte][i1] + 3;
              i8 = this.W[paramByte][i1] + 2;
              i9 = this.V[paramByte][i1] - 2;
              i10 = this.W[paramByte][i1] - 3;
              i11 = this.V[paramByte][i1] + 3;
            }
            if ((this == bE.cZ) || (bE.cv == 0))
            {
              bE.fj.drawLine(i4 - ag.hF, i5 - ag.hE, i6 - ag.hF, i7 - ag.hE);
              bE.fj.drawLine(i8 - ag.hF, i9 - ag.hE, i10 - ag.hF, i11 - ag.hE);
            }
          }
          bE.fj.setColor(goto[this.aV][2]);
          int i12 = 4;
          if (this.aZ[paramByte][i1] < 4) {
            i12 = 3;
          } else if (this.aZ[paramByte][i1] < 2) {
            i12 = 2;
          }
          if ((this == bE.cZ) || (bE.cv == 0)) {
            bE.fj.fillArc(this.W[paramByte][i1] - i12 / 2 - ag.hF, this.V[paramByte][i1] - i12 / 2 - ag.hE, i12, i12, 0, 360);
          }
          int tmp1050_1049 = i1;
          short[] tmp1050_1048 = this.W[paramByte];
          tmp1050_1048[tmp1050_1049] = ((short)(tmp1050_1048[tmp1050_1049] + this.aZ[paramByte][i1] * h.jdMethod_new(this.U[paramByte][i1]) / 256));
          int tmp1086_1085 = i1;
          short[] tmp1086_1084 = this.V[paramByte];
          tmp1086_1084[tmp1086_1085] = ((short)(tmp1086_1084[tmp1086_1085] + this.aZ[paramByte][i1] * h.jdMethod_do(this.U[paramByte][i1]) / 256));
          if (this.X % 2 == 0)
          {
            int tmp1131_1130 = i1;
            byte[] tmp1131_1129 = this.aZ[paramByte];
            tmp1131_1129[tmp1131_1130] = ((byte)(tmp1131_1129[tmp1131_1130] - 1));
          }
          if (this.aZ[paramByte][i1] < 0) {
            this.aZ[paramByte][i1] = 0;
          }
        }
        if ((this.X >= 8) && (i1 == this.W[paramByte].length - 1)) {
          this.bv = false;
        }
        break;
      }
    }
    return false;
  }
  
  public void jdMethod_if(x paramx)
  {
    this.bj = paramx.jdField_for[0];
    this.bi = paramx.jdField_for[1];
    this.bh = paramx.jdField_for[2];
    this.ac = paramx.jdField_for[3];
  }
  
  public void a(x paramx, int[] paramArrayOfInt)
  {
    if (paramArrayOfInt[3] == -1) {
      paramArrayOfInt[3] = 0;
    }
    try
    {
      if ((paramx.jdField_int[paramArrayOfInt[3]][2] == 0) || (paramx.jdField_int[paramArrayOfInt[3]][3] == 0))
      {
        this.an = ((short[][])null);
      }
      else
      {
        this.an = new short[1][4];
        this.an[0][0] = ((short)paramx.jdField_int[paramArrayOfInt[3]][0]);
        this.an[0][1] = ((short)paramx.jdField_int[paramArrayOfInt[3]][1]);
        this.an[0][2] = ((short)paramx.jdField_int[paramArrayOfInt[3]][2]);
        this.an[0][3] = ((short)paramx.jdField_int[paramArrayOfInt[3]][3]);
        if ((this == bE.cZ) && (bE.cZ.a4 != 2))
        {
          int tmp164_163 = 2;
          short[] tmp164_162 = this.an[0];
          tmp164_162[tmp164_163] = ((short)(tmp164_162[tmp164_163] + bE.cZ.ay()));
        }
      }
    }
    catch (Exception localException)
    {
      h.a(localException);
    }
  }
  
  public void a(byte paramByte1, byte paramByte2, byte paramByte3, byte paramByte4)
  {
    if ((paramByte3 == 0) || (paramByte4 == 0))
    {
      this.an = ((short[][])null);
    }
    else
    {
      this.an = new short[1][4];
      this.an[0][0] = ((short)paramByte1);
      this.an[0][1] = ((short)paramByte2);
      this.an[0][2] = ((short)paramByte3);
      this.an[0][3] = ((short)paramByte4);
    }
  }
  
  public void a()
  {
    if (this.bD)
    {
      this.an = new short[this.w.length][4];
      int i1 = 0;
      int i2 = 0;
      for (int i3 = 0; i3 < this.w.length; i3 = (byte)(i3 + 1))
      {
        i1 = (short)(this.w[i3][0] - this.aP);
        i2 = (short)(this.w[i3][1] - this.aM);
        int i4;
        int i5;
        int i6;
        switch (this.jdField_char)
        {
        case 0: 
          if ((this.a5 != a.ac) && (this.a5 != a.char) && (this.a5 != a.J) && (this.a5 != a.null)) {
            continue;
          }
          switch (this.w.length)
          {
          case 1: 
            this.an[i3][2] = ((short)a.R);
            this.an[i3][3] = ((short)a.Q);
            break;
          case 2: 
            this.an[i3][2] = ((short)a.q);
            this.an[i3][3] = ((short)a.Q);
            break;
          case 3: 
            this.an[i3][2] = ((short)a.D);
            this.an[i3][3] = ((short)a.af);
            break;
          case 4: 
            this.an[i3][2] = ((short)a.K);
            this.an[i3][3] = ((short)a.do);
          }
          this.an[i3][0] = ((short)(i1 + (this.au == 3 ? -this.an[i3][2] : a.ac)));
          this.an[i3][1] = ((short)(i2 - a.e - this.an[i3][3] / a.t));
          break;
        case 1: 
          if (this.a5 >= 4) {
            continue;
          }
          i4 = (byte)(this.au == 3 ? -1 : 1);
          i5 = (short)a.F;
          i6 = (short)a.void;
          if (this.by)
          {
            i5 = (short)a.R;
            i6 = (short)a.U;
          }
          this.an[i3][0] = ((short)(i1 + this.a5 * a.o * i4 + (this.au == 3 ? -i5 : a.ac)));
          this.an[i3][1] = ((short)(i2 - a.T - i6 / a.t));
          this.an[i3][2] = i5;
          this.an[i3][3] = i6;
          break;
        case 2: 
          this.c = ((byte)(this.au == 3 ? -1 : 1));
          if ((this.jdField_char != a.c) && (this.a5 != a.C) && (this.a5 != a.J)) {
            continue;
          }
          this.an[i3][0] = ((short)(i1 + a.R * this.c - a.void / a.t));
          this.an[i3][1] = ((short)(i2 - a.A));
          this.an[i3][2] = ((short)a.void);
          this.an[i3][3] = ((short)a.void);
          break;
        case 3: 
          if ((this.a5 >= a.t) && (this.a5 <= a.ad))
          {
            this.an[i3][0] = ((short)(i1 - a.T));
            this.an[i3][1] = ((short)(i2 - a.T - a.m));
            this.an[i3][2] = ((short)a.try);
            this.an[i3][3] = ((short)a.try);
          }
        case 4: 
          if ((this.a5 < a.t) || (this.a5 > 16)) {
            continue;
          }
          this.an[i3][0] = ((short)(i1 - a.T));
          this.an[i3][1] = ((short)(i2 - a.T - a.m));
          this.an[i3][2] = ((short)a.try);
          this.an[i3][3] = ((short)a.try);
          break;
        case 5: 
          if ((this.a5 <= a.t) || (this.a5 > a.J)) {
            continue;
          }
          this.an[i3][0] = ((short)(i1 - a.m));
          this.an[i3][1] = ((short)(i2 - a.case));
          this.an[i3][2] = ((short)a.a);
          this.an[i3][3] = ((short)a.a);
          break;
        case 6: 
          if ((this.a5 < a.char) || (this.a5 > a.i)) {
            continue;
          }
          this.an[i3][0] = ((short)(i1 - a.void / a.t));
          this.an[i3][1] = ((short)(i2 - a.n));
          this.an[i3][2] = ((short)a.void);
          this.an[i3][3] = ((short)a.T);
          break;
        case 7: 
          if ((this.a5 < a.char) || (this.a5 > a.i)) {
            continue;
          }
          if (this.au == 3) {
            this.an[i3][0] = ((short)(i1 - h.dU));
          } else {
            this.an[i3][0] = i1;
          }
          i4 = (short)a.g;
          if (this.a5 == a.t) {
            i4 = (short)a.o;
          } else if (this.a5 == a.i) {
            i4 = (short)a.m;
          }
          this.an[i3][1] = ((short)(i2 - i4));
          this.an[i3][2] = h.dU;
          this.an[i3][3] = i4;
          break;
        case 8: 
          if (this.a5 == a.char)
          {
            this.an[i3][0] = ((short)(i1 - a.M / a.t));
            this.an[i3][1] = ((short)(i2 - a.long / a.t));
            this.an[i3][2] = ((short)a.M);
            this.an[i3][3] = ((short)a.long);
          }
          else if ((this.a5 >= a.t) && (this.a5 <= a.i))
          {
            this.an[i3][0] = ((short)(i1 - a.w / a.t));
            this.an[i3][1] = ((short)(i2 - a.v / a.t));
            this.an[i3][2] = ((short)a.w);
            this.an[i3][3] = ((short)a.v);
          }
          break;
        case 9: 
          if (this.a5 != a.J) {
            continue;
          }
          if (this.w.length == a.C)
          {
            this.an[i3][0] = ((short)(ag.hF - this.aP));
            this.an[i3][1] = ((short)(ag.hE - this.aM));
            this.an[i3][2] = h.dU;
            this.an[i3][3] = h.fp;
          }
          else
          {
            this.an[i3][0] = ((short)(ag.hF - this.aP));
            this.an[i3][1] = ((short)(i2 - a.o));
            this.an[i3][2] = h.dU;
            this.an[i3][3] = ((short)a.o);
          }
          break;
        case 10: 
          if (this.a5 != 1) {
            continue;
          }
          this.an[i3][0] = ((short)(i1 - a.T));
          this.an[i3][1] = ((short)(i2 - a.ad / a.t));
          this.an[i3][2] = ((short)a.void);
          this.an[i3][3] = ((short)a.n);
          break;
        case 11: 
          if ((this.a5 != 0) && (this.a5 != 1) && (this.a5 != 5) && (this.a5 != 9)) {
            continue;
          }
          if (this.by)
          {
            this.an[i3][2] = 100;
            this.an[i3][3] = 35;
          }
          else
          {
            this.an[i3][2] = 60;
            this.an[i3][3] = 22;
          }
          i1 = (short)(i1 - (this.au == 3 ? -1 : 1) * this.an[i3][2] / 2);
          this.an[i3][0] = ((short)(i1 + (this.au == 3 ? -this.an[i3][2] : 0)));
          this.an[i3][1] = ((short)(i2 - 7 - this.an[i3][3] / 2));
          break;
        case 12: 
          i4 = (byte)(this.au == 3 ? -1 : 1);
          i5 = i1;
          i6 = (short)(i2 - a.A);
          int i7 = 0;
          switch (this.a5)
          {
          case 0: 
          case 1: 
            i5 = (short)(i5 + a.t * i4);
            i7 = (byte)a.n;
            this.an[i3][0] = ((short)(i5 - i7 / a.t));
            this.an[i3][1] = ((short)(i6 - i7 / a.t));
            this.an[i3][2] = ((short)i7);
            this.an[i3][3] = ((short)i7);
            break;
          case 2: 
            i5 = (short)(i5 + a.t * i4);
            i7 = (byte)a.T;
            this.an[i3][0] = ((short)(i5 - i7 / a.t));
            this.an[i3][1] = ((short)(i6 - i7 / a.t));
            this.an[i3][2] = ((short)i7);
            this.an[i3][3] = ((short)i7);
            break;
          case 3: 
            i5 = (short)(i5 + a.o * i4);
            i7 = (byte)a.void;
            this.an[i3][0] = ((short)(i5 - i7 / a.t));
            this.an[i3][1] = ((short)(i6 - a.long / a.t));
            this.an[i3][2] = ((short)i7);
            this.an[i3][3] = ((short)a.c);
            break;
          case 4: 
            i5 = (short)(i5 + a.R * i4);
            i6 = (short)(i6 + a.ac);
            i7 = (byte)a.n;
            this.an[i3][0] = ((short)(i5 - i7 / a.t));
            this.an[i3][1] = ((short)(i6 - i7 / a.t));
            this.an[i3][2] = ((short)i7);
            this.an[i3][3] = ((short)i7);
            break;
          case 5: 
            i5 = (short)(i5 + a.R * i4);
            i6 = (short)(i6 + a.ac);
            i7 = (byte)a.U;
            this.an[i3][0] = ((short)(i5 - i7 / a.t));
            this.an[i3][1] = ((short)(i6 - i7 / a.t));
            this.an[i3][2] = ((short)i7);
            this.an[i3][3] = ((short)i7);
          }
          break;
        }
        if (this.jdField_char < 0)
        {
          if (this.aQ[3] == -1) {
            this.aQ[3] = 0;
          }
          try
          {
            if ((bE.dF.jdField_int[this.aQ[3]][2] == 0) || (bE.dF.jdField_int[this.aQ[3]][3] == 0))
            {
              this.an = ((short[][])null);
              return;
            }
            this.an[i3][0] = ((short)bE.dF.jdField_int[this.aQ[3]][0]);
            this.an[i3][1] = ((short)(bE.dF.jdField_int[this.aQ[3]][1] + i2));
            this.an[i3][2] = ((short)bE.dF.jdField_int[this.aQ[3]][2]);
            this.an[i3][3] = ((short)bE.dF.jdField_int[this.aQ[3]][3]);
          }
          catch (Exception localException)
          {
            h.a(localException);
          }
        }
      }
    }
    else
    {
      this.an = ((short[][])null);
    }
  }
  
  public boolean jdMethod_else()
  {
    return false;
  }
  
  public boolean a(a3 parama3)
  {
    return false;
  }
  
  public boolean jdMethod_null()
  {
    boolean[] arrayOfBoolean = new boolean[this.w.length];
    for (int i1 = 0; i1 < this.w.length; i2 = (byte)(i1 + 1))
    {
      int i3 = (short)(this.w[i1][0] - ag.hF);
      int i4 = (short)(this.w[i1][1] - ag.hE);
      int i5 = 1;
      if ((this != bE.cZ) && (bE.cv != 0)) {
        i5 = 0;
      }
      int i6 = 0;
      int i7;
      int i8;
      int i11;
      int i12;
      int i13;
      int i14;
      int i15;
      int i9;
      int i10;
      switch (this.jdField_char)
      {
      case 0: 
      case 11: 
        switch (this.a5)
        {
        case 0: 
        case 1: 
        case 2: 
        case 3: 
        case 4: 
        case 5: 
        case 6: 
        case 7: 
        case 8: 
        case 9: 
        case 10: 
          if (i5 != 0) {
            for (i7 = 0; i7 < 3; i7 = (byte)(i7 + 1))
            {
              i8 = (byte)h.jdMethod_if(2, 3);
              short[] arrayOfShort1 = new short[i8 + 2];
              short[] arrayOfShort2 = new short[i8 + 2];
              i11 = (byte)(this.au == 3 ? -1 : 1);
              i12 = 60;
              i13 = 12;
              i14 = i3;
              if (this.jdField_char == 0)
              {
                switch (this.w.length)
                {
                case 2: 
                  i12 = 75;
                  i13 = 22;
                  break;
                case 3: 
                  i12 = 90;
                  i13 = 32;
                  break;
                case 4: 
                  i12 = 105;
                  i13 = 44;
                }
              }
              else
              {
                i12 = 60;
                i13 = 14;
                if (this.by)
                {
                  i12 = 100;
                  i13 = 18;
                }
                i14 = (short)(i3 - i11 * i12 / 2);
              }
              for (i15 = 0; i15 < arrayOfShort1.length; i15 = (byte)(i15 + 1)) {
                if (i15 == 0)
                {
                  arrayOfShort1[i15] = i14;
                  arrayOfShort2[i15] = ((short)(i4 - 15));
                }
                else if (i15 == arrayOfShort1.length - 1)
                {
                  arrayOfShort1[i15] = ((short)(i14 + i11 * i12));
                  arrayOfShort2[i15] = ((short)(i4 - 15));
                }
                else
                {
                  arrayOfShort1[i15] = ((short)(i14 + i11 * (i12 / (i8 + 1) * i15)));
                  arrayOfShort2[i15] = ((short)(i4 - 15 + h.jdMethod_if(-i13 / 4, i13 / 4)));
                }
              }
              for (i15 = 1; i15 < arrayOfShort1.length; i15 = (byte)(i15 + 1))
              {
                if (h.jdMethod_if(0, 1) == 0) {
                  bE.fj.setColor(goto[this.aV][0]);
                } else {
                  bE.fj.setColor(goto[this.aV][3]);
                }
                bE.fj.drawLine(arrayOfShort1[(i15 - 1)], arrayOfShort2[(i15 - 1)], arrayOfShort1[i15], arrayOfShort2[i15]);
              }
            }
          }
          break;
        default: 
          i6 = 1;
        }
        break;
      case 1: 
        switch (this.a5)
        {
        case 0: 
        case 1: 
        case 2: 
        case 3: 
          if (i5 != 0)
          {
            i7 = (byte)(this.au == 3 ? -1 : 1);
            i8 = 40;
            i9 = 30;
            if (this.by)
            {
              i8 = 60;
              i9 = 50;
            }
            i10 = (short)(i3 + i8 * i7);
            i11 = (short)(i4 - 15);
            i12 = i3;
            i13 = (short)(i4 - 15 - i9 / 2);
            i14 = i3;
            i15 = (short)(i4 - 15 + i9 / 2);
            i10 = (short)(i10 + this.a5 * 20 * i7);
            i12 = (short)(i12 + this.a5 * 20 * i7);
            i14 = (short)(i14 + this.a5 * 20 * i7);
            bE.fj.setColor(goto[this.aV][3]);
            bE.fj.fillTriangle(i10, i11, i12, i13, i10 - (3 - this.a5) * 3 * i7, i11);
            bE.fj.fillTriangle(i10, i11, i14, i15, i10 - (3 - this.a5) * 3 * i7, i11);
            bE.fj.setColor(goto[this.aV][1]);
            bE.fj.drawLine(i10 - 2 * i7, i11, i12 - 2 * i7 + i7 * (Math.abs(i10 - i12) / 2), i13 + Math.abs(i11 - i13) / 2);
            bE.fj.drawLine(i10 - 2 * i7, i11, i14 - 2 * i7 + i7 * (Math.abs(i10 - i14) / 2), i15 - Math.abs(i11 - i15) / 2);
            bE.fj.setColor(goto[this.aV][0]);
            bE.fj.drawLine(i10, i11, i12, i13);
            bE.fj.drawLine(i10, i11, i14, i15);
          }
          break;
        default: 
          i6 = 1;
        }
        break;
      case 2: 
      case 12: 
        i7 = (byte)(this.au == 3 ? -1 : 1);
        i8 = i3;
        i9 = (short)(i4 - 19);
        switch (this.a5)
        {
        case 0: 
        case 1: 
          if (i5 != 0)
          {
            i8 = (short)(i8 + 2 * i7);
            i9 = (short)(i9 + 0);
            i10 = 10;
            bE.fj.setColor(goto[this.aV][0]);
            bE.fj.fillArc(i8 - i10 / 2, i9 - i10 / 2, i10, i10, 0, 360);
            i10 = 8;
            bE.fj.setColor(goto[this.aV][1]);
            bE.fj.fillArc(i8 - i10 / 2, i9 - i10 / 2, i10, i10, 0, 360);
            bE.fj.setColor(goto[this.aV][3]);
            i10 = 3;
            bE.fj.fillArc(i8 - i10 / 2, i9 - i10 / 2, i10, i10, 0, 360);
          }
          break;
        case 2: 
          if (i5 != 0)
          {
            i8 = (short)(i8 + 2 * i7);
            bE.fj.setColor(goto[this.aV][0]);
            bE.fj.fillRect(i8, i9, 2, 2);
            i8 = (short)(i8 + 2 * i7);
            bE.fj.setColor(goto[this.aV][1]);
            bE.fj.fillRect(i8, i9, 3, 3);
            i8 = (short)(i8 + 5 * i7);
            bE.fj.setColor(goto[this.aV][2]);
            bE.fj.fillRect(i8, i9, 4, 4);
            i8 = (short)(i8 + 5 * i7);
            bE.fj.setColor(goto[this.aV][3]);
            bE.fj.fillRect(i8, i9, 6, 6);
          }
          break;
        case 3: 
          if (i5 != 0)
          {
            i8 = (short)(i8 + 45 * i7);
            bE.fj.setColor(goto[this.aV][3]);
            bE.fj.fillRect(i8, i9, 6, 6);
            i8 = (short)(i8 + -7 * i7);
            bE.fj.setColor(goto[this.aV][2]);
            bE.fj.fillRect(i8, i9, 4, 4);
            i8 = (short)(i8 + -9 * i7);
            bE.fj.setColor(goto[this.aV][1]);
            bE.fj.fillRect(i8, i9, 3, 3);
            i8 = (short)(i8 + -14 * i7);
            bE.fj.setColor(goto[this.aV][0]);
            bE.fj.fillRect(i8, i9, 2, 2);
          }
          break;
        case 4: 
          if (i5 != 0)
          {
            i8 = (short)(i8 + 60 * i7);
            i9 = (short)(i9 + 0);
            this.aK = 10;
            bE.fj.setColor(goto[this.aV][0]);
            bE.fj.fillArc(i8 - this.aK / 2, i9 - this.aK / 2, this.aK, this.aK, 0, 360);
            this.aK = 8;
            bE.fj.setColor(goto[this.aV][1]);
            bE.fj.fillArc(i8 - this.aK / 2, i9 - this.aK / 2, this.aK, this.aK, 0, 360);
            this.aK = 5;
            bE.fj.setColor(goto[this.aV][2]);
            bE.fj.fillArc(i8 - this.aK / 2, i9 - this.aK / 2, this.aK, this.aK, 0, 360);
            bE.fj.setColor(goto[this.aV][3]);
            this.aK = 3;
            bE.fj.fillArc(i8 - this.aK / 2, i9 - this.aK / 2, this.aK, this.aK, 0, 360);
            a((short)(60 * i7), (short)-19, (byte)2, 0);
          }
          break;
        case 5: 
          if (i5 != 0)
          {
            i8 = (short)(i8 + 60 * i7);
            i9 = (short)(i9 + 0);
            this.aK = 22;
            bE.fj.setColor(goto[this.aV][0]);
            bE.fj.fillArc(i8 - this.aK / 2, i9 - this.aK / 2, this.aK, this.aK, 0, 360);
            this.aK = 20;
            bE.fj.setColor(goto[this.aV][1]);
            bE.fj.fillArc(i8 - this.aK / 2, i9 - this.aK / 2, this.aK, this.aK, 0, 360);
            this.aK = 16;
            bE.fj.setColor(goto[this.aV][2]);
            bE.fj.fillArc(i8 - this.aK / 2, i9 - this.aK / 2, this.aK, this.aK, 0, 360);
            bE.fj.setColor(goto[this.aV][3]);
            this.aK = 10;
            bE.fj.fillArc(i8 - this.aK / 2, i9 - this.aK / 2, this.aK, this.aK, 0, 360);
          }
          break;
        default: 
          i6 = 1;
        }
        break;
      case 3: 
        if (i5 != 0)
        {
          bE.fj.setColor(goto[this.aV][Math.min(this.a5 / 2, 3)]);
          for (i10 = 0; i10 < 3; i10 = (byte)(i10 + 1)) {
            bE.fj.drawLine(i3 + this.aT[i1][i10], i4 + this.aS[i1][i10] - 15, i3 + this.aT[i1][((i10 + 1) % 3)], i4 + this.aS[i1][((i10 + 1) % 3)] - 15);
          }
          for (i10 = 0; i10 < 3; i10 = (byte)(i10 + 1))
          {
            this.aT[i1][i10] = ((short)(h.jdMethod_new(i10 * 120 + this.a5 * 50) * (10 + this.a5) / 256));
            this.aS[i1][i10] = ((short)(h.jdMethod_do(i10 * 120 + this.a5 * 50) * (10 + this.a5) / 256));
          }
        }
        if (this.a5 >= 8) {
          i6 = 1;
        }
        break;
      case 4: 
        if (i5 != 0)
        {
          bE.fj.setColor(goto[this.aV][0]);
          for (i10 = 0; i10 < 3; i10 = (byte)(i10 + 1)) {
            bE.fj.drawLine(i3 + this.aT[i1][i10], i4 + this.aS[i1][i10] - 15, i3 + this.aT[i1][((i10 + 1) % 3)], i4 + this.aS[i1][((i10 + 1) % 3)] - 15);
          }
          i10 = (short)(this.a5 * 50 * (this.au == 3 ? -1 : 1));
          for (i11 = 0; i11 < 3; i11 = (byte)(i11 + 1))
          {
            this.aT[i1][i11] = ((short)(h.jdMethod_new(i11 * 120 + i10) * 12 / 256));
            this.aS[i1][i11] = ((short)(h.jdMethod_do(i11 * 120 + i10) * 12 / 256));
          }
          if (this.au == 3)
          {
            int tmp2783_2782 = 0;
            short[] tmp2783_2781 = this.w[i1];
            tmp2783_2781[tmp2783_2782] = ((short)(tmp2783_2781[tmp2783_2782] - 5));
          }
          else
          {
            int tmp2799_2798 = 0;
            short[] tmp2799_2797 = this.w[i1];
            tmp2799_2797[tmp2799_2798] = ((short)(tmp2799_2797[tmp2799_2798] + 5));
          }
        }
        if (this.a5 > 16) {
          i6 = 1;
        }
        break;
      case 5: 
        i10 = 0;
        switch (this.a5)
        {
        case 0: 
          if (i5 != 0)
          {
            bE.fj.setColor(goto[this.aV][0]);
            i10 = 10;
            bE.fj.fillArc(i3 - i10 / 2, i4 - this.bA - i10 / 2, i10, i10, 0, 360);
            bE.fj.setColor(goto[this.aV][1]);
            i10 = 8;
            bE.fj.fillArc(i3 - i10 / 2, i4 - this.bA - i10 / 2, i10, i10, 0, 360);
            bE.fj.setColor(goto[this.aV][2]);
            i10 = 4;
            bE.fj.fillArc(i3 - i10 / 2, i4 - this.bA - i10 / 2, i10, i10, 0, 360);
          }
          break;
        case 1: 
          if (i5 != 0)
          {
            bE.fj.setColor(goto[this.aV][0]);
            i10 = 30;
            bE.fj.fillArc(i3 - i10 / 2, i4 - this.bA - i10 / 2, i10, i10, 0, 360);
            bE.fj.setColor(goto[this.aV][1]);
            i10 = 24;
            bE.fj.fillArc(i3 - i10 / 2, i4 - this.bA - i10 / 2, i10, i10, 0, 360);
            bE.fj.setColor(goto[this.aV][2]);
            i10 = 18;
            bE.fj.fillArc(i3 - i10 / 2, i4 - this.bA - i10 / 2, i10, i10, 0, 360);
          }
          break;
        case 2: 
          if (i5 != 0)
          {
            bE.fj.setColor(goto[this.aV][0]);
            i10 = 50;
            bE.fj.fillArc(i3 - i10 / 2, i4 - this.bA - i10 / 2, i10, i10, 0, 360);
            bE.fj.setColor(goto[this.aV][1]);
            i10 = 40;
            bE.fj.fillArc(i3 - i10 / 2, i4 - this.bA - i10 / 2, i10, i10, 0, 360);
            bE.fj.setColor(goto[this.aV][3]);
            i10 = 30;
            bE.fj.fillArc(i3 - i10 / 2, i4 - this.bA - i10 / 2, i10, i10, 0, 360);
          }
          break;
        case 3: 
          if (i5 != 0)
          {
            bE.fj.setColor(goto[this.aV][1]);
            i10 = 20;
            bE.fj.fillArc(i3 - i10 / 2, i4 - this.bA - i10 / 2, i10, i10, 0, 360);
            bE.fj.setColor(goto[this.aV][3]);
            i10 = 14;
            bE.fj.fillArc(i3 - i10 / 2, i4 - this.bA - i10 / 2, i10, i10, 0, 360);
          }
          break;
        case 4: 
          if (i5 != 0)
          {
            bE.fj.setColor(goto[this.aV][2]);
            i10 = 10;
            bE.fj.fillArc(i3 - i10 / 2, i4 - this.bA - i10 / 2, i10, i10, 0, 360);
            bE.fj.setColor(goto[this.aV][3]);
            i10 = 6;
            bE.fj.fillArc(i3 - i10 / 2, i4 - this.bA - i10 / 2, i10, i10, 0, 360);
          }
          break;
        case 5: 
          if (i5 != 0)
          {
            bE.fj.setColor(goto[this.aV][3]);
            i10 = 4;
            bE.fj.fillArc(i3 - i10 / 2, i4 - this.bA - i10 / 2, i10, i10, 0, 360);
          }
          break;
        default: 
          i6 = 1;
        }
        break;
      case 6: 
        if (i5 == 0)
        {
          if (this.a5 > 5) {
            i6 = 1;
          } else {
            i6 = 0;
          }
        }
        else {
          switch (this.a5)
          {
          case 0: 
            bE.fj.setColor(goto[this.aV][3]);
            bE.fj.fillArc(i3 - 5, i4 - 5, 10, 10, 0, 360);
            break;
          case 1: 
            bE.fj.setColor(goto[this.aV][3]);
            bE.fj.fillArc(i3 - 13, i4 - 6, 26, 12, 0, 360);
            bE.fj.setColor(goto[this.aV][0]);
            bE.fj.fillArc(i3 - 9, i4 - 70, 18, 70, 0, 360);
            bE.fj.setColor(goto[this.aV][1]);
            bE.fj.fillArc(i3 - 6, i4 - 60, 12, 60, 0, 360);
            bE.fj.setColor(goto[this.aV][2]);
            bE.fj.fillArc(i3 - 4, i4 - 46, 8, 46, 0, 360);
            break;
          case 2: 
            bE.fj.setColor(goto[this.aV][3]);
            bE.fj.fillArc(i3 - 14, i4 - 7, 28, 15, 0, 360);
            bE.fj.setColor(goto[this.aV][0]);
            bE.fj.fillArc(i3 - 6, i4 - 86, 12, 86, 0, 360);
            bE.fj.setColor(goto[this.aV][1]);
            bE.fj.fillArc(i3 - 3, i4 - 76, 6, 76, 0, 360);
            bE.fj.setColor(goto[this.aV][2]);
            bE.fj.fillArc(i3 - 2, i4 - 56, 4, 56, 0, 360);
            break;
          case 3: 
            bE.fj.setColor(goto[this.aV][1]);
            bE.fj.fillArc(i3 - 3, i4 - 108, 6, 108, 0, 360);
            break;
          case 4: 
            bE.fj.setColor(goto[this.aV][2]);
            bE.fj.fillArc(i3 - 5, i4 - 52, 2, 37, 0, 360);
            bE.fj.fillArc(i3, i4 - 45, 1, 30, 0, 360);
            bE.fj.fillArc(i3, i4 - 115, 2, 40, 0, 360);
            break;
          case 5: 
            bE.fj.setColor(goto[this.aV][3]);
            bE.fj.fillArc(i3 - 5, i4 - 65, 1, 55, 0, 360);
            bE.fj.fillArc(i3, i4 - 120, 1, 20, 0, 360);
            break;
          default: 
            i6 = 1;
          }
        }
        break;
      case 7: 
        if (i5 == 0)
        {
          if (this.a5 > 4) {
            i6 = 1;
          } else {
            i6 = 0;
          }
        }
        else {
          switch (this.a5)
          {
          case 0: 
            i11 = 24;
            bE.fj.setColor(goto[this.aV][0]);
            bE.fj.fillArc(i3 - i11 / 2, i4 - i11 / 2 - 15, i11, i11, 0, 360);
            i11 = 20;
            bE.fj.setColor(goto[this.aV][2]);
            bE.fj.fillArc(i3 - i11 / 2, i4 - i11 / 2 - 15, i11, i11, 0, 360);
            i11 = 16;
            bE.fj.setColor(goto[this.aV][3]);
            bE.fj.fillArc(i3 - i11 / 2, i4 - i11 / 2 - 15, i11, i11, 0, 360);
            break;
          case 1: 
            i11 = 24;
            bE.fj.setColor(goto[this.aV][0]);
            bE.fj.fillArc(i3 - i11 / 2, i4 - i11 / 2 - 15, i11, i11, 0, 360);
            if (this.au == 3) {
              bE.fj.fillRect(0, i4 - i11 / 2 - 15, i3, i11);
            } else {
              bE.fj.fillRect(i3, i4 - i11 / 2 - 15, h.dU, i11);
            }
            i11 = 20;
            bE.fj.setColor(goto[this.aV][1]);
            bE.fj.fillArc(i3 - i11 / 2, i4 - i11 / 2 - 15, i11, i11, 0, 360);
            if (this.au == 3) {
              bE.fj.fillRect(0, i4 - i11 / 2 - 15, i3, i11);
            } else {
              bE.fj.fillRect(i3, i4 - i11 / 2 - 15, h.dU, i11);
            }
            i11 = 16;
            bE.fj.setColor(goto[this.aV][3]);
            bE.fj.fillArc(i3 - i11 / 2, i4 - i11 / 2 - 15, i11, i11, 0, 360);
            if (this.au == 3) {
              bE.fj.fillRect(0, i4 - i11 / 2 - 15, i3, i11);
            } else {
              bE.fj.fillRect(i3, i4 - i11 / 2 - 15, h.dU, i11);
            }
            break;
          case 2: 
            i11 = 20;
            bE.fj.setColor(goto[this.aV][0]);
            bE.fj.fillArc(i3 - i11 / 2, i4 - i11 / 2 - 15, i11, i11, 0, 360);
            if (this.au == 3) {
              bE.fj.fillRect(0, i4 - i11 / 2 - 15, i3, i11);
            } else {
              bE.fj.fillRect(i3, i4 - i11 / 2 - 15, h.dU, i11);
            }
            i11 = 16;
            bE.fj.setColor(goto[this.aV][2]);
            bE.fj.fillArc(i3 - i11 / 2, i4 - i11 / 2 - 15, i11, i11, 0, 360);
            if (this.au == 3) {
              bE.fj.fillRect(0, i4 - i11 / 2 - 15, i3, i11);
            } else {
              bE.fj.fillRect(i3, i4 - i11 / 2 - 15, h.dU, i11);
            }
            i11 = 12;
            bE.fj.setColor(goto[this.aV][3]);
            bE.fj.fillArc(i3 - i11 / 2, i4 - i11 / 2 - 15, i11, i11, 0, 360);
            if (this.au == 3) {
              bE.fj.fillRect(0, i4 - i11 / 2 - 15, i3, i11);
            } else {
              bE.fj.fillRect(i3, i4 - i11 / 2 - 15, h.dU, i11);
            }
            break;
          case 3: 
            i11 = 14;
            bE.fj.setColor(goto[this.aV][0]);
            bE.fj.fillArc(i3 - i11 / 2, i4 - i11 / 2 - 15, i11, i11, 0, 360);
            if (this.au == 3) {
              bE.fj.fillRect(0, i4 - i11 / 2 - 15, i3, i11);
            } else {
              bE.fj.fillRect(i3, i4 - i11 / 2 - 15, h.dU, i11);
            }
            i11 = 10;
            bE.fj.setColor(goto[this.aV][2]);
            bE.fj.fillArc(i3 - i11 / 2, i4 - i11 / 2 - 15, i11, i11, 0, 360);
            if (this.au == 3) {
              bE.fj.fillRect(0, i4 - i11 / 2 - 15, i3, i11);
            } else {
              bE.fj.fillRect(i3, i4 - i11 / 2 - 15, h.dU, i11);
            }
            i11 = 6;
            bE.fj.setColor(goto[this.aV][3]);
            bE.fj.fillArc(i3 - i11 / 2, i4 - i11 / 2 - 15, i11, i11, 0, 360);
            if (this.au == 3) {
              bE.fj.fillRect(0, i4 - i11 / 2 - 15, i3, i11);
            } else {
              bE.fj.fillRect(i3, i4 - i11 / 2 - 15, h.dU, i11);
            }
            break;
          case 4: 
            i11 = 4;
            bE.fj.setColor(goto[this.aV][2]);
            bE.fj.fillArc(i3 - i11 / 2, i4 - i11 / 2 - 15, i11, i11, 0, 360);
            if (this.au == 3) {
              bE.fj.fillRect(0, i4 - i11 / 2 - 15, i3, i11);
            } else {
              bE.fj.fillRect(i3, i4 - i11 / 2 - 15, h.dU, i11);
            }
            break;
          default: 
            i6 = 1;
          }
        }
        break;
      case 8: 
        i10 = 0;
        i11 = 0;
        switch (this.a5)
        {
        case 0: 
          if (i5 != 0)
          {
            if (this == bE.cZ)
            {
              bE.S.ad = true;
              bE.S.X = ag.hF;
              bE.S.V = ag.hE;
            }
            bE.fj.setColor(goto[this.aV][3]);
            i10 = 39;
            i11 = 9;
            bE.fj.drawArc(i3 - i10 / 2, i4 - i11 / 2, i10, i11, 0, 80);
            bE.fj.drawArc(i3 - i10 / 2, i4 - i11 / 2, i10, i11, 100, 260);
            bE.fj.setColor(goto[this.aV][0]);
            i10 = 26;
            i11 = 3;
            bE.fj.drawArc(i3 - i10 / 2, i4 - i11 / 2, i10, i11, 0, 80);
            bE.fj.drawArc(i3 - i10 / 2, i4 - i11 / 2, i10, i11, 100, 260);
          }
          break;
        case 1: 
          if (i5 != 0)
          {
            bE.fj.setColor(goto[this.aV][0]);
            i10 = 62;
            i11 = 16;
            bE.fj.drawArc(i3 - i10 / 2, i4 - i11 / 2, i10, i11, 0, 80);
            bE.fj.drawArc(i3 - i10 / 2, i4 - i11 / 2, i10, i11, 100, 260);
            bE.fj.setColor(goto[this.aV][1]);
            i10 = 51;
            i11 = 11;
            bE.fj.drawArc(i3 - i10 / 2, i4 - i11 / 2, i10, i11, 0, 80);
            bE.fj.drawArc(i3 - i10 / 2, i4 - i11 / 2, i10, i11, 100, 260);
            bE.fj.setColor(goto[this.aV][3]);
            i10 = 35;
            i11 = 5;
            bE.fj.drawArc(i3 - i10 / 2, i4 - i11 / 2, i10, i11, 0, 80);
            bE.fj.drawArc(i3 - i10 / 2, i4 - i11 / 2, i10, i11, 100, 260);
          }
          break;
        case 2: 
          if (i5 != 0)
          {
            bE.fj.setColor(goto[this.aV][0]);
            i10 = 71;
            i11 = 21;
            bE.fj.drawArc(i3 - i10 / 2, i4 - i11 / 2, i10, i11, 0, 80);
            bE.fj.drawArc(i3 - i10 / 2, i4 - i11 / 2, i10, i11, 100, 260);
            bE.fj.setColor(goto[this.aV][2]);
            i10 = 62;
            i11 = 16;
            bE.fj.drawArc(i3 - i10 / 2, i4 - i11 / 2, i10, i11, 0, 80);
            bE.fj.drawArc(i3 - i10 / 2, i4 - i11 / 2, i10, i11, 100, 260);
            bE.fj.setColor(goto[this.aV][3]);
            i10 = 51;
            i11 = 11;
            bE.fj.drawArc(i3 - i10 / 2, i4 - i11 / 2, i10, i11, 0, 80);
            bE.fj.drawArc(i3 - i10 / 2, i4 - i11 / 2, i10, i11, 100, 260);
          }
          break;
        case 3: 
          if (i5 != 0)
          {
            bE.fj.setColor(goto[this.aV][1]);
            i10 = 72;
            i11 = 21;
            bE.fj.drawArc(i3 - i10 / 2, i4 - i11 / 2, i10, i11, 0, 80);
            bE.fj.drawArc(i3 - i10 / 2, i4 - i11 / 2, i10, i11, 100, 260);
            bE.fj.setColor(goto[this.aV][2]);
            i10 = 62;
            i11 = 16;
            bE.fj.drawArc(i3 - i10 / 2, i4 - i11 / 2, i10, i11, 0, 80);
            bE.fj.drawArc(i3 - i10 / 2, i4 - i11 / 2, i10, i11, 100, 260);
          }
          break;
        default: 
          if (this == bE.cZ)
          {
            bE.S.ad = false;
            ag.hF = bE.S.X;
            ag.hE = bE.S.V;
          }
          i6 = 1;
        }
        break;
      case 9: 
        i12 = i3;
        i13 = i4;
        if (i5 == 0)
        {
          if (this.a5 > 7)
          {
            if ((this == bE.cZ) && (this.w.length == 4))
            {
              bE.S.ad = false;
              ag.hF = bE.S.X;
              ag.hE = bE.S.V;
            }
            i6 = 1;
          }
          else
          {
            i6 = 0;
          }
        }
        else {
          switch (this.a5)
          {
          case 0: 
          case 1: 
            if (this.a5 == 0) {
              i13 = (short)(i13 - 110);
            } else {
              i13 = (short)(i13 - 40);
            }
            bE.fj.setColor(goto[this.aV][0]);
            bE.fj.fillArc(i12 - 7, i13 - 10, 15, 21, 0, 360);
            bE.fj.fillRect(i12 - 4, 0, 9, i13);
            bE.fj.setColor(goto[this.aV][1]);
            bE.fj.fillArc(i12 - 5, i13 - 9, 11, 19, 0, 360);
            bE.fj.fillRect(i12 - 3, 0, 7, i13);
            bE.fj.setColor(goto[this.aV][3]);
            bE.fj.fillArc(i12 - 3, i13 - 7, 7, 15, 0, 360);
            bE.fj.fillRect(i12 - 2, 0, 5, i13);
            break;
          case 2: 
            bE.fj.setColor(goto[this.aV][0]);
            bE.fj.fillRect(i12 - 4, 0, 9, i13);
            bE.fj.fillArc(i12 - 30, i13 - 15, 60, 30, 0, 180);
            bE.fj.setColor(goto[this.aV][1]);
            bE.fj.fillRect(i12 - 3, 0, 7, i13);
            bE.fj.fillArc(i12 - 26, i13 - 13, 52, 26, 0, 180);
            bE.fj.setColor(goto[this.aV][3]);
            bE.fj.fillRect(i12 - 2, 0, 5, i13);
            bE.fj.fillArc(i12 - 24, i13 - 11, 48, 22, 0, 180);
            a((short)0, (short)0, (byte)0, 0);
            if ((this.w.length == 4) && (this == bE.cZ))
            {
              bE.S.ad = true;
              bE.S.X = ag.hF;
              bE.S.V = ag.hE;
            }
            break;
          case 3: 
            bE.fj.setColor(goto[this.aV][0]);
            bE.fj.fillArc(i12 - 25, i13 - 4, 51, 8, 0, 180);
            bE.fj.setColor(goto[this.aV][3]);
            bE.fj.fillArc(i12 - 24, i13 - 3, 49, 6, 0, 180);
            break;
          case 4: 
            bE.fj.setColor(goto[this.aV][0]);
            bE.fj.fillArc(i12 - 40, i13 - 3, 81, 6, 0, 180);
            bE.fj.setColor(goto[this.aV][3]);
            bE.fj.fillArc(i12 - 34, i13 - 2, 68, 4, 0, 180);
            break;
          case 5: 
          case 6: 
            bE.fj.setColor(goto[this.aV][0]);
            bE.fj.fillRect(0, i13 - 4, h.dU, 8);
            bE.fj.setColor(goto[this.aV][1]);
            bE.fj.fillRect(0, i13 - 3, h.dU, 6);
            bE.fj.setColor(goto[this.aV][3]);
            bE.fj.fillRect(0, i13 - 2, h.dU, 4);
            break;
          case 7: 
            bE.fj.setColor(goto[this.aV][0]);
            bE.fj.fillRect(0, i13 - 2, h.dU, 4);
            if ((this.w.length == 4) && (bE.cZ == this))
            {
              bE.S.ad = false;
              ag.hF = bE.S.X;
              ag.hE = bE.S.V;
            }
            break;
          default: 
            i6 = 1;
          }
        }
        break;
      case 10: 
      default: 
        if (this.jdField_char < 0)
        {
          if (i5 != 0) {
            bE.dF.a(i3, i4, bE.bt, this.aQ, this.au == 3 ? 2 : 0);
          }
          if (i1 == 0) {
            bE.dF.a(this.aQ);
          }
          if (this.aQ[4] == 0) {
            i6 = 1;
          }
        }
        else
        {
          i6 = 1;
        }
        break;
      }
      if ((jdMethod_for(i1)) && (i6 != 0)) {
        arrayOfBoolean[i1] = true;
      }
    }
    this.X = ((short)(this.X + 1));
    this.bD = false;
    for (int i2 = 0; i2 < arrayOfBoolean.length; i2 = (byte)(i2 + 1)) {
      if (arrayOfBoolean[i2] == 0) {
        this.bD = true;
      }
    }
    if (!this.bD) {
      return true;
    }
    this.a5 = ((short)(this.a5 + 1));
    return false;
  }
  
  public a3(h paramh, x paramx)
  {
    if (bE == null) {
      bE = paramh;
    }
    this.a7 = new short[a.ad];
    this.H = new int[a.ad];
    for (int i1 = 0; i1 < this.a7.length; i1++)
    {
      this.a7[i1] = -1;
      this.H[i1] = a(-1, a.C);
    }
    this.af = paramx;
  }
  
  public void jdMethod_long()
  {
    this.G = 0;
  }
  
  public void jdMethod_new(byte paramByte)
  {
    this.G = ((byte)(this.G | 1 << paramByte));
  }
  
  public boolean jdMethod_do(byte paramByte)
  {
    return (this.G & 1 << paramByte) == 0;
  }
  
  protected int f()
  {
    return this.bb;
  }
  
  public void jdMethod_if()
  {
    int i1 = (byte)(f() - 3 > 0 ? f() - 3 : 1);
    switch (this.jdField_try)
    {
    case 0: 
      if (this.aM + this.aI + bp[this.jdField_try] * f() <= 0)
      {
        this.aM = 0;
        jdMethod_new((byte)0);
        d();
      }
      else if ((bE.fJ[bE.cJ.jdMethod_for(this.aP + 1, this.aM + this.aI + bp[this.jdField_try] * f())] < 0) && (bE.fJ[bE.cJ.jdMethod_for(this.aP + this.aK - 1, this.aM + this.aI + bp[this.jdField_try] * f())] < 0) && (bE.fJ[bE.cJ.jdMethod_for(this.aP + this.aK / 2 - 1, this.aM + this.aI + bp[this.jdField_try] * f())] < 0))
      {
        this.aM = ((short)(bE.cJ.jdMethod_for(this.aP, this.aM + this.aI + bp[this.jdField_try] * f()) / bE.w * h.b8 + h.b8 - this.aI));
        jdMethod_new((byte)0);
        d();
      }
      else if ((bE.fJ[bE.cJ.jdMethod_for(this.aP + 1, this.aM + this.aI + bp[this.jdField_try] * f())] < 0) && (this.ao))
      {
        this.aM = ((short)(bE.cJ.jdMethod_for(this.aP, this.aM + this.aI + bp[this.jdField_try] * f()) / bE.w * h.b8 + h.b8 - this.aI));
        this.aP = ((short)(this.aP + bq[1] * i1));
        if (this.aP + this.aK >= bE.ad) {
          this.aP = ((short)(bE.ad - this.aK - 1));
        }
      }
      else if ((bE.fJ[bE.cJ.jdMethod_for(this.aP + this.aK - 1, this.aM + this.aI + bp[this.jdField_try] * f())] < 0) && (this.ao))
      {
        this.aM = ((short)(bE.cJ.jdMethod_for(this.aP, this.aM + this.aI + bp[this.jdField_try] * f()) / bE.w * h.b8 + h.b8 - this.aI));
        this.aP = ((short)(this.aP + bq[3] * i1));
        if (this.aP < 0) {
          this.aP = 0;
        }
      }
      break;
    case 3: 
      if (this.aP + bq[this.jdField_try] * f() <= 0)
      {
        this.aP = 0;
        jdMethod_new((byte)3);
        d();
      }
      else if ((bE.fJ[bE.cJ.jdMethod_for(this.aP + bq[this.jdField_try] * f(), this.aM + this.aI)] < 0) && (bE.fJ[bE.cJ.jdMethod_for(this.aP + bq[this.jdField_try] * f(), this.aM + this.bA - 1)] < 0))
      {
        this.aP = ((short)(bE.cJ.jdMethod_for(this.aP + bq[this.jdField_try] * f(), this.aM + this.aI) % bE.w * h.u + h.u));
        jdMethod_new((byte)3);
        d();
      }
      else if ((bE.fJ[bE.cJ.jdMethod_for(this.aP + bq[this.jdField_try] * f(), this.aM + this.aI)] < 0) && (this.ao))
      {
        this.aP = ((short)(bE.cJ.jdMethod_for(this.aP + bq[this.jdField_try] * f(), this.aM + this.aI) % bE.w * h.u + h.u));
        this.aM = ((short)(this.aM + bp[2] * i1));
        if (this.aM + this.bA >= bE.dz) {
          this.aM = ((short)(bE.dz - this.bA - 1));
        }
      }
      else if ((bE.fJ[bE.cJ.jdMethod_for(this.aP + bq[this.jdField_try] * f(), this.aM + this.bA - 1)] < 0) && (this.ao))
      {
        this.aP = ((short)(bE.cJ.jdMethod_for(this.aP + bq[this.jdField_try] * f(), this.aM + this.aI) % bE.w * h.u + h.u));
        this.aM = ((short)(this.aM + bp[0] * i1));
        if (this.aM < 0) {
          this.aM = 0;
        }
      }
      break;
    case 2: 
      if (this.aM + bp[this.jdField_try] * f() + this.bA >= bE.dz)
      {
        this.aM = ((short)(bE.dz - this.bA));
        jdMethod_new((byte)2);
        d();
      }
      else if ((bE.fJ[bE.cJ.jdMethod_for(this.aP + 1, this.aM + bp[this.jdField_try] * f() + this.bA)] < 0) && (bE.fJ[bE.cJ.jdMethod_for(this.aP + this.aK - 1, this.aM + bp[this.jdField_try] * f() + this.bA)] < 0) && (bE.fJ[bE.cJ.jdMethod_for(this.aP + this.aK / 2 - 1, this.aM + bp[this.jdField_try] * f() + this.bA)] < 0))
      {
        this.aM = ((short)(bE.cJ.jdMethod_for(this.aP, this.aM + bp[this.jdField_try] * f() + this.bA) / bE.w * h.b8 - this.bA));
        jdMethod_new((byte)2);
        d();
      }
      else if ((bE.fJ[bE.cJ.jdMethod_for(this.aP + 1, this.aM + bp[this.jdField_try] * f() + this.bA)] < 0) && (this.ao))
      {
        this.aM = ((short)(bE.cJ.jdMethod_for(this.aP, this.aM + bp[this.jdField_try] * f() + this.bA) / bE.w * h.b8 - this.bA));
        this.aP = ((short)(this.aP + bq[1] * i1));
        if (this.aP + this.aK >= bE.ad) {
          this.aP = ((short)(bE.ad - this.aK - 1));
        }
      }
      else if ((bE.fJ[bE.cJ.jdMethod_for(this.aP + this.aK - 1, this.aM + bp[this.jdField_try] * f() + this.bA)] < 0) && (this.ao))
      {
        this.aM = ((short)(bE.cJ.jdMethod_for(this.aP, this.aM + bp[this.jdField_try] * f() + this.bA) / bE.w * h.b8 - this.bA));
        this.aP = ((short)(this.aP + bq[3] * i1));
        if (this.aP < 0) {
          this.aP = 0;
        }
      }
      break;
    case 1: 
      if (this.aP + bq[this.jdField_try] * f() + this.aK >= bE.ad)
      {
        this.aP = ((short)(bE.ad - this.aK));
        jdMethod_new((byte)1);
        d();
      }
      else if ((bE.fJ[bE.cJ.jdMethod_for(this.aP + this.aK + bq[this.jdField_try] * f(), this.aM + this.aI)] < 0) && (bE.fJ[bE.cJ.jdMethod_for(this.aP + this.aK + bq[this.jdField_try] * f(), this.aM + this.bA - 1)] < 0))
      {
        this.aP = ((short)(bE.cJ.jdMethod_for(this.aP + this.aK + bq[this.jdField_try] * f(), this.aM + this.aI) % bE.w * h.u - this.aK));
        jdMethod_new((byte)1);
        d();
      }
      else if ((bE.fJ[bE.cJ.jdMethod_for(this.aP + this.aK + bq[this.jdField_try] * f(), this.aM + this.aI)] < 0) && (this.ao))
      {
        this.aP = ((short)(bE.cJ.jdMethod_for(this.aP + this.aK + bq[this.jdField_try] * f(), this.aM + this.aI) % bE.w * h.u - this.aK));
        this.aM = ((short)(this.aM + bp[2] * i1));
        if (this.aM + this.bA >= bE.dz) {
          this.aM = ((short)(bE.dz - this.bA - 1));
        }
      }
      else if ((bE.fJ[bE.cJ.jdMethod_for(this.aP + this.aK + bq[this.jdField_try] * f(), this.aM + this.bA - 1)] < 0) && (this.ao))
      {
        this.aP = ((short)(bE.cJ.jdMethod_for(this.aP + this.aK + bq[this.jdField_try] * f(), this.aM + this.aI) % bE.w * h.u - this.aK));
        this.aM = ((short)(this.aM + bp[0] * i1));
        if (this.aM < 0) {
          this.aM = 0;
        }
      }
      break;
    }
  }
  
  public int a(int paramInt)
  {
    int i1 = a.ac;
    for (int i2 = 0; i2 < this.H.length - 1; i2 = (byte)(i2 + 1)) {
      if (jdMethod_int(this.H[i2], a.C) > -1)
      {
        int i3 = h.q((short)jdMethod_int(this.H[i2], a.C));
        if ((i3 == paramInt) || ((i3 == a.C) && ((paramInt == a.ac) || (paramInt == a.t)))) {
          i1 += h.jdMethod_void((short)jdMethod_int(this.H[i2], a.C));
        }
      }
    }
    return i1;
  }
  
  public int e()
  {
    int i1 = a((byte)28);
    if ((this == bE.cZ) && (bE.cJ.jdField_do != 13) && (bE.cJ.jdField_do != 25))
    {
      if (bE.jdMethod_new((byte)2)) {
        i1 += i1 * a.t / a.n;
      }
      if (bE.cZ.hT[0] > 0) {
        i1 += a((byte)28) * bE.cZ.hT[0] / a.new;
      }
      if (bE.cZ.gR != null) {
        i1 += bE.a(bE.cZ.gR, 0);
      }
    }
    i1 += a(0);
    return i1;
  }
  
  public int jdMethod_goto()
  {
    int i1 = a((byte)30);
    if ((this == bE.cZ) && (bE.cJ.jdField_do != 13) && (bE.cJ.jdField_do != 25))
    {
      if (bE.jdMethod_new((byte)3)) {
        i1 += i1 * a.t / a.n;
      }
      if (bE.cZ.hT[2] > 0) {
        i1 += a((byte)30) * bE.cZ.hT[2] / a.new;
      }
      if (bE.cZ.gR != null) {
        i1 += bE.a(bE.cZ.gR, 1);
      }
    }
    i1 += a(1);
    return i1;
  }
  
  public int jdMethod_byte()
  {
    int i1 = a((byte)32);
    if ((this == bE.cZ) && (bE.cJ.jdField_do != 13) && (bE.cJ.jdField_do != 25))
    {
      if (bE.jdMethod_new((byte)4)) {
        i1 += i1 * a.t / a.n;
      }
      if (bE.cZ.hT[1] > 0) {
        i1 += a((byte)32) * bE.cZ.hT[1] / a.new;
      }
      if (bE.cZ.gR != null) {
        i1 += bE.a(bE.cZ.gR, a.t);
      }
    }
    i1 += a(a.t);
    return i1;
  }
  
  public int jdMethod_try()
  {
    int i1 = a((byte)34);
    if ((this == bE.cZ) && (bE.cJ.jdField_do != 13) && (bE.cJ.jdField_do != 25))
    {
      if (bE.jdMethod_new((byte)5)) {
        i1 += i1 * a.t / a.n;
      }
      if (bE.cZ.hT[3] > 0) {
        i1 += a((byte)34) * bE.cZ.hT[3] / a.new;
      }
      if (bE.cZ.gR != null) {
        i1 += bE.a(bE.cZ.gR, a.i);
      }
    }
    i1 += a(a.i);
    return i1;
  }
  
  public int jdMethod_do(a3 parama3)
  {
    int i1 = e() * a.t - parama3.jdMethod_goto() + h.jdMethod_if(-1, a.char) * h.jdMethod_if(a.char, a((byte)14));
    if (this == bE.cZ)
    {
      if (bE.cZ.n((byte)4)) {
        i1 /= a.t;
      }
    }
    else if ((this != bE.cZ) && (bE.cZ.n((byte)3))) {
      i1 *= a.t;
    }
    if ((parama3 instanceof ag)) {
      if (((ag)parama3).fE) {
        i1 /= a.J;
      } else if (((ag)parama3).hv) {
        i1 = i1 * a.n / (a.void + ag.eI * ((ag)parama3).jdMethod_int(((ag)parama3).bo, a.byte));
      }
    }
    return Math.max(a.char, i1);
  }
  
  public int jdMethod_if(a3 parama3)
  {
    int i1 = 0;
    if (this == bE.cZ)
    {
      i1 = (jdMethod_byte() * a.i / a.t + jdMethod_do(this.b, a.C) - a.t * parama3.jdMethod_try()) * h.jdMethod_if(a.D, a.B) / a.new;
      if ((ag.l(bE.cZ.fm)) && (bE.cZ.fm != a.byte)) {
        i1 = (i1 * a.n + i1 * ag.eJ * (bE.cZ.jdMethod_int(bE.cZ.bo, bE.cZ.fm) - 1)) / a.n;
      }
      if (bE.cZ.n((byte)6)) {
        i1 /= a.t;
      }
    }
    else
    {
      i1 = (a((byte)32) * a.t - parama3.jdMethod_try()) * h.jdMethod_if(a.D, a.B) / a.new;
      if (bE.cZ.n((byte)5)) {
        i1 *= a.t;
      }
    }
    if ((parama3 instanceof ag)) {
      if (((ag)parama3).fE) {
        i1 /= a.J;
      } else if (((ag)parama3).hv) {
        i1 = i1 * a.n / (a.void + ag.eI * ((ag)parama3).jdMethod_int(((ag)parama3).bo, a.byte));
      }
    }
    return Math.max(a.char, i1);
  }
  
  public int jdMethod_void()
  {
    int i1 = (byte)(a((byte)14) + a.char);
    int i2 = (i1 - a.char) * (i1 - a.char) * (i1 - a.char) * (i1 - a.char) + a.t * i1 * i1;
    return i2;
  }
  
  /* Error */
  public void a(ag paramag)
  {
    // Byte code:
    //   0: aload_1
    //   1: getfield 172	ag:fm	B
    //   4: aload_1
    //   5: pop
    //   6: getstatic 175	ag:d8	B
    //   9: if_icmpne +10 -> 19
    //   12: aload_0
    //   13: invokevirtual 137	a3:d	()V
    //   16: goto +1129 -> 1145
    //   19: getstatic 31	a3:bE	Lh;
    //   22: getfield 176	h:b0	Lx;
    //   25: aload_0
    //   26: iconst_1
    //   27: invokevirtual 177	a3:int	(B)B
    //   30: iconst_0
    //   31: aload_1
    //   32: getfield 124	a3:al	[I
    //   35: invokevirtual 33	x:a	(II[I)V
    //   38: aload_1
    //   39: iconst_1
    //   40: putfield 178	ag:hU	Z
    //   43: aload_1
    //   44: iconst_0
    //   45: putfield 179	ag:dZ	Z
    //   48: aload_1
    //   49: getfield 180	ag:eZ	B
    //   52: iconst_3
    //   53: if_icmpne +37 -> 90
    //   56: aload_1
    //   57: getfield 181	ag:hH	B
    //   60: ifne +30 -> 90
    //   63: getstatic 31	a3:bE	Lh;
    //   66: getfield 176	h:b0	Lx;
    //   69: aload_0
    //   70: aload_1
    //   71: getfield 182	ag:fH	[B
    //   74: aload_1
    //   75: getfield 183	ag:id	B
    //   78: baload
    //   79: invokevirtual 177	a3:int	(B)B
    //   82: iconst_0
    //   83: aload_1
    //   84: getfield 124	a3:al	[I
    //   87: invokevirtual 33	x:a	(II[I)V
    //   90: aload_1
    //   91: iconst_0
    //   92: putfield 184	ag:ft	B
    //   95: aload_1
    //   96: iconst_2
    //   97: putfield 62	a3:a4	B
    //   100: aload_1
    //   101: getstatic 31	a3:bE	Lh;
    //   104: getfield 49	h:cZ	Lag;
    //   107: if_acmpne +332 -> 439
    //   110: getstatic 31	a3:bE	Lh;
    //   113: getfield 139	h:cJ	Lg;
    //   116: getfield 186	ap:if	S
    //   119: getstatic 14	a:t	I
    //   122: if_icmple +317 -> 439
    //   125: getstatic 31	a3:bE	Lh;
    //   128: getfield 187	h:aG	Lq;
    //   131: sipush 5231
    //   134: invokevirtual 188	q:int	(I)Z
    //   137: ifeq +130 -> 267
    //   140: getstatic 31	a3:bE	Lh;
    //   143: getfield 187	h:aG	Lq;
    //   146: aload_1
    //   147: getfield 172	ag:fm	B
    //   150: iconst_2
    //   151: invokestatic 117	a3:new	(II)I
    //   154: invokevirtual 189	q:for	(I)V
    //   157: getstatic 31	a3:bE	Lh;
    //   160: getfield 187	h:aG	Lq;
    //   163: aload_1
    //   164: bipush 24
    //   166: invokevirtual 151	a3:a	(B)I
    //   169: iconst_2
    //   170: invokestatic 117	a3:new	(II)I
    //   173: invokevirtual 189	q:for	(I)V
    //   176: getstatic 31	a3:bE	Lh;
    //   179: getfield 187	h:aG	Lq;
    //   182: aload_1
    //   183: getfield 190	ag:hh	I
    //   186: invokevirtual 189	q:for	(I)V
    //   189: getstatic 31	a3:bE	Lh;
    //   192: getfield 187	h:aG	Lq;
    //   195: aload_1
    //   196: getfield 191	ag:ev	B
    //   199: invokevirtual 192	q:do	(I)V
    //   202: iconst_0
    //   203: istore 5
    //   205: aload_1
    //   206: getfield 193	ag:fd	Z
    //   209: ifeq +10 -> 219
    //   212: iload 5
    //   214: iconst_1
    //   215: ior
    //   216: i2b
    //   217: istore 5
    //   219: aload_1
    //   220: getfield 194	ag:fb	Z
    //   223: ifeq +10 -> 233
    //   226: iload 5
    //   228: iconst_2
    //   229: ior
    //   230: i2b
    //   231: istore 5
    //   233: aload_1
    //   234: getfield 195	ag:e9	Z
    //   237: ifeq +10 -> 247
    //   240: iload 5
    //   242: iconst_4
    //   243: ior
    //   244: i2b
    //   245: istore 5
    //   247: getstatic 31	a3:bE	Lh;
    //   250: getfield 187	h:aG	Lq;
    //   253: iload 5
    //   255: invokevirtual 192	q:do	(I)V
    //   258: getstatic 31	a3:bE	Lh;
    //   261: getfield 187	h:aG	Lq;
    //   264: invokevirtual 196	q:if	()V
    //   267: aload_1
    //   268: getfield 197	a3:D	Z
    //   271: ifeq +13 -> 284
    //   274: aload_1
    //   275: iconst_0
    //   276: putfield 197	a3:D	Z
    //   279: aload_0
    //   280: aload_1
    //   281: invokevirtual 198	a3:if	(Lag;)V
    //   284: aload_1
    //   285: getfield 172	ag:fm	B
    //   288: getstatic 199	ag:dt	B
    //   291: if_icmpeq +148 -> 439
    //   294: aload_1
    //   295: getfield 172	ag:fm	B
    //   298: getstatic 200	ag:hX	B
    //   301: if_icmpeq +138 -> 439
    //   304: aload_1
    //   305: getfield 172	ag:fm	B
    //   308: getstatic 201	ag:ig	B
    //   311: if_icmpeq +128 -> 439
    //   314: aload_1
    //   315: getfield 172	ag:fm	B
    //   318: getstatic 202	ag:eV	B
    //   321: if_icmpeq +118 -> 439
    //   324: aload_1
    //   325: getfield 172	ag:fm	B
    //   328: getstatic 203	ag:dV	B
    //   331: if_icmpeq +108 -> 439
    //   334: aload_1
    //   335: getfield 172	ag:fm	B
    //   338: getstatic 204	ag:ey	B
    //   341: if_icmpeq +98 -> 439
    //   344: aload_1
    //   345: getfield 172	ag:fm	B
    //   348: getstatic 175	ag:d8	B
    //   351: if_icmpeq +88 -> 439
    //   354: aload_1
    //   355: getfield 172	ag:fm	B
    //   358: invokestatic 173	ag:l	(B)Z
    //   361: ifne +78 -> 439
    //   364: iconst_0
    //   365: istore 5
    //   367: aload_1
    //   368: bipush 24
    //   370: invokevirtual 151	a3:a	(B)I
    //   373: aload_1
    //   374: bipush 26
    //   376: invokevirtual 151	a3:a	(B)I
    //   379: iconst_2
    //   380: idiv
    //   381: if_icmpge +58 -> 439
    //   384: iconst_m1
    //   385: getstatic 31	a3:bE	Lh;
    //   388: bipush 111
    //   390: invokevirtual 205	h:if	(B)S
    //   393: dup
    //   394: istore 5
    //   396: if_icmpeq +43 -> 439
    //   399: getstatic 31	a3:bE	Lh;
    //   402: getfield 139	h:cJ	Lg;
    //   405: iload 5
    //   407: iconst_1
    //   408: invokevirtual 206	g:a	(SZ)V
    //   411: getstatic 31	a3:bE	Lh;
    //   414: iload 5
    //   416: iconst_1
    //   417: invokevirtual 207	h:if	(SZ)V
    //   420: getstatic 31	a3:bE	Lh;
    //   423: getfield 139	h:cJ	Lg;
    //   426: iload 5
    //   428: iconst_0
    //   429: invokevirtual 206	g:a	(SZ)V
    //   432: getstatic 31	a3:bE	Lh;
    //   435: iconst_2
    //   436: invokevirtual 208	h:c	(B)V
    //   439: goto +706 -> 1145
    //   442: astore_2
    //   443: getstatic 31	a3:bE	Lh;
    //   446: pop
    //   447: iconst_1
    //   448: putstatic 185	h:bi	Z
    //   451: aload_1
    //   452: iconst_2
    //   453: putfield 62	a3:a4	B
    //   456: aload_1
    //   457: getstatic 31	a3:bE	Lh;
    //   460: getfield 49	h:cZ	Lag;
    //   463: if_acmpne +332 -> 795
    //   466: getstatic 31	a3:bE	Lh;
    //   469: getfield 139	h:cJ	Lg;
    //   472: getfield 186	ap:if	S
    //   475: getstatic 14	a:t	I
    //   478: if_icmple +317 -> 795
    //   481: getstatic 31	a3:bE	Lh;
    //   484: getfield 187	h:aG	Lq;
    //   487: sipush 5231
    //   490: invokevirtual 188	q:int	(I)Z
    //   493: ifeq +130 -> 623
    //   496: getstatic 31	a3:bE	Lh;
    //   499: getfield 187	h:aG	Lq;
    //   502: aload_1
    //   503: getfield 172	ag:fm	B
    //   506: iconst_2
    //   507: invokestatic 117	a3:new	(II)I
    //   510: invokevirtual 189	q:for	(I)V
    //   513: getstatic 31	a3:bE	Lh;
    //   516: getfield 187	h:aG	Lq;
    //   519: aload_1
    //   520: bipush 24
    //   522: invokevirtual 151	a3:a	(B)I
    //   525: iconst_2
    //   526: invokestatic 117	a3:new	(II)I
    //   529: invokevirtual 189	q:for	(I)V
    //   532: getstatic 31	a3:bE	Lh;
    //   535: getfield 187	h:aG	Lq;
    //   538: aload_1
    //   539: getfield 190	ag:hh	I
    //   542: invokevirtual 189	q:for	(I)V
    //   545: getstatic 31	a3:bE	Lh;
    //   548: getfield 187	h:aG	Lq;
    //   551: aload_1
    //   552: getfield 191	ag:ev	B
    //   555: invokevirtual 192	q:do	(I)V
    //   558: iconst_0
    //   559: istore 5
    //   561: aload_1
    //   562: getfield 193	ag:fd	Z
    //   565: ifeq +10 -> 575
    //   568: iload 5
    //   570: iconst_1
    //   571: ior
    //   572: i2b
    //   573: istore 5
    //   575: aload_1
    //   576: getfield 194	ag:fb	Z
    //   579: ifeq +10 -> 589
    //   582: iload 5
    //   584: iconst_2
    //   585: ior
    //   586: i2b
    //   587: istore 5
    //   589: aload_1
    //   590: getfield 195	ag:e9	Z
    //   593: ifeq +10 -> 603
    //   596: iload 5
    //   598: iconst_4
    //   599: ior
    //   600: i2b
    //   601: istore 5
    //   603: getstatic 31	a3:bE	Lh;
    //   606: getfield 187	h:aG	Lq;
    //   609: iload 5
    //   611: invokevirtual 192	q:do	(I)V
    //   614: getstatic 31	a3:bE	Lh;
    //   617: getfield 187	h:aG	Lq;
    //   620: invokevirtual 196	q:if	()V
    //   623: aload_1
    //   624: getfield 197	a3:D	Z
    //   627: ifeq +13 -> 640
    //   630: aload_1
    //   631: iconst_0
    //   632: putfield 197	a3:D	Z
    //   635: aload_0
    //   636: aload_1
    //   637: invokevirtual 198	a3:if	(Lag;)V
    //   640: aload_1
    //   641: getfield 172	ag:fm	B
    //   644: getstatic 199	ag:dt	B
    //   647: if_icmpeq +148 -> 795
    //   650: aload_1
    //   651: getfield 172	ag:fm	B
    //   654: getstatic 200	ag:hX	B
    //   657: if_icmpeq +138 -> 795
    //   660: aload_1
    //   661: getfield 172	ag:fm	B
    //   664: getstatic 201	ag:ig	B
    //   667: if_icmpeq +128 -> 795
    //   670: aload_1
    //   671: getfield 172	ag:fm	B
    //   674: getstatic 202	ag:eV	B
    //   677: if_icmpeq +118 -> 795
    //   680: aload_1
    //   681: getfield 172	ag:fm	B
    //   684: getstatic 203	ag:dV	B
    //   687: if_icmpeq +108 -> 795
    //   690: aload_1
    //   691: getfield 172	ag:fm	B
    //   694: getstatic 204	ag:ey	B
    //   697: if_icmpeq +98 -> 795
    //   700: aload_1
    //   701: getfield 172	ag:fm	B
    //   704: getstatic 175	ag:d8	B
    //   707: if_icmpeq +88 -> 795
    //   710: aload_1
    //   711: getfield 172	ag:fm	B
    //   714: invokestatic 173	ag:l	(B)Z
    //   717: ifne +78 -> 795
    //   720: iconst_0
    //   721: istore 5
    //   723: aload_1
    //   724: bipush 24
    //   726: invokevirtual 151	a3:a	(B)I
    //   729: aload_1
    //   730: bipush 26
    //   732: invokevirtual 151	a3:a	(B)I
    //   735: iconst_2
    //   736: idiv
    //   737: if_icmpge +58 -> 795
    //   740: iconst_m1
    //   741: getstatic 31	a3:bE	Lh;
    //   744: bipush 111
    //   746: invokevirtual 205	h:if	(B)S
    //   749: dup
    //   750: istore 5
    //   752: if_icmpeq +43 -> 795
    //   755: getstatic 31	a3:bE	Lh;
    //   758: getfield 139	h:cJ	Lg;
    //   761: iload 5
    //   763: iconst_1
    //   764: invokevirtual 206	g:a	(SZ)V
    //   767: getstatic 31	a3:bE	Lh;
    //   770: iload 5
    //   772: iconst_1
    //   773: invokevirtual 207	h:if	(SZ)V
    //   776: getstatic 31	a3:bE	Lh;
    //   779: getfield 139	h:cJ	Lg;
    //   782: iload 5
    //   784: iconst_0
    //   785: invokevirtual 206	g:a	(SZ)V
    //   788: getstatic 31	a3:bE	Lh;
    //   791: iconst_2
    //   792: invokevirtual 208	h:c	(B)V
    //   795: goto +350 -> 1145
    //   798: astore_3
    //   799: aload_1
    //   800: iconst_2
    //   801: putfield 62	a3:a4	B
    //   804: aload_1
    //   805: getstatic 31	a3:bE	Lh;
    //   808: getfield 49	h:cZ	Lag;
    //   811: if_acmpne +332 -> 1143
    //   814: getstatic 31	a3:bE	Lh;
    //   817: getfield 139	h:cJ	Lg;
    //   820: getfield 186	ap:if	S
    //   823: getstatic 14	a:t	I
    //   826: if_icmple +317 -> 1143
    //   829: getstatic 31	a3:bE	Lh;
    //   832: getfield 187	h:aG	Lq;
    //   835: sipush 5231
    //   838: invokevirtual 188	q:int	(I)Z
    //   841: ifeq +130 -> 971
    //   844: getstatic 31	a3:bE	Lh;
    //   847: getfield 187	h:aG	Lq;
    //   850: aload_1
    //   851: getfield 172	ag:fm	B
    //   854: iconst_2
    //   855: invokestatic 117	a3:new	(II)I
    //   858: invokevirtual 189	q:for	(I)V
    //   861: getstatic 31	a3:bE	Lh;
    //   864: getfield 187	h:aG	Lq;
    //   867: aload_1
    //   868: bipush 24
    //   870: invokevirtual 151	a3:a	(B)I
    //   873: iconst_2
    //   874: invokestatic 117	a3:new	(II)I
    //   877: invokevirtual 189	q:for	(I)V
    //   880: getstatic 31	a3:bE	Lh;
    //   883: getfield 187	h:aG	Lq;
    //   886: aload_1
    //   887: getfield 190	ag:hh	I
    //   890: invokevirtual 189	q:for	(I)V
    //   893: getstatic 31	a3:bE	Lh;
    //   896: getfield 187	h:aG	Lq;
    //   899: aload_1
    //   900: getfield 191	ag:ev	B
    //   903: invokevirtual 192	q:do	(I)V
    //   906: iconst_0
    //   907: istore 5
    //   909: aload_1
    //   910: getfield 193	ag:fd	Z
    //   913: ifeq +10 -> 923
    //   916: iload 5
    //   918: iconst_1
    //   919: ior
    //   920: i2b
    //   921: istore 5
    //   923: aload_1
    //   924: getfield 194	ag:fb	Z
    //   927: ifeq +10 -> 937
    //   930: iload 5
    //   932: iconst_2
    //   933: ior
    //   934: i2b
    //   935: istore 5
    //   937: aload_1
    //   938: getfield 195	ag:e9	Z
    //   941: ifeq +10 -> 951
    //   944: iload 5
    //   946: iconst_4
    //   947: ior
    //   948: i2b
    //   949: istore 5
    //   951: getstatic 31	a3:bE	Lh;
    //   954: getfield 187	h:aG	Lq;
    //   957: iload 5
    //   959: invokevirtual 192	q:do	(I)V
    //   962: getstatic 31	a3:bE	Lh;
    //   965: getfield 187	h:aG	Lq;
    //   968: invokevirtual 196	q:if	()V
    //   971: aload_1
    //   972: getfield 197	a3:D	Z
    //   975: ifeq +13 -> 988
    //   978: aload_1
    //   979: iconst_0
    //   980: putfield 197	a3:D	Z
    //   983: aload_0
    //   984: aload_1
    //   985: invokevirtual 198	a3:if	(Lag;)V
    //   988: aload_1
    //   989: getfield 172	ag:fm	B
    //   992: getstatic 199	ag:dt	B
    //   995: if_icmpeq +148 -> 1143
    //   998: aload_1
    //   999: getfield 172	ag:fm	B
    //   1002: getstatic 200	ag:hX	B
    //   1005: if_icmpeq +138 -> 1143
    //   1008: aload_1
    //   1009: getfield 172	ag:fm	B
    //   1012: getstatic 201	ag:ig	B
    //   1015: if_icmpeq +128 -> 1143
    //   1018: aload_1
    //   1019: getfield 172	ag:fm	B
    //   1022: getstatic 202	ag:eV	B
    //   1025: if_icmpeq +118 -> 1143
    //   1028: aload_1
    //   1029: getfield 172	ag:fm	B
    //   1032: getstatic 203	ag:dV	B
    //   1035: if_icmpeq +108 -> 1143
    //   1038: aload_1
    //   1039: getfield 172	ag:fm	B
    //   1042: getstatic 204	ag:ey	B
    //   1045: if_icmpeq +98 -> 1143
    //   1048: aload_1
    //   1049: getfield 172	ag:fm	B
    //   1052: getstatic 175	ag:d8	B
    //   1055: if_icmpeq +88 -> 1143
    //   1058: aload_1
    //   1059: getfield 172	ag:fm	B
    //   1062: invokestatic 173	ag:l	(B)Z
    //   1065: ifne +78 -> 1143
    //   1068: iconst_0
    //   1069: istore 5
    //   1071: aload_1
    //   1072: bipush 24
    //   1074: invokevirtual 151	a3:a	(B)I
    //   1077: aload_1
    //   1078: bipush 26
    //   1080: invokevirtual 151	a3:a	(B)I
    //   1083: iconst_2
    //   1084: idiv
    //   1085: if_icmpge +58 -> 1143
    //   1088: iconst_m1
    //   1089: getstatic 31	a3:bE	Lh;
    //   1092: bipush 111
    //   1094: invokevirtual 205	h:if	(B)S
    //   1097: dup
    //   1098: istore 5
    //   1100: if_icmpeq +43 -> 1143
    //   1103: getstatic 31	a3:bE	Lh;
    //   1106: getfield 139	h:cJ	Lg;
    //   1109: iload 5
    //   1111: iconst_1
    //   1112: invokevirtual 206	g:a	(SZ)V
    //   1115: getstatic 31	a3:bE	Lh;
    //   1118: iload 5
    //   1120: iconst_1
    //   1121: invokevirtual 207	h:if	(SZ)V
    //   1124: getstatic 31	a3:bE	Lh;
    //   1127: getfield 139	h:cJ	Lg;
    //   1130: iload 5
    //   1132: iconst_0
    //   1133: invokevirtual 206	g:a	(SZ)V
    //   1136: getstatic 31	a3:bE	Lh;
    //   1139: iconst_2
    //   1140: invokevirtual 208	h:c	(B)V
    //   1143: aload_3
    //   1144: athrow
    //   1145: return
    // Local variable table:
    //   start	length	slot	name	signature
    //   0	1146	0	this	a3
    //   0	1146	1	paramag	ag
    //   442	1	2	localException	Exception
    //   798	346	3	localObject	Object
    //   203	928	5	s1	short
    // Exception table:
    //   from	to	target	type
    //   19	95	442	java/lang/Exception
    //   19	95	798	finally
    //   442	451	798	finally
    //   798	799	798	finally
  }
  
  public void jdMethod_if(ag paramag)
  {
    if ((paramag == bE.cZ) && (bE.cJ.jdField_if > a.t) && (bE.aG.jdMethod_int(4421)))
    {
      bE.aG.jdMethod_for(jdMethod_new(paramag.a((byte)16), a.t));
      bE.aG.jdMethod_for(jdMethod_new(paramag.a((byte)24), a.t));
      bE.aG.jdMethod_for(jdMethod_new(paramag.bx, 2));
      bE.aG.jdMethod_for(jdMethod_new(paramag.f, a.t));
      bE.aG.jdMethod_for(jdMethod_new(paramag.ak, a.t));
      bE.aG.jdMethod_do(h.jdMethod_if(10, 127));
      bE.aG.jdMethod_if();
    }
  }
  
  protected void b()
  {
    switch (this.jdField_try)
    {
    case 0: 
      jdMethod_new();
      break;
    case 1: 
      c();
      break;
    case 2: 
      h();
      break;
    case 3: 
      g();
    }
  }
  
  public void jdMethod_for(a3 parama3)
  {
    if ((bE.cJ.jdField_if < 3) || (bE.cZ.jdMethod_else())) {
      return;
    }
    if (bE.aG.jdMethod_int(4411))
    {
      bE.aG.jdMethod_new(jdMethod_new(parama3.t, 2));
      bE.aG.jdMethod_if();
    }
  }
  
  public boolean jdMethod_if(int paramInt1, int paramInt2)
  {
    return h.a(paramInt1, paramInt2, this.aK, this.bA, ag.hF, ag.hE, h.dU, h.fp);
  }
  
  public void a(a3 parama3, byte paramByte1, byte paramByte2, byte paramByte3, byte paramByte4, byte paramByte5, short paramShort, boolean paramBoolean) {}
  
  protected void jdMethod_if(a3 parama3, byte paramByte1, byte paramByte2, byte paramByte3, byte paramByte4, byte paramByte5, short paramShort, boolean paramBoolean)
  {
    this.aD = parama3;
    this.jdField_for = a(paramShort, 0);
    this.z = paramByte1;
    this.jdField_if = paramByte2;
    if (paramShort == 0) {
      bE.a((short)9998, this.aP, this.aM, (byte)0);
    } else {
      bE.a((short)-paramShort, this.aP, this.aM, (byte)0);
    }
    if (paramShort > 0)
    {
      if ((bE.cJ.jdField_if == 2) && (this == bE.cZ) && (paramShort >= a((byte)16))) {
        paramShort = (short)(a((byte)16) - 1);
      }
      if ((!(this instanceof ag)) || (this == bE.cZ)) {
        jdMethod_for((byte)16, paramShort);
      }
      if (this == bE.cZ) {
        if ((bE.cZ.gE) && (g.dD == 2) && (g.dZ == 1) && (!bE.cJ.iJ))
        {
          if (bE.aG.jdMethod_int(3608))
          {
            bE.aG.jdMethod_new(parama3.t);
            bE.aG.jdMethod_if(bE.cZ.O);
            bE.aG.jdMethod_do(bE.cZ.bo);
            bE.aG.jdMethod_new(paramShort);
            bE.aG.jdMethod_do(paramByte1);
            bE.aG.jdMethod_do(bE.cZ.eC);
            bE.aG.jdMethod_if();
          }
        }
        else if (bE.aG.jdMethod_int(4006))
        {
          bE.aG.jdMethod_new(parama3.t);
          bE.aG.jdMethod_if(bE.cZ.O);
          bE.aG.jdMethod_do(bE.cZ.bo);
          bE.aG.jdMethod_new(paramShort);
          bE.aG.jdMethod_do(paramByte1);
          bE.aG.jdMethod_do(bE.cZ.eC);
          bE.aG.jdMethod_if();
        }
      }
    }
    this.T = false;
    if (parama3 != null) {
      if (this.aP + this.aK / 2 < parama3.aP + parama3.aK / 2)
      {
        this.au = 1;
        this.c = -1;
      }
      else
      {
        this.au = 3;
        this.c = 1;
      }
    }
    this.jdField_void = this.aM;
    this.bm = 0;
    this.aE = true;
    this.aC = false;
    switch (paramByte3)
    {
    case 5: 
      this.j = false;
      this.aF = false;
      if (paramByte4 >= 0) {
        this.aN = ((short)paramByte4);
      } else if (this.aN < 30) {
        this.aN = ((short)(this.aN - paramByte4));
      }
      if (this.aN == this.bH) {
        this.ag = 4;
      }
      if ((this.a4 == 112) && (this.bF == 5)) {
        this.bg = ((short)(this.bg + 1));
      } else {
        this.bg = 1;
      }
      this.bc = true;
      break;
    case 4: 
      this.j = false;
      this.aF = false;
      this.bC = paramByte4;
      this.bP = true;
      break;
    case 0: 
      this.h = 0;
      this.j = paramBoolean;
      this.aF = true;
      if (paramByte4 == 0)
      {
        this.h = 0;
        this.g = -10;
        this.B = 4;
      }
      else if (paramByte4 == 1)
      {
        this.h = 0;
        this.g = -16;
        this.B = 4;
        this.aC = true;
      }
      break;
    case 1: 
      this.h = ((short)this.c);
      this.j = paramBoolean;
      this.aF = true;
      if (paramByte4 == 0)
      {
        this.h = ((short)(this.h * 10));
        this.g = -20;
        this.B = 5;
      }
      else if (paramByte4 == 1)
      {
        this.h = ((short)(this.h * 16));
        this.g = -26;
        this.B = 5;
        this.aC = true;
      }
      break;
    case 2: 
      this.h = ((short)this.c);
      this.j = paramBoolean;
      this.aF = true;
      if (paramByte4 == 0)
      {
        this.h = ((short)(this.h * 20));
        this.g = 0;
        this.B = 0;
      }
      else if (paramByte4 == 1)
      {
        this.h = ((short)(this.h * 28));
        this.g = 0;
        this.B = 0;
        this.aC = true;
      }
      this.aG = 0;
      break;
    case 3: 
      this.h = ((short)this.c);
      this.j = paramBoolean;
      this.aF = false;
      if (paramByte4 == 0)
      {
        this.h = ((short)(this.h * 8));
        this.g = 0;
        this.B = 0;
      }
      else if (paramByte4 == 1)
      {
        this.h = ((short)(this.h * 10));
        this.g = 0;
        this.B = 0;
      }
      this.aG = 0;
    }
    if (this.aF)
    {
      this.aB = ((short)(this.aM + this.bA));
      this.aj = new int[5];
      bE.b0.a(54, 0, this.aj);
    }
    else
    {
      this.aj = null;
    }
    if (this.aE)
    {
      this.ay = ((short)(this.aM + this.bA / 3));
      this.ai = new int[5];
      bE.b0.a(paramByte5, 0, this.ai);
    }
    else
    {
      this.ai = null;
    }
    if (this.aC)
    {
      this.aw = ((short)(this.aP + this.aK / 2));
      this.ap = ((short)(this.aM + this.bA));
      this.ab = new int[5];
      bE.b0.a(57, 0, this.ab);
    }
    else
    {
      this.ab = null;
    }
    this.bF = paramByte3;
  }
  
  protected void i()
  {
    if (this.aE)
    {
      bE.b0.a(this.aP - ag.hF + (this.c == -1 ? this.aK / 2 : 0), this.ay - ag.hE, bE.o, this.ai, this.c == -1 ? 2 : 0, false, 0);
      bE.b0.a(this.ai);
      if (this.ai[4] == 0)
      {
        this.ai = null;
        this.aE = false;
      }
    }
  }
  
  protected boolean jdMethod_for()
  {
    if (this.aC)
    {
      bE.b0.a(this.aw - ag.hF, this.ap - ag.hE, bE.o, this.ab, 0, false, 0);
      bE.b0.a(this.ab);
      if (this.ab[4] == 0)
      {
        this.ab = null;
        this.aC = false;
      }
    }
    if (this.aF)
    {
      bE.b0.a(this.aP - ag.hF, this.aB - ag.hE, bE.o, this.aj, this.c == -1 ? 2 : 0, false, 0);
      bE.b0.a(this.aj);
      if ((this.h == 0) || (this.T))
      {
        this.aj = null;
        this.aF = false;
      }
    }
    switch (this.bF)
    {
    case 5: 
      if (a((byte)16) <= 0) {
        this.aN = 0;
      }
      this.aN = ((short)(this.aN - 1));
      if (this.ag > 0)
      {
        if ((this.aP + this.c * this.ag + 1 < 0) || (this.aP + this.c * this.ag + this.aK - 1 > bE.ad)) {
          this.ag = 0;
        } else if ((bE.fJ[bE.cJ.jdMethod_for(this.aP + this.c * this.ag + 1, this.aM + this.aI)] < 0) || (bE.fJ[bE.cJ.jdMethod_for(this.aP + this.c * this.ag + this.aK - 1, this.aM + this.aI)] < 0) || (bE.fJ[bE.cJ.jdMethod_for(this.aP + this.c * this.ag + this.aK / 2 - 1, this.aM + this.aI)] < 0)) {
          this.ag = 0;
        }
        this.aP = ((short)(this.aP + this.c * this.ag));
        this.ag = ((byte)(this.ag - 1));
      }
      return this.aN <= 0;
    case 4: 
      this.bC = ((byte)(this.bC - 1));
      return this.bC <= 0;
    case 0: 
    case 1: 
    case 2: 
    case 3: 
      if (!this.T)
      {
        if ((this.aP + this.h + 1 < 0) || (this.aP + this.h + this.aK - 1 > bE.ad)) {
          this.h = 0;
        } else if ((bE.fJ[bE.cJ.jdMethod_for(this.aP + this.h + 1, this.jdField_void + this.aI)] < 0) || (bE.fJ[bE.cJ.jdMethod_for(this.aP + this.h + this.aK - 1, this.jdField_void + this.aI)] < 0) || (bE.fJ[bE.cJ.jdMethod_for(this.aP + this.h + this.aK / 2 - 1, this.jdField_void + this.aI)] < 0)) {
          this.h = 0;
        }
        this.aP = ((short)(this.aP + this.h));
        this.aM = ((short)(this.aM + this.g));
        this.aM = ((short)(this.aM + this.bm));
        if (this.aM >= this.jdField_void)
        {
          this.aM = this.jdField_void;
        }
        else
        {
          this.g = ((short)(this.g + this.B));
          if (this.g >= 0) {
            this.B = ((short)(this.B - 1));
          } else {
            this.B = ((short)(this.B + 1));
          }
        }
        switch (this.bF)
        {
        case 0: 
        case 1: 
          if (this.h > 0) {
            this.h = ((short)(this.h - 1));
          } else if (this.h < 0) {
            this.h = ((short)(this.h + 1));
          }
          if (this.aM == this.jdField_void)
          {
            this.af.a(1, 0, this.al);
            this.af.a(jdMethod_int((byte)0), 0, this.al);
            this.T = true;
          }
          else
          {
            return false;
          }
          break;
        case 3: 
          this.aG = ((byte)(this.aG - 1));
          if (this.h > 0) {
            this.h = ((short)(this.h - 1));
          } else if (this.h < 0) {
            this.h = ((short)(this.h + 1));
          }
          return (this.h == 0) && (this.aG <= 0);
        case 2: 
          this.aG = ((byte)(this.aG - 1));
          if (this.h > 0) {
            this.h = ((short)(this.h - 4));
          } else if (this.h < 0) {
            this.h = ((short)(this.h + 4));
          }
          if ((this.h == 0) && (this.aG <= 0))
          {
            this.af.a(jdMethod_int((byte)0), 0, this.al);
            this.T = true;
          }
          else
          {
            return false;
          }
          break;
        }
      }
      else
      {
        if ((((this instanceof ar)) && (this.al[4] == 0)) || (((this instanceof ag)) && (bE.b0.jdMethod_if(this.al)) && (this.al[1] == jdMethod_int((byte)0))))
        {
          this.T = false;
          return true;
        }
        return false;
      }
      break;
    }
    return false;
  }
  
  public void jdMethod_int()
  {
    if ((this.bF == 5) && (a((byte)16) > 0))
    {
      bE.fj.setColor(16776960);
      bE.fj.drawString("!", this.aP + 6 - ag.hF, this.aM - 6 - ag.hE + (bE.cJ.jdField_int % 6 == 0 ? -3 : 0), 33);
    }
  }
  
  public void a(x paramx)
  {
    this.af = paramx;
  }
  
  protected byte jdMethod_int(byte paramByte)
  {
    return 0;
  }
  
  protected void jdMethod_new() {}
  
  protected void h() {}
  
  protected void g() {}
  
  protected void c() {}
  
  public void jdMethod_char() {}
  
  public void jdMethod_if(byte paramByte) {}
  
  public void d() {}
  
  public void jdMethod_case() {}
  
  public byte[] jdMethod_do()
  {
    return this.jdField_case;
  }
  
  public void a(byte[] paramArrayOfByte)
  {
    this.jdField_case = paramArrayOfByte;
  }
  
  public void jdMethod_do(byte paramByte, int paramInt)
  {
    int i1 = a(paramByte);
    int i2 = i1 + paramInt;
    jdMethod_if(paramByte, i2);
  }
  
  public void jdMethod_for(byte paramByte, int paramInt)
  {
    if (paramInt <= 0) {
      return;
    }
    int i1 = a(paramByte);
    int i2 = Math.max(0, i1 - paramInt);
    jdMethod_if(paramByte, i2);
    i2 = a(paramByte);
    if ((this == bE.cZ) && (bE.aG.jdMethod_int(4417)))
    {
      bE.aG.jdMethod_for(jdMethod_new(paramByte, 4));
      bE.aG.jdMethod_for(jdMethod_new(i1, 4));
      bE.aG.jdMethod_for(jdMethod_new(i2, 4));
      bE.aG.jdMethod_for(jdMethod_new(paramInt, 4));
      bE.aG.jdMethod_if();
    }
  }
  
  public void a(byte paramByte, int paramInt)
  {
    int i1 = a(paramByte);
    int i2 = i1 - paramInt;
    jdMethod_if(paramByte, i2 <= 0 ? 0 : i2);
  }
  
  public void jdMethod_if(byte paramByte, int paramInt)
  {
    int i1 = 2;
    i1 = (byte)(i1 + ((paramByte == 4) || (paramByte == 0) || (paramByte == 16) || (paramByte == 8) || (paramByte == 50) || (paramByte == 20) || (paramByte == 0) || (paramByte == 4) ? 2 : 0));
    a(this.jdField_case, jdMethod_new(jdMethod_for(paramByte, paramInt), i1), paramByte, i1);
  }
  
  private int jdMethod_for(int paramInt1, int paramInt2)
  {
    paramInt2 = paramInt2 < 0 ? 0 : paramInt2;
    switch (paramInt1)
    {
    case 24: 
      int i1 = a((byte)26);
      if ((i1 > 0) && (paramInt2 > i1)) {
        paramInt2 = i1;
      }
      break;
    case 26: 
      return paramInt2 > 9999 ? 9999 : paramInt2;
    }
    return paramInt2;
  }
  
  public int a(byte paramByte)
  {
    int i1 = 2;
    i1 = (byte)(i1 + ((paramByte == 4) || (paramByte == 0) || (paramByte == 16) || (paramByte == 8) || (paramByte == 50) || (paramByte == 20) || (paramByte == 0) || (paramByte == 4) ? 2 : 0));
    return jdMethod_do(a(this.jdField_case, paramByte, i1), i1);
  }
  
  private void a(byte[] paramArrayOfByte, int paramInt1, int paramInt2, int paramInt3)
  {
    for (int i1 = paramInt3 - 1; i1 >= 0; i1--) {
      paramArrayOfByte[(paramInt2 + i1)] = ((byte)(paramInt1 >> 8 * i1 & 0xFF));
    }
  }
  
  private int a(byte[] paramArrayOfByte, int paramInt1, int paramInt2)
  {
    int i1 = 0;
    for (int i2 = paramInt2 - 1; i2 >= 0; i2--)
    {
      i1 <<= 8;
      i1 += paramArrayOfByte[(i2 + paramInt1)];
      i1 += (paramArrayOfByte[(i2 + paramInt1)] < 0 ? 256 : 0);
    }
    return i1;
  }
  
  private static int jdMethod_if(int paramInt)
  {
    paramInt -= (paramInt >> a.char & 0x55555555);
    paramInt = (paramInt & 0x33333333) + (paramInt >> 2 & 0x33333333);
    paramInt = paramInt + (paramInt >> a.C) & 0xF0F0F0F;
    paramInt += (paramInt >> a.ad);
    paramInt += (paramInt >> a.long);
    return paramInt & 0x3F;
  }
  
  public static int jdMethod_new(int paramInt1, int paramInt2)
  {
    paramInt1 <<= a.char;
    if (((paramInt2 == a.t ? jdMethod_if(paramInt1 & 0xFF00) : jdMethod_if(paramInt1 & 0xFFFF0000)) & 0x1) == a.ac) {
      if (paramInt2 == a.C) {
        paramInt1 |= 0x80000000;
      } else {
        paramInt1 |= 0x8000;
      }
    }
    if (((paramInt2 == a.t ? jdMethod_if(paramInt1 & 0xFF) : jdMethod_if(paramInt1 & 0xFFFF)) & 0x1) == a.ac) {
      paramInt1 |= 0x1;
    }
    return paramInt1;
  }
  
  public static int jdMethod_do(int paramInt1, int paramInt2)
  {
    if (paramInt2 == a.t)
    {
      if (((jdMethod_if(paramInt1 & 0xFF00) & 0x1) == a.ac) || ((jdMethod_if(paramInt1 & 0xFF) & 0x1) == a.ac)) {
        return a.ac;
      }
      return (paramInt1 & 0x7FFE) >> a.char;
    }
    if (((jdMethod_if(paramInt1 & 0xFFFF0000) & 0x1) == a.ac) || ((jdMethod_if(paramInt1 & 0xFFFF) & 0x1) == a.ac)) {
      return a.ac;
    }
    return (paramInt1 & 0x7FFFFFFE) >> a.char;
  }
  
  public static int a(int paramInt1, int paramInt2)
  {
    return paramInt1 * a.t - a.V;
  }
  
  public static int jdMethod_int(int paramInt1, int paramInt2)
  {
   // paramInt1+9999/2
    return (paramInt1 + a.V) / a.t;
  }
}


/* Location:              D:\OneDrive\游戏\客户端SOT觉醒者 - 副本.jar!\a3.class
 * Java compiler version: 1 (45.3)
 * JD-Core Version:       0.7.1
 */